Workbook
Name BÜRO: '4. Reduktionsfaktorer, LENI-tal'!$Q$13:$Q$23
Name Faktorer: #REF!
Name FromArray_1: _xlfn.ANCHORARRAY('[1]4. Reduktionsfaktorer, LENI-tal'!$S$13)
Name FromArray_1: _xlfn.ANCHORARRAY('4. Reduktionsfaktorer, LENI-tal'!$S$13)
Name FromArray_2: _xlfn.ANCHORARRAY('4. Reduktionsfaktorer, LENI-tal'!$H$13)
Name HOSPITAL: '4. Reduktionsfaktorer, LENI-tal'!$T$13:$T$20
Name IDRETTSHALL: '4. Reduktionsfaktorer, LENI-tal'!$S$13:$S$17
Name INDUSTRI: '4. Reduktionsfaktorer, LENI-tal'!$U$13:$U$21
Name INDUSTRIE: '4. Reduktionsfaktorer, LENI-tal'!$U$13:$U$21
Name INDUSTRY: '4. Reduktionsfaktorer, LENI-tal'!$U$13:$U$21
Name KONTOR: '4. Reduktionsfaktorer, LENI-tal'!$Q$13:$Q$23
Name KRANKENHAUS: '4. Reduktionsfaktorer, LENI-tal'!$T$13:$T$20
Name OFFICE: '4. Reduktionsfaktorer, LENI-tal'!$Q$13:$Q$23
Name Omvandlingsfaktorer: #REF!
Name SCHOOL_AND_RESTAURANT: '4. Reduktionsfaktorer, LENI-tal'!$R$13:$R$21
Name SCHULE_UND_RESTAURANT: '4. Reduktionsfaktorer, LENI-tal'!$R$13:$R$21
Name SJUKHUS: '4. Reduktionsfaktorer, LENI-tal'!$T$13:$T$20
Name SKOLA: #REF!
Name SKOLA_OCH_RESTAURANG: '4. Reduktionsfaktorer, LENI-tal'!$R$13:$R$21
Name SKOLE_OG_RESTAURANT: '4. Reduktionsfaktorer, LENI-tal'!$R$13:$R$21
Name SPORTHALL: '4. Reduktionsfaktorer, LENI-tal'!$S$13:$S$17
Name SPORTHALLAR: #REF!
Name SPORTHALLE: '4. Reduktionsfaktorer, LENI-tal'!$S$13:$S$17
Name SPORTS_HALL: '4. Reduktionsfaktorer, LENI-tal'!$S$13:$S$17
Name Språkval: Förutsättningar!$V$18
Name Språkval: Förutsättningar!$V$18
Name STYRNING: #REF!
Name SYKEHUS: '4. Reduktionsfaktorer, LENI-tal'!$T$13:$T$20
Name test: Sammanfattning!$B:$V

Sheet 1. Introduktion
A1: (PW: LCC)
G2: LCC-kalkyl för upphandling av inomhusbelysning
G3: Version 3.0
G4: Datum: 2024-12-17
B9: Introduktion
B11: Generella instruktioner kring hur verktyget används.
B14: Versionsinformation
B16: Upphandlingsmyndighetens LCC-verktyg har utvecklats i omgångar sedan 2009.
B19: Ändringar i senaste versionen (v 3.1) av LCC-verktyg Inomhusbelysning: Flik 1 har uppdaterats med denna versionsinformation och information om nytt lösenordsskydd, texter är genomgångna och uppdaterade. Flik 2 (4 alt) är nu utan makrofunktion att lägga till/ta bort rumstyper och armaturtyper. Ny funktion med förinställda byggnadstyper och rumstyper som hämtar reduktionsfaktorer från flik 4. Observera att funktionalitet förloras om värdet skrivs över. (Kursiverat är ändrat sedan v 3.0) Flik 3 är texter genomgångna och uppdaterade. Flik 4 har uppdaterats med riktlinjer för installerad effekt och jämförelsetal energianvändning (LENI-tal) enligt Ljus & Rum utgåva 4 (2022). Flik 5 har uppdaterats med aktuella beräkningsfaktorer klimat samt källor.
H23: Vad är LCC?
H24: LCC står för "Life Cycle Costs" - livscykelkostnader. Med hjälp av en LCC-beräkning erhålls en totalbild över varans, tjänstens eller anläggningens kostnader under hela dess nyttjandetid. Jämförelser mellan olika produktalternativ och lösningar kan göras. Livscykelkostnadsperspektivet kan med fördel användas i flera delar av inköpsprocessen och även i det strategiska arbetet med organisationens budget.
H25: Läs mer om LCC på Upphandlingsmyndighetens webbplats
H27: Hur ska jag använda detta LCC-verktyg?
H28: Detta LCC-verktyg är specifikt utvecklat att användas vid upphandling av inomhusbelysning. Verktyget kan med fördel användas både i behovsanalysen, vid kravställande och i anbudsutvärderingen. I behovsanalysen kan verktyget användas för att i ett tidigt skede få en översikt över vilka typer av kostnader som förekommer under nyttjandetiden och hur stora dessa kostnader är. För en belysningsanläggning utgör exempelvis driftskostnaden för energi en stor kostnadspost. Detta kan till exempel testas med olika scenarier för energiprisökning, eller med olika styrfunktioner. Att använda verktyget på det sättet ökar medvetenheten i organisationen och kan vara ett bra underlag till viktiga vägval inför upphandlingen. Använd gärna kalkylparametrarna som en checklista, exempelvis inför leverantörsdialogen. När LCC-beräkning ställs som krav i upphandlingen måste förfrågningsunderlaget beskriva de parametrar som ska ingå i beräkningen, hur dessa ska dokumenteras och vilka mätmetoder som ska användas. Använd gärna kriteriet "belysningsanläggningens livscykelkostnad (LCC)" som kan laddas hem genom Upphandlingsmyndighetens kriterietjänst. En tumregel är att vid kravställande endast ta med de stora kostnadsposterna eller de kostnader som förväntas skilja sig åt mellan olika leverantörer.
B29: Lösenordsskydd Varje flik i Excelfilen är skyddad med ett lösenord, för att förhindra oavsiktliga förändringar i LCC-kalkylen. - För att låsa upp välj Granska > Ta bort bladets skydd. | H29: Vid anbudsutvärdering vägs livscykelkostnaden in som en parameter för bedömning av det ekonomiskt mest fördelaktiga anbudet. Kvalitativa krav på belysningsanläggningen, såsom ljuskvalitet, ingår inte i kalkylen utan måste kravställas i förfrågningsunderlaget. I detta LCC-verktyg finns även möjlighet till jämförelse av alternativens klimatpåverkan från energianvändningen under nyttjandetiden.
B30: - Lösenordet är LCC.
H31: Hur är LCC-verktyget uppbyggt?
H32: Verktyget består av 7 flikar: 1. Introduktion: generella instruktioner kring hur verktyget används. 2. LCC-kalkyl A1-4: Fyra stycken kalkylblad där LCC-beräkningen utförs med standardiserade parametrar. Ett blad används per anläggning. 3. Kalkylparametrar: Samlade instruktioner kring vad kalkylparametrarna innebär och vad som ska ingå. 4. Reduktionsfaktorer styrning: reduktionsfaktorer för belysningsstyrning, hämtade från Belysningsbranschens handbok "Ljus & Rum". 5. Beräkningsfaktorer klimatpåverkan: frivilliga indata för att kunna beräkna klimatpåverkan från elenergi. 6. Resultat: visuell översikt över LCC-beräkningens resultat. 7. Svarsformulär: svarsformulär som leverantören bifogar anbudet. Beskrivning av anläggningen med rumstyper och storlek på dessa måste göras i förfrågningsunderlaget. Beställaren (upphandlande myndighet) anger kalkylförutsättningar och information kring användning; detta utgör grunden för beräkningen. Läs mer om kalkylförutsättningar och ekonomiska parametrar på länken under rubriken Vad är LCC ovan. Anbudsgivaren fyller i resterande uppgifter i kalkylbladet (indata) enligt de standarder eller instruktioner som anges. Kostnaderna anges utan moms. I kolumnerna anges de olika rumstyper som förekommer i belysningsanläggningen enligt beställarens beskrivning i förfrågningsunderlaget. Rummen summeras i slutet och LCC-resultatet för hela anläggningen visas. Ett kalkylblad per anläggning används. Alternativa investeringslösningar, om sådana finns, anges i kalkylblad A2-A4. Anbudsgivaren fyller i svarsformuläret (ett formulär per typrum) och bifogar den till beställaren. Beställaren kan sedan föra in varje anbudsgivares uppgifter i ett nytt kalkylblad för att kunna jämföra alla anbud i resultatfliken. Beställaren kan även använda ett av kalkylbladen A1-A4 för att fylla i information kring befintlig anläggning om sådan finns; detta för att tydliggöra förbättringarna med en ny eller renoverad anläggning. LCC-kalkylerna är baserade på nuvärdesmetoden för att kunna omräkna framtida kostnader till dagens värde. Omräkningsfaktorer till nuvärde är inkluderade i formlerna. Kalkylränta, elpris och användningstid är exempel på parametrar som kan variera och som måste beslutas i den upphandlande organisationen. Kostnadsbilden påverkas beroende på valet av dessa parametrar, exempelvis innebär en hög ränta att pengarnas värde sjunker under kalkylperioden och vid låg ränta behåller pengarna sitt värde. En lång användningstid gör att driftskostnadernas betydelse ökar i kalkylen. För att få en förståelse för effekten på slutresultatet vid olika scenarier, t.ex. energiprisökning, kan kalkylen testas med ett antal olika värden.
H33: Kontakt
H34: Upphandlingsmyndigheten utvecklar och förvaltar LCC-verktygen som är frivilliga att använda inom såväl offentlig som privat sektor. Upphandlingsmyndigheten står för innehållet i denna version. Eventuella ändringar görs på eget ansvar. Vid frågor om verktyget kan du kontakta oss via vår frågeportal på www.upphandlingsmyndigheten.se.

Sheet Förutsättningar
A1: =NOW() -> 46147.726
U18: Region | V18: SE
P19: {=IFERROR( INDEX( tblStrings[], MATCH( 1, (tblStrings[Cell]=SUBSTITUTE(CELL("adress",INDIRECT("RC",FALSE)),"$","")) * (tblStrings[Sheet]=AllStrings!$C$354), 0 ), MATCH(Språkval, tblStrings[#Headers], 0) ), "" )} -> Kalkylförutsättningar
P20: {=IFERROR( INDEX( tblStrings[], MATCH( 1, (tblStrings[Cell]=SUBSTITUTE(CELL("adress",INDIRECT("RC",FALSE)),"$","")) * (tblStrings[Sheet]=AllStrings!$C$354), 0 ), MATCH(Språkval, tblStrings[#Headers], 0) ), "" )} -> Projekt:
P21: {=IFERROR( INDEX( tblStrings[], MATCH( 1, (tblStrings[Cell]=SUBSTITUTE(CELL("adress",INDIRECT("RC",FALSE)),"$","")) * (tblStrings[Sheet]=AllStrings!$C$354), 0 ), MATCH(Språkval, tblStrings[#Headers], 0) ), "" )} -> Datum:
P22: {=IFERROR( INDEX( tblStrings[], MATCH( 1, (tblStrings[Cell]=SUBSTITUTE(CELL("adress",INDIRECT("RC",FALSE)),"$","")) * (tblStrings[Sheet]=AllStrings!$C$354), 0 ), MATCH(Språkval, tblStrings[#Headers], 0) ), "" )} -> Handläggare:
O24: 1.1 | P24: {=IFERROR( INDEX( tblStrings[], MATCH( 1, (tblStrings[Cell]=SUBSTITUTE(CELL("adress",INDIRECT("RC",FALSE)),"$","")) * (tblStrings[Sheet]=AllStrings!$C$354), 0 ), MATCH(Språkval, tblStrings[#Headers], 0) ), "" )} -> Tid kalkylen omfattar | U24: 20 | V24: {=IFERROR( INDEX( tblStrings[], MATCH( 1, (tblStrings[Cell]=SUBSTITUTE(CELL("adress",INDIRECT("RC",FALSE)),"$","")) * (tblStrings[Sheet]=AllStrings!$C$354), 0 ), MATCH(Språkval, tblStrings[#Headers], 0) ), "" )} -> år
O25: 1.2 | P25: {=IFERROR( INDEX( tblStrings[], MATCH( 1, (tblStrings[Cell]=SUBSTITUTE(CELL("adress",INDIRECT("RC",FALSE)),"$","")) * (tblStrings[Sheet]=AllStrings!$C$354), 0 ), MATCH(Språkval, tblStrings[#Headers], 0) ), "" )} -> Kalkylränta | U25: 5 | V25: %
O26: 1.3 | P26: {=IFERROR( INDEX( tblStrings[], MATCH( 1, (tblStrings[Cell]=SUBSTITUTE(CELL("adress",INDIRECT("RC",FALSE)),"$","")) * (tblStrings[Sheet]=AllStrings!$C$354), 0 ), MATCH(Språkval, tblStrings[#Headers], 0) ), "" )} -> Elpris | U26: =IF( D26="", _xlfn.XLOOKUP(Språkval, tblDefaults[Region],tblDefaults[Price/kWh]), D26 ) -> 3 | V26: {=IFERROR( INDEX( tblStrings[], MATCH( 1, (tblStrings[Cell]=SUBSTITUTE(CELL("adress",INDIRECT("RC",FALSE)),"$","")) * (tblStrings[Sheet]=AllStrings!$C$354), 0 ), MATCH(Språkval, tblStrings[#Headers], 0) ), "" )} -> kr/kWh
O27: 1.4 | P27: {=IFERROR( INDEX( tblStrings[], MATCH( 1, (tblStrings[Cell]=SUBSTITUTE(CELL("adress",INDIRECT("RC",FALSE)),"$","")) * (tblStrings[Sheet]=AllStrings!$C$354), 0 ), MATCH(Språkval, tblStrings[#Headers], 0) ), "" )} -> Årlig prisförändring energi (frivillig) | U27: 2 | V27: %
O28: 1.5 | P28: {=IFERROR( INDEX( tblStrings[], MATCH( 1, (tblStrings[Cell]=SUBSTITUTE(CELL("adress",INDIRECT("RC",FALSE)),"$","")) * (tblStrings[Sheet]=AllStrings!$C$354), 0 ), MATCH(Språkval, tblStrings[#Headers], 0) ), "" )} -> Klimatpåverkan energianvändning (frivillig) | U28: =IF( D28="", _xlfn.XLOOKUP(Språkval, tblDefaults[Region],tblDefaults[CO2_kg_kWh]), D28 ) -> 0.02 | V28: {=IFERROR( INDEX( tblStrings[], MATCH( 1, (tblStrings[Cell]=SUBSTITUTE(CELL("adress",INDIRECT("RC",FALSE)),"$","")) * (tblStrings[Sheet]=AllStrings!$C$354), 0 ), MATCH(Språkval, tblStrings[#Headers], 0) ), "" )} -> kgCO₂/kwh
O29: 1.6 | P29: {=IFERROR( INDEX( tblStrings[], MATCH( 1, (tblStrings[Cell]=SUBSTITUTE(CELL("adress",INDIRECT("RC",FALSE)),"$","")) * (tblStrings[Sheet]=AllStrings!$C$354), 0 ), MATCH(Språkval, tblStrings[#Headers], 0) ), "" )} -> Drifttid | U29: 4000 | V29: {=IFERROR( INDEX( tblStrings[], MATCH( 1, (tblStrings[Cell]=SUBSTITUTE(CELL("adress",INDIRECT("RC",FALSE)),"$","")) * (tblStrings[Sheet]=AllStrings!$C$354), 0 ), MATCH(Språkval, tblStrings[#Headers], 0) ), "" )} -> h/år

Sheet 1. LCC Befintlig Installation
C2: LCC-kalkyl | E2: Befintlig Installation
C4: Kalkylförutsättningar
C5: PROJEKT: | F5: =Förutsättningar!S20 -> 0
C6: DATUM: | F6: =Förutsättningar!S21 -> 0
C7: HANDLÄGGARE: | F7: =Förutsättningar!S22 -> 0
B9: 1.1 | C9: Tid kalkylen omfattar | H9: =Förutsättningar!U24 -> 20 | I9: år
B10: 1.2 | C10: Kalkylränta | H10: =Förutsättningar!U25 -> 5
B11: 1.3 | C11: Elpris | H11: =Förutsättningar!U26 -> 3 | I11: kr/kWh
B12: 1.4 | C12: Årlig prisförändring energi (frivillig) | H12: =Förutsättningar!U27 -> 2
B13: 1.5 | C13: Klimatpåverkan energianvändning (frivillig) | H13: =Förutsättningar!U28 -> 0.02 | I13: kgCO2/kwh
B14: 1.6 | C14: Drifttid | H14: =Förutsättningar!U29 -> 4000 | I14: h/år
C16: {=IFERROR( INDEX( tblStrings[], MATCH(SUBSTITUTE(CELL("adress",C16),"$",""), tblStrings[Cell], 0), MATCH(Språkval, tblStrings[#Headers], 0) ), "" )} -> Beskrivning av anläggningen och belysningsförslag
C18: {=IFERROR( INDEX( tblStrings[], MATCH(SUBSTITUTE(CELL("adress",C18),"$",""), tblStrings[Cell], 0), MATCH(Språkval, tblStrings[#Headers], 0) ), "" )} -> BESKRIVNING AV ANLÄGGNINGEN
C19: {=IFERROR( INDEX( tblStrings[], MATCH( 1, (tblStrings[Cell]=SUBSTITUTE(CELL("adress",INDIRECT("RC",FALSE)),"$","")) * (tblStrings[Sheet]=AllStrings!$C$433), 0 ), MATCH(Språkval, tblStrings[#Headers], 0) ), )} -> Byggnadstyp
C20: {=IFERROR( INDEX( tblStrings[], MATCH( 1, (tblStrings[Cell]=SUBSTITUTE(CELL("adress",INDIRECT("RC",FALSE)),"$","")) * (tblStrings[Sheet]=AllStrings!$C$433), 0 ), MATCH(Språkval, tblStrings[#Headers], 0) ), )} -> Byggnadstyp hjälprad | I20: =SUBSTITUTE(I19," ","_") | J20: =SUBSTITUTE(J19," ","_") | K20: =SUBSTITUTE(K19," ","_") | L20: =SUBSTITUTE(L19," ","_") | M20: =SUBSTITUTE(M19," ","_") | N20: =SUBSTITUTE(N19," ","_") | O20: =SUBSTITUTE(O19," ","_") | P20: =SUBSTITUTE(P19," ","_") | ... R20: =SUBSTITUTE(R19," ","_")
C21: {=IFERROR( INDEX( tblStrings[], MATCH( 1, (tblStrings[Cell]=SUBSTITUTE(CELL("adress",INDIRECT("RC",FALSE)),"$","")) * (tblStrings[Sheet]=AllStrings!$C$433), 0 ), MATCH(Språkval, tblStrings[#Headers], 0) ), )} -> Rumstyp (välj byggnadstyp ovan för att få lista med giltiga rumstyper)
C22: {=IFERROR( INDEX( tblStrings[], MATCH( 1, (tblStrings[Cell]=SUBSTITUTE(CELL("adress",INDIRECT("RC",FALSE)),"$","")) * (tblStrings[Sheet]=AllStrings!$C$433), 0 ), MATCH(Språkval, tblStrings[#Headers], 0) ), )} -> Rumsbeteckning
C23: {=IFERROR( INDEX( tblStrings[], MATCH( 1, (tblStrings[Cell]=SUBSTITUTE(CELL("adress",INDIRECT("RC",FALSE)),"$","")) * (tblStrings[Sheet]=AllStrings!$C$433), 0 ), MATCH(Språkval, tblStrings[#Headers], 0) ), )} -> Antal rum av samma typ | H23: {=IFERROR( INDEX( tblStrings[], MATCH( 1, (tblStrings[Cell]=SUBSTITUTE(CELL("adress",INDIRECT("RC",FALSE)),"$","")) * (tblStrings[Sheet]=AllStrings!$C$433), 0 ), MATCH(Språkval, tblStrings[#Headers], 0) ), )} -> stk
C24: {=IFERROR( INDEX( tblStrings[], MATCH( 1, (tblStrings[Cell]=SUBSTITUTE(CELL("adress",INDIRECT("RC",FALSE)),"$","")) * (tblStrings[Sheet]=AllStrings!$C$433), 0 ), MATCH(Språkval, tblStrings[#Headers], 0) ), )} -> Antal kvadratmeter | H24: {=IFERROR( INDEX( tblStrings[], MATCH( 1, (tblStrings[Cell]=SUBSTITUTE(CELL("adress",INDIRECT("RC",FALSE)),"$","")) * (tblStrings[Sheet]=AllStrings!$C$433), 0 ), MATCH(Språkval, tblStrings[#Headers], 0) ), )} -> m2/rum
C25: {=IFERROR( INDEX( tblStrings[], MATCH(SUBSTITUTE(CELL("adress",C25),"$",""), tblStrings[Cell], 0), MATCH(Språkval, tblStrings[#Headers], 0) ), "" )} -> BELYSNINGSFÖRSLAG
C26: {=IFERROR( INDEX( tblStrings[], MATCH( 1, (tblStrings[Cell]=SUBSTITUTE(CELL("adress",INDIRECT("RC",FALSE)),"$","")) * (tblStrings[Sheet]=AllStrings!$C$433), 0 ), MATCH(Språkval, tblStrings[#Headers], 0) ), )} -> Armaturbeteckning
B27: 2.1 | C27: {=IFERROR( INDEX( tblStrings[], MATCH( 1, (tblStrings[Cell]=SUBSTITUTE(CELL("adress",INDIRECT("RC",FALSE)),"$","")) * (tblStrings[Sheet]=AllStrings!$C$433), 0 ), MATCH(Språkval, tblStrings[#Headers], 0) ), )} -> Antal armaturer | H27: {=IFERROR( INDEX( tblStrings[], MATCH( 1, (tblStrings[Cell]=SUBSTITUTE(CELL("adress",INDIRECT("RC",FALSE)),"$","")) * (tblStrings[Sheet]=AllStrings!$C$433), 0 ), MATCH(Språkval, tblStrings[#Headers], 0) ), )} -> stk
B28: 2.2 | C28: {=IFERROR( INDEX( tblStrings[], MATCH( 1, (tblStrings[Cell]=SUBSTITUTE(CELL("adress",INDIRECT("RC",FALSE)),"$","")) * (tblStrings[Sheet]=AllStrings!$C$433), 0 ), MATCH(Språkval, tblStrings[#Headers], 0) ), )} -> Armaturpris | H28: {=IFERROR( INDEX( tblStrings[], MATCH( 1, (tblStrings[Cell]=SUBSTITUTE(CELL("adress",INDIRECT("RC",FALSE)),"$","")) * (tblStrings[Sheet]=AllStrings!$C$433), 0 ), MATCH(Språkval, tblStrings[#Headers], 0) ), )} -> kr/stk
B29: 2.3 | C29: {=IFERROR( INDEX( tblStrings[], MATCH( 1, (tblStrings[Cell]=SUBSTITUTE(CELL("adress",INDIRECT("RC",FALSE)),"$","")) * (tblStrings[Sheet]=AllStrings!$C$433), 0 ), MATCH(Språkval, tblStrings[#Headers], 0) ), )} -> Material- och arbetskostnader armatur | H29: {=IFERROR( INDEX( tblStrings[], MATCH( 1, (tblStrings[Cell]=SUBSTITUTE(CELL("adress",INDIRECT("RC",FALSE)),"$","")) * (tblStrings[Sheet]=AllStrings!$C$433), 0 ), MATCH(Språkval, tblStrings[#Headers], 0) ), )} -> kr
B30: 2.4 | C30: {=IFERROR( INDEX( tblStrings[], MATCH( 1, (tblStrings[Cell]=SUBSTITUTE(CELL("adress",INDIRECT("RC",FALSE)),"$","")) * (tblStrings[Sheet]=AllStrings!$C$433), 0 ), MATCH(Språkval, tblStrings[#Headers], 0) ), )} -> Effekt per armatur, inkl. driftsförluster | H30: {=IFERROR( INDEX( tblStrings[], MATCH( 1, (tblStrings[Cell]=SUBSTITUTE(CELL("adress",INDIRECT("RC",FALSE)),"$","")) * (tblStrings[Sheet]=AllStrings!$C$433), 0 ), MATCH(Språkval, tblStrings[#Headers], 0) ), )} -> W/stk
B31: 2.5 | C31: {=IFERROR( INDEX( tblStrings[], MATCH( 1, (tblStrings[Cell]=SUBSTITUTE(CELL("adress",INDIRECT("RC",FALSE)),"$","")) * (tblStrings[Sheet]=AllStrings!$C$433), 0 ), MATCH(Språkval, tblStrings[#Headers], 0) ), )} -> Typ av styrning
B32: 2.6 | C32: {=IFERROR( INDEX( tblStrings[], MATCH( 1, (tblStrings[Cell]=SUBSTITUTE(CELL("adress",INDIRECT("RC",FALSE)),"$","")) * (tblStrings[Sheet]=AllStrings!$C$433), 0 ), MATCH(Språkval, tblStrings[#Headers], 0) ), )} -> Reduktionsfaktor manuell styrning | H32: {=IFERROR( INDEX( tblStrings[], MATCH( 1, (tblStrings[Cell]=SUBSTITUTE(CELL("adress",INDIRECT("RC",FALSE)),"$","")) * (tblStrings[Sheet]=RIGHT(CELL("filnamn"),LEN(CELL("filnamn"))-SEARCH("]",CELL("filnamn")))), 0 ), MATCH(Språkval, tblStrings[#Headers], 0) ), "" )} | I32: {=IFERROR(_xlfn.IFS(I$19='4. Reduktionsfaktorer, LENI-tal'!$Q$12,INDEX('4. Reduktionsfaktorer, LENI-tal'!$H$13:$O$23,MATCH(I$21,'4. Reduktionsfaktorer, LENI-tal'!$H$13:$H$23,0),3), I$19='4. Reduktionsfaktorer, LENI-tal'!$R$12,INDEX('4. Reduktionsfaktorer, LENI-tal'!$H$24:$O$32,MATCH(I$21,'4. Reduktionsfaktorer, LENI-tal'!$H$24:$H$32,0),3), I$19='4. Reduktionsfaktorer, LENI-tal'!$S$12,INDEX('4. Reduktionsfaktorer, LENI-tal'!$H$33:$O$37,MATCH(I$21,'4. Reduktionsfaktorer, LENI-tal'!$H$33:$H$37,0),3), I$19='4. Reduktionsfaktorer, LENI-tal'!$T$12,INDEX('4. Reduktionsfaktorer, LENI-tal'!$H$38:$O$45,MATCH(I$21,'4. Reduktionsfaktorer, LENI-tal'!$H$38:$H$45,0),3), I$19='4. Reduktionsfaktorer, LENI-tal'!$U$12,INDEX('4. Reduktionsfaktorer, LENI-tal'!$H$46:$O$54,MATCH(I$21,'4. Reduktionsfaktorer, LENI-tal'!$H$46:$H$54,0),3)), IFERROR( INDEX( tblStrings[], MATCH( 1, (tblStrings[[Cell]:[Cell]]=AllStrings!$D$350) * (tblStrings[[Sheet]:[Sheet]]=AllStrings!$C$433), 0 ), MATCH(Språkval, tblStrings[#Headers], 0) ), ))} -> Fyll i byggnads- och rumstyp ovan | J32: {=IFERROR(_xlfn.IFS(J$19='4. Reduktionsfaktorer, LENI-tal'!$Q$12,INDEX('4. Reduktionsfaktorer, LENI-tal'!$H$13:$O$23,MATCH(J$21,'4. Reduktionsfaktorer, LENI-tal'!$H$13:$H$23,0),3), J$19='4. Reduktionsfaktorer, LENI-tal'!$R$12,INDEX('4. Reduktionsfaktorer, LENI-tal'!$H$24:$O$32,MATCH(J$21,'4. Reduktionsfaktorer, LENI-tal'!$H$24:$H$32,0),3), J$19='4. Reduktionsfaktorer, LENI-tal'!$S$12,INDEX('4. Reduktionsfaktorer, LENI-tal'!$H$33:$O$37,MATCH(J$21,'4. Reduktionsfaktorer, LENI-tal'!$H$33:$H$37,0),3), J$19='4. Reduktionsfaktorer, LENI-tal'!$T$12,INDEX('4. Reduktionsfaktorer, LENI-tal'!$H$38:$O$45,MATCH(J$21,'4. Reduktionsfaktorer, LENI-tal'!$H$38:$H$45,0),3), J$19='4. Reduktionsfaktorer, LENI-tal'!$U$12,INDEX('4. Reduktionsfaktorer, LENI-tal'!$H$46:$O$54,MATCH(J$21,'4. Reduktionsfaktorer, LENI-tal'!$H$46:$H$54,0),3)), IFERROR( INDEX( tblStrings[], MATCH( 1, (tblStrings[[Cell]:[Cell]]=AllStrings!$D$350) * (tblStrings[[Sheet]:[Sheet]]=AllStrings!$C$433), 0 ), MATCH(Språkval, tblStrings[#Headers], 0) ), ))} -> Fyll i byggnads- och rumstyp ovan | K32: {=IFERROR(_xlfn.IFS(K$19='4. Reduktionsfaktorer, LENI-tal'!$Q$12,INDEX('4. Reduktionsfaktorer, LENI-tal'!$H$13:$O$23,MATCH(K$21,'4. Reduktionsfaktorer, LENI-tal'!$H$13:$H$23,0),3), K$19='4. Reduktionsfaktorer, LENI-tal'!$R$12,INDEX('4. Reduktionsfaktorer, LENI-tal'!$H$24:$O$32,MATCH(K$21,'4. Reduktionsfaktorer, LENI-tal'!$H$24:$H$32,0),3), K$19='4. Reduktionsfaktorer, LENI-tal'!$S$12,INDEX('4. Reduktionsfaktorer, LENI-tal'!$H$33:$O$37,MATCH(K$21,'4. Reduktionsfaktorer, LENI-tal'!$H$33:$H$37,0),3), K$19='4. Reduktionsfaktorer, LENI-tal'!$T$12,INDEX('4. Reduktionsfaktorer, LENI-tal'!$H$38:$O$45,MATCH(K$21,'4. Reduktionsfaktorer, LENI-tal'!$H$38:$H$45,0),3), K$19='4. Reduktionsfaktorer, LENI-tal'!$U$12,INDEX('4. Reduktionsfaktorer, LENI-tal'!$H$46:$O$54,MATCH(K$21,'4. Reduktionsfaktorer, LENI-tal'!$H$46:$H$54,0),3)), IFERROR( INDEX( tblStrings[], MATCH( 1, (tblStrings[[Cell]:[Cell]]=AllStrings!$D$350) * (tblStrings[[Sheet]:[Sheet]]=AllStrings!$C$433), 0 ), MATCH(Språkval, tblStrings[#Headers], 0) ), ))} -> Fyll i byggnads- och rumstyp ovan | L32: {=IFERROR(_xlfn.IFS(L$19='4. Reduktionsfaktorer, LENI-tal'!$Q$12,INDEX('4. Reduktionsfaktorer, LENI-tal'!$H$13:$O$23,MATCH(L$21,'4. Reduktionsfaktorer, LENI-tal'!$H$13:$H$23,0),3), L$19='4. Reduktionsfaktorer, LENI-tal'!$R$12,INDEX('4. Reduktionsfaktorer, LENI-tal'!$H$24:$O$32,MATCH(L$21,'4. Reduktionsfaktorer, LENI-tal'!$H$24:$H$32,0),3), L$19='4. Reduktionsfaktorer, LENI-tal'!$S$12,INDEX('4. Reduktionsfaktorer, LENI-tal'!$H$33:$O$37,MATCH(L$21,'4. Reduktionsfaktorer, LENI-tal'!$H$33:$H$37,0),3), L$19='4. Reduktionsfaktorer, LENI-tal'!$T$12,INDEX('4. Reduktionsfaktorer, LENI-tal'!$H$38:$O$45,MATCH(L$21,'4. Reduktionsfaktorer, LENI-tal'!$H$38:$H$45,0),3), L$19='4. Reduktionsfaktorer, LENI-tal'!$U$12,INDEX('4. Reduktionsfaktorer, LENI-tal'!$H$46:$O$54,MATCH(L$21,'4. Reduktionsfaktorer, LENI-tal'!$H$46:$H$54,0),3)), IFERROR( INDEX( tblStrings[], MATCH( 1, (tblStrings[[Cell]:[Cell]]=AllStrings!$D$350) * (tblStrings[[Sheet]:[Sheet]]=AllStrings!$C$433), 0 ), MATCH(Språkval, tblStrings[#Headers], 0) ), ))} -> Fyll i byggnads- och rumstyp ovan | M32: {=IFERROR(_xlfn.IFS(M$19='4. Reduktionsfaktorer, LENI-tal'!$Q$12,INDEX('4. Reduktionsfaktorer, LENI-tal'!$H$13:$O$23,MATCH(M$21,'4. Reduktionsfaktorer, LENI-tal'!$H$13:$H$23,0),3), M$19='4. Reduktionsfaktorer, LENI-tal'!$R$12,INDEX('4. Reduktionsfaktorer, LENI-tal'!$H$24:$O$32,MATCH(M$21,'4. Reduktionsfaktorer, LENI-tal'!$H$24:$H$32,0),3), M$19='4. Reduktionsfaktorer, LENI-tal'!$S$12,INDEX('4. Reduktionsfaktorer, LENI-tal'!$H$33:$O$37,MATCH(M$21,'4. Reduktionsfaktorer, LENI-tal'!$H$33:$H$37,0),3), M$19='4. Reduktionsfaktorer, LENI-tal'!$T$12,INDEX('4. Reduktionsfaktorer, LENI-tal'!$H$38:$O$45,MATCH(M$21,'4. Reduktionsfaktorer, LENI-tal'!$H$38:$H$45,0),3), M$19='4. Reduktionsfaktorer, LENI-tal'!$U$12,INDEX('4. Reduktionsfaktorer, LENI-tal'!$H$46:$O$54,MATCH(M$21,'4. Reduktionsfaktorer, LENI-tal'!$H$46:$H$54,0),3)), IFERROR( INDEX( tblStrings[], MATCH( 1, (tblStrings[[Cell]:[Cell]]=AllStrings!$D$350) * (tblStrings[[Sheet]:[Sheet]]=AllStrings!$C$433), 0 ), MATCH(Språkval, tblStrings[#Headers], 0) ), ))} -> Fyll i byggnads- och rumstyp ovan | N32: {=IFERROR(_xlfn.IFS(N$19='4. Reduktionsfaktorer, LENI-tal'!$Q$12,INDEX('4. Reduktionsfaktorer, LENI-tal'!$H$13:$O$23,MATCH(N$21,'4. Reduktionsfaktorer, LENI-tal'!$H$13:$H$23,0),3), N$19='4. Reduktionsfaktorer, LENI-tal'!$R$12,INDEX('4. Reduktionsfaktorer, LENI-tal'!$H$24:$O$32,MATCH(N$21,'4. Reduktionsfaktorer, LENI-tal'!$H$24:$H$32,0),3), N$19='4. Reduktionsfaktorer, LENI-tal'!$S$12,INDEX('4. Reduktionsfaktorer, LENI-tal'!$H$33:$O$37,MATCH(N$21,'4. Reduktionsfaktorer, LENI-tal'!$H$33:$H$37,0),3), N$19='4. Reduktionsfaktorer, LENI-tal'!$T$12,INDEX('4. Reduktionsfaktorer, LENI-tal'!$H$38:$O$45,MATCH(N$21,'4. Reduktionsfaktorer, LENI-tal'!$H$38:$H$45,0),3), N$19='4. Reduktionsfaktorer, LENI-tal'!$U$12,INDEX('4. Reduktionsfaktorer, LENI-tal'!$H$46:$O$54,MATCH(N$21,'4. Reduktionsfaktorer, LENI-tal'!$H$46:$H$54,0),3)), IFERROR( INDEX( tblStrings[], MATCH( 1, (tblStrings[[Cell]:[Cell]]=AllStrings!$D$350) * (tblStrings[[Sheet]:[Sheet]]=AllStrings!$C$433), 0 ), MATCH(Språkval, tblStrings[#Headers], 0) ), ))} -> Fyll i byggnads- och rumstyp ovan | O32: {=IFERROR(_xlfn.IFS(O$19='4. Reduktionsfaktorer, LENI-tal'!$Q$12,INDEX('4. Reduktionsfaktorer, LENI-tal'!$H$13:$O$23,MATCH(O$21,'4. Reduktionsfaktorer, LENI-tal'!$H$13:$H$23,0),3), O$19='4. Reduktionsfaktorer, LENI-tal'!$R$12,INDEX('4. Reduktionsfaktorer, LENI-tal'!$H$24:$O$32,MATCH(O$21,'4. Reduktionsfaktorer, LENI-tal'!$H$24:$H$32,0),3), O$19='4. Reduktionsfaktorer, LENI-tal'!$S$12,INDEX('4. Reduktionsfaktorer, LENI-tal'!$H$33:$O$37,MATCH(O$21,'4. Reduktionsfaktorer, LENI-tal'!$H$33:$H$37,0),3), O$19='4. Reduktionsfaktorer, LENI-tal'!$T$12,INDEX('4. Reduktionsfaktorer, LENI-tal'!$H$38:$O$45,MATCH(O$21,'4. Reduktionsfaktorer, LENI-tal'!$H$38:$H$45,0),3), O$19='4. Reduktionsfaktorer, LENI-tal'!$U$12,INDEX('4. Reduktionsfaktorer, LENI-tal'!$H$46:$O$54,MATCH(O$21,'4. Reduktionsfaktorer, LENI-tal'!$H$46:$H$54,0),3)), IFERROR( INDEX( tblStrings[], MATCH( 1, (tblStrings[[Cell]:[Cell]]=AllStrings!$D$350) * (tblStrings[[Sheet]:[Sheet]]=AllStrings!$C$433), 0 ), MATCH(Språkval, tblStrings[#Headers], 0) ), ))} -> Fyll i byggnads- och rumstyp ovan | P32: {=IFERROR(_xlfn.IFS(P$19='4. Reduktionsfaktorer, LENI-tal'!$Q$12,INDEX('4. Reduktionsfaktorer, LENI-tal'!$H$13:$O$23,MATCH(P$21,'4. Reduktionsfaktorer, LENI-tal'!$H$13:$H$23,0),3), P$19='4. Reduktionsfaktorer, LENI-tal'!$R$12,INDEX('4. Reduktionsfaktorer, LENI-tal'!$H$24:$O$32,MATCH(P$21,'4. Reduktionsfaktorer, LENI-tal'!$H$24:$H$32,0),3), P$19='4. Reduktionsfaktorer, LENI-tal'!$S$12,INDEX('4. Reduktionsfaktorer, LENI-tal'!$H$33:$O$37,MATCH(P$21,'4. Reduktionsfaktorer, LENI-tal'!$H$33:$H$37,0),3), P$19='4. Reduktionsfaktorer, LENI-tal'!$T$12,INDEX('4. Reduktionsfaktorer, LENI-tal'!$H$38:$O$45,MATCH(P$21,'4. Reduktionsfaktorer, LENI-tal'!$H$38:$H$45,0),3), P$19='4. Reduktionsfaktorer, LENI-tal'!$U$12,INDEX('4. Reduktionsfaktorer, LENI-tal'!$H$46:$O$54,MATCH(P$21,'4. Reduktionsfaktorer, LENI-tal'!$H$46:$H$54,0),3)), IFERROR( INDEX( tblStrings[], MATCH( 1, (tblStrings[[Cell]:[Cell]]=AllStrings!$D$350) * (tblStrings[[Sheet]:[Sheet]]=AllStrings!$C$433), 0 ), MATCH(Språkval, tblStrings[#Headers], 0) ), ))} -> Fyll i byggnads- och rumstyp ovan | ... R32: {=IFERROR(_xlfn.IFS(R$19='4. Reduktionsfaktorer, LENI-tal'!$Q$12,INDEX('4. Reduktionsfaktorer, LENI-tal'!$H$13:$O$23,MATCH(R$21,'4. Reduktionsfaktorer, LENI-tal'!$H$13:$H$23,0),3), R$19='4. Reduktionsfaktorer, LENI-tal'!$R$12,INDEX('4. Reduktionsfaktorer, LENI-tal'!$H$24:$O$32,MATCH(R$21,'4. Reduktionsfaktorer, LENI-tal'!$H$24:$H$32,0),3), R$19='4. Reduktionsfaktorer, LENI-tal'!$S$12,INDEX('4. Reduktionsfaktorer, LENI-tal'!$H$33:$O$37,MATCH(R$21,'4. Reduktionsfaktorer, LENI-tal'!$H$33:$H$37,0),3), R$19='4. Reduktionsfaktorer, LENI-tal'!$T$12,INDEX('4. Reduktionsfaktorer, LENI-tal'!$H$38:$O$45,MATCH(R$21,'4. Reduktionsfaktorer, LENI-tal'!$H$38:$H$45,0),3), R$19='4. Reduktionsfaktorer, LENI-tal'!$U$12,INDEX('4. Reduktionsfaktorer, LENI-tal'!$H$46:$O$54,MATCH(R$21,'4. Reduktionsfaktorer, LENI-tal'!$H$46:$H$54,0),3)), IFERROR( INDEX( tblStrings[], MATCH( 1, (tblStrings[[Cell]:[Cell]]=AllStrings!$D$350) * (tblStrings[[Sheet]:[Sheet]]=AllStrings!$C$433), 0 ), MATCH(Språkval, tblStrings[#Headers], 0) ), ))} -> Fyll i byggnads- och rumstyp ovan
B33: 2.7 | C33: {=IFERROR( INDEX( tblStrings[], MATCH( 1, (tblStrings[Cell]=SUBSTITUTE(CELL("adress",INDIRECT("RC",FALSE)),"$","")) * (tblStrings[Sheet]=AllStrings!$C$433), 0 ), MATCH(Språkval, tblStrings[#Headers], 0) ), )} -> Reduktionsfaktor närvaro-/frånvarostyrning | H33: {=IFERROR( INDEX( tblStrings[], MATCH( 1, (tblStrings[Cell]=SUBSTITUTE(CELL("adress",INDIRECT("RC",FALSE)),"$","")) * (tblStrings[Sheet]=RIGHT(CELL("filnamn"),LEN(CELL("filnamn"))-SEARCH("]",CELL("filnamn")))), 0 ), MATCH(Språkval, tblStrings[#Headers], 0) ), "" )} | I33: {=IFERROR(_xlfn.IFS(I$19='4. Reduktionsfaktorer, LENI-tal'!$Q$12,INDEX('4. Reduktionsfaktorer, LENI-tal'!$H$13:$O$23,MATCH(I$21,'4. Reduktionsfaktorer, LENI-tal'!$H$13:$H$23,0),4), I$19='4. Reduktionsfaktorer, LENI-tal'!$R$12,INDEX('4. Reduktionsfaktorer, LENI-tal'!$H$24:$O$32,MATCH(I$21,'4. Reduktionsfaktorer, LENI-tal'!$H$24:$H$32,0),4), I$19='4. Reduktionsfaktorer, LENI-tal'!$S$12,INDEX('4. Reduktionsfaktorer, LENI-tal'!$H$33:$O$37,MATCH(I$21,'4. Reduktionsfaktorer, LENI-tal'!$H$33:$H$37,0),4), I$19='4. Reduktionsfaktorer, LENI-tal'!$T$12,INDEX('4. Reduktionsfaktorer, LENI-tal'!$H$38:$O$45,MATCH(I$21,'4. Reduktionsfaktorer, LENI-tal'!$H$38:$H$45,0),4), I$19='4. Reduktionsfaktorer, LENI-tal'!$U$12,INDEX('4. Reduktionsfaktorer, LENI-tal'!$H$46:$O$54,MATCH(I$21,'4. Reduktionsfaktorer, LENI-tal'!$H$46:$H$54,0),4)), IFERROR( INDEX( tblStrings[], MATCH( 1, (tblStrings[[Cell]:[Cell]]=AllStrings!$D$350) * (tblStrings[[Sheet]:[Sheet]]=AllStrings!$C$433), 0 ), MATCH(Språkval, tblStrings[#Headers], 0) ), ))} -> Fyll i byggnads- och rumstyp ovan | J33: {=IFERROR(_xlfn.IFS(J$19='4. Reduktionsfaktorer, LENI-tal'!$Q$12,INDEX('4. Reduktionsfaktorer, LENI-tal'!$H$13:$O$23,MATCH(J$21,'4. Reduktionsfaktorer, LENI-tal'!$H$13:$H$23,0),4), J$19='4. Reduktionsfaktorer, LENI-tal'!$R$12,INDEX('4. Reduktionsfaktorer, LENI-tal'!$H$24:$O$32,MATCH(J$21,'4. Reduktionsfaktorer, LENI-tal'!$H$24:$H$32,0),4), J$19='4. Reduktionsfaktorer, LENI-tal'!$S$12,INDEX('4. Reduktionsfaktorer, LENI-tal'!$H$33:$O$37,MATCH(J$21,'4. Reduktionsfaktorer, LENI-tal'!$H$33:$H$37,0),4), J$19='4. Reduktionsfaktorer, LENI-tal'!$T$12,INDEX('4. Reduktionsfaktorer, LENI-tal'!$H$38:$O$45,MATCH(J$21,'4. Reduktionsfaktorer, LENI-tal'!$H$38:$H$45,0),4), J$19='4. Reduktionsfaktorer, LENI-tal'!$U$12,INDEX('4. Reduktionsfaktorer, LENI-tal'!$H$46:$O$54,MATCH(J$21,'4. Reduktionsfaktorer, LENI-tal'!$H$46:$H$54,0),4)), IFERROR( INDEX( tblStrings[], MATCH( 1, (tblStrings[[Cell]:[Cell]]=AllStrings!$D$350) * (tblStrings[[Sheet]:[Sheet]]=AllStrings!$C$433), 0 ), MATCH(Språkval, tblStrings[#Headers], 0) ), ))} -> Fyll i byggnads- och rumstyp ovan | K33: {=IFERROR(_xlfn.IFS(K$19='4. Reduktionsfaktorer, LENI-tal'!$Q$12,INDEX('4. Reduktionsfaktorer, LENI-tal'!$H$13:$O$23,MATCH(K$21,'4. Reduktionsfaktorer, LENI-tal'!$H$13:$H$23,0),4), K$19='4. Reduktionsfaktorer, LENI-tal'!$R$12,INDEX('4. Reduktionsfaktorer, LENI-tal'!$H$24:$O$32,MATCH(K$21,'4. Reduktionsfaktorer, LENI-tal'!$H$24:$H$32,0),4), K$19='4. Reduktionsfaktorer, LENI-tal'!$S$12,INDEX('4. Reduktionsfaktorer, LENI-tal'!$H$33:$O$37,MATCH(K$21,'4. Reduktionsfaktorer, LENI-tal'!$H$33:$H$37,0),4), K$19='4. Reduktionsfaktorer, LENI-tal'!$T$12,INDEX('4. Reduktionsfaktorer, LENI-tal'!$H$38:$O$45,MATCH(K$21,'4. Reduktionsfaktorer, LENI-tal'!$H$38:$H$45,0),4), K$19='4. Reduktionsfaktorer, LENI-tal'!$U$12,INDEX('4. Reduktionsfaktorer, LENI-tal'!$H$46:$O$54,MATCH(K$21,'4. Reduktionsfaktorer, LENI-tal'!$H$46:$H$54,0),4)), IFERROR( INDEX( tblStrings[], MATCH( 1, (tblStrings[[Cell]:[Cell]]=AllStrings!$D$350) * (tblStrings[[Sheet]:[Sheet]]=AllStrings!$C$433), 0 ), MATCH(Språkval, tblStrings[#Headers], 0) ), ))} -> Fyll i byggnads- och rumstyp ovan | L33: {=IFERROR(_xlfn.IFS(L$19='4. Reduktionsfaktorer, LENI-tal'!$Q$12,INDEX('4. Reduktionsfaktorer, LENI-tal'!$H$13:$O$23,MATCH(L$21,'4. Reduktionsfaktorer, LENI-tal'!$H$13:$H$23,0),4), L$19='4. Reduktionsfaktorer, LENI-tal'!$R$12,INDEX('4. Reduktionsfaktorer, LENI-tal'!$H$24:$O$32,MATCH(L$21,'4. Reduktionsfaktorer, LENI-tal'!$H$24:$H$32,0),4), L$19='4. Reduktionsfaktorer, LENI-tal'!$S$12,INDEX('4. Reduktionsfaktorer, LENI-tal'!$H$33:$O$37,MATCH(L$21,'4. Reduktionsfaktorer, LENI-tal'!$H$33:$H$37,0),4), L$19='4. Reduktionsfaktorer, LENI-tal'!$T$12,INDEX('4. Reduktionsfaktorer, LENI-tal'!$H$38:$O$45,MATCH(L$21,'4. Reduktionsfaktorer, LENI-tal'!$H$38:$H$45,0),4), L$19='4. Reduktionsfaktorer, LENI-tal'!$U$12,INDEX('4. Reduktionsfaktorer, LENI-tal'!$H$46:$O$54,MATCH(L$21,'4. Reduktionsfaktorer, LENI-tal'!$H$46:$H$54,0),4)), IFERROR( INDEX( tblStrings[], MATCH( 1, (tblStrings[[Cell]:[Cell]]=AllStrings!$D$350) * (tblStrings[[Sheet]:[Sheet]]=AllStrings!$C$433), 0 ), MATCH(Språkval, tblStrings[#Headers], 0) ), ))} -> Fyll i byggnads- och rumstyp ovan | M33: {=IFERROR(_xlfn.IFS(M$19='4. Reduktionsfaktorer, LENI-tal'!$Q$12,INDEX('4. Reduktionsfaktorer, LENI-tal'!$H$13:$O$23,MATCH(M$21,'4. Reduktionsfaktorer, LENI-tal'!$H$13:$H$23,0),4), M$19='4. Reduktionsfaktorer, LENI-tal'!$R$12,INDEX('4. Reduktionsfaktorer, LENI-tal'!$H$24:$O$32,MATCH(M$21,'4. Reduktionsfaktorer, LENI-tal'!$H$24:$H$32,0),4), M$19='4. Reduktionsfaktorer, LENI-tal'!$S$12,INDEX('4. Reduktionsfaktorer, LENI-tal'!$H$33:$O$37,MATCH(M$21,'4. Reduktionsfaktorer, LENI-tal'!$H$33:$H$37,0),4), M$19='4. Reduktionsfaktorer, LENI-tal'!$T$12,INDEX('4. Reduktionsfaktorer, LENI-tal'!$H$38:$O$45,MATCH(M$21,'4. Reduktionsfaktorer, LENI-tal'!$H$38:$H$45,0),4), M$19='4. Reduktionsfaktorer, LENI-tal'!$U$12,INDEX('4. Reduktionsfaktorer, LENI-tal'!$H$46:$O$54,MATCH(M$21,'4. Reduktionsfaktorer, LENI-tal'!$H$46:$H$54,0),4)), IFERROR( INDEX( tblStrings[], MATCH( 1, (tblStrings[[Cell]:[Cell]]=AllStrings!$D$350) * (tblStrings[[Sheet]:[Sheet]]=AllStrings!$C$433), 0 ), MATCH(Språkval, tblStrings[#Headers], 0) ), ))} -> Fyll i byggnads- och rumstyp ovan | N33: {=IFERROR(_xlfn.IFS(N$19='4. Reduktionsfaktorer, LENI-tal'!$Q$12,INDEX('4. Reduktionsfaktorer, LENI-tal'!$H$13:$O$23,MATCH(N$21,'4. Reduktionsfaktorer, LENI-tal'!$H$13:$H$23,0),4), N$19='4. Reduktionsfaktorer, LENI-tal'!$R$12,INDEX('4. Reduktionsfaktorer, LENI-tal'!$H$24:$O$32,MATCH(N$21,'4. Reduktionsfaktorer, LENI-tal'!$H$24:$H$32,0),4), N$19='4. Reduktionsfaktorer, LENI-tal'!$S$12,INDEX('4. Reduktionsfaktorer, LENI-tal'!$H$33:$O$37,MATCH(N$21,'4. Reduktionsfaktorer, LENI-tal'!$H$33:$H$37,0),4), N$19='4. Reduktionsfaktorer, LENI-tal'!$T$12,INDEX('4. Reduktionsfaktorer, LENI-tal'!$H$38:$O$45,MATCH(N$21,'4. Reduktionsfaktorer, LENI-tal'!$H$38:$H$45,0),4), N$19='4. Reduktionsfaktorer, LENI-tal'!$U$12,INDEX('4. Reduktionsfaktorer, LENI-tal'!$H$46:$O$54,MATCH(N$21,'4. Reduktionsfaktorer, LENI-tal'!$H$46:$H$54,0),4)), IFERROR( INDEX( tblStrings[], MATCH( 1, (tblStrings[[Cell]:[Cell]]=AllStrings!$D$350) * (tblStrings[[Sheet]:[Sheet]]=AllStrings!$C$433), 0 ), MATCH(Språkval, tblStrings[#Headers], 0) ), ))} -> Fyll i byggnads- och rumstyp ovan | O33: {=IFERROR(_xlfn.IFS(O$19='4. Reduktionsfaktorer, LENI-tal'!$Q$12,INDEX('4. Reduktionsfaktorer, LENI-tal'!$H$13:$O$23,MATCH(O$21,'4. Reduktionsfaktorer, LENI-tal'!$H$13:$H$23,0),4), O$19='4. Reduktionsfaktorer, LENI-tal'!$R$12,INDEX('4. Reduktionsfaktorer, LENI-tal'!$H$24:$O$32,MATCH(O$21,'4. Reduktionsfaktorer, LENI-tal'!$H$24:$H$32,0),4), O$19='4. Reduktionsfaktorer, LENI-tal'!$S$12,INDEX('4. Reduktionsfaktorer, LENI-tal'!$H$33:$O$37,MATCH(O$21,'4. Reduktionsfaktorer, LENI-tal'!$H$33:$H$37,0),4), O$19='4. Reduktionsfaktorer, LENI-tal'!$T$12,INDEX('4. Reduktionsfaktorer, LENI-tal'!$H$38:$O$45,MATCH(O$21,'4. Reduktionsfaktorer, LENI-tal'!$H$38:$H$45,0),4), O$19='4. Reduktionsfaktorer, LENI-tal'!$U$12,INDEX('4. Reduktionsfaktorer, LENI-tal'!$H$46:$O$54,MATCH(O$21,'4. Reduktionsfaktorer, LENI-tal'!$H$46:$H$54,0),4)), IFERROR( INDEX( tblStrings[], MATCH( 1, (tblStrings[[Cell]:[Cell]]=AllStrings!$D$350) * (tblStrings[[Sheet]:[Sheet]]=AllStrings!$C$433), 0 ), MATCH(Språkval, tblStrings[#Headers], 0) ), ))} -> Fyll i byggnads- och rumstyp ovan | P33: {=IFERROR(_xlfn.IFS(P$19='4. Reduktionsfaktorer, LENI-tal'!$Q$12,INDEX('4. Reduktionsfaktorer, LENI-tal'!$H$13:$O$23,MATCH(P$21,'4. Reduktionsfaktorer, LENI-tal'!$H$13:$H$23,0),4), P$19='4. Reduktionsfaktorer, LENI-tal'!$R$12,INDEX('4. Reduktionsfaktorer, LENI-tal'!$H$24:$O$32,MATCH(P$21,'4. Reduktionsfaktorer, LENI-tal'!$H$24:$H$32,0),4), P$19='4. Reduktionsfaktorer, LENI-tal'!$S$12,INDEX('4. Reduktionsfaktorer, LENI-tal'!$H$33:$O$37,MATCH(P$21,'4. Reduktionsfaktorer, LENI-tal'!$H$33:$H$37,0),4), P$19='4. Reduktionsfaktorer, LENI-tal'!$T$12,INDEX('4. Reduktionsfaktorer, LENI-tal'!$H$38:$O$45,MATCH(P$21,'4. Reduktionsfaktorer, LENI-tal'!$H$38:$H$45,0),4), P$19='4. Reduktionsfaktorer, LENI-tal'!$U$12,INDEX('4. Reduktionsfaktorer, LENI-tal'!$H$46:$O$54,MATCH(P$21,'4. Reduktionsfaktorer, LENI-tal'!$H$46:$H$54,0),4)), IFERROR( INDEX( tblStrings[], MATCH( 1, (tblStrings[[Cell]:[Cell]]=AllStrings!$D$350) * (tblStrings[[Sheet]:[Sheet]]=AllStrings!$C$433), 0 ), MATCH(Språkval, tblStrings[#Headers], 0) ), ))} -> Fyll i byggnads- och rumstyp ovan | ... R33: {=IFERROR(_xlfn.IFS(R$19='4. Reduktionsfaktorer, LENI-tal'!$Q$12,INDEX('4. Reduktionsfaktorer, LENI-tal'!$H$13:$O$23,MATCH(R$21,'4. Reduktionsfaktorer, LENI-tal'!$H$13:$H$23,0),4), R$19='4. Reduktionsfaktorer, LENI-tal'!$R$12,INDEX('4. Reduktionsfaktorer, LENI-tal'!$H$24:$O$32,MATCH(R$21,'4. Reduktionsfaktorer, LENI-tal'!$H$24:$H$32,0),4), R$19='4. Reduktionsfaktorer, LENI-tal'!$S$12,INDEX('4. Reduktionsfaktorer, LENI-tal'!$H$33:$O$37,MATCH(R$21,'4. Reduktionsfaktorer, LENI-tal'!$H$33:$H$37,0),4), R$19='4. Reduktionsfaktorer, LENI-tal'!$T$12,INDEX('4. Reduktionsfaktorer, LENI-tal'!$H$38:$O$45,MATCH(R$21,'4. Reduktionsfaktorer, LENI-tal'!$H$38:$H$45,0),4), R$19='4. Reduktionsfaktorer, LENI-tal'!$U$12,INDEX('4. Reduktionsfaktorer, LENI-tal'!$H$46:$O$54,MATCH(R$21,'4. Reduktionsfaktorer, LENI-tal'!$H$46:$H$54,0),4)), IFERROR( INDEX( tblStrings[], MATCH( 1, (tblStrings[[Cell]:[Cell]]=AllStrings!$D$350) * (tblStrings[[Sheet]:[Sheet]]=AllStrings!$C$433), 0 ), MATCH(Språkval, tblStrings[#Headers], 0) ), ))} -> Fyll i byggnads- och rumstyp ovan
B34: 2.8 | C34: {=IFERROR( INDEX( tblStrings[], MATCH( 1, (tblStrings[Cell]=SUBSTITUTE(CELL("adress",INDIRECT("RC",FALSE)),"$","")) * (tblStrings[Sheet]=AllStrings!$C$433), 0 ), MATCH(Språkval, tblStrings[#Headers], 0) ), )} -> Reduktionsfaktor dagsljusstyrning | H34: {=IFERROR( INDEX( tblStrings[], MATCH( 1, (tblStrings[Cell]=SUBSTITUTE(CELL("adress",INDIRECT("RC",FALSE)),"$","")) * (tblStrings[Sheet]=RIGHT(CELL("filnamn"),LEN(CELL("filnamn"))-SEARCH("]",CELL("filnamn")))), 0 ), MATCH(Språkval, tblStrings[#Headers], 0) ), "" )} | I34: {=IFERROR(_xlfn.IFS(I$19='4. Reduktionsfaktorer, LENI-tal'!$Q$12,INDEX('4. Reduktionsfaktorer, LENI-tal'!$H$13:$O$23,MATCH(I$21,'4. Reduktionsfaktorer, LENI-tal'!$H$13:$H$23,0),5), I$19='4. Reduktionsfaktorer, LENI-tal'!$R$12,INDEX('4. Reduktionsfaktorer, LENI-tal'!$H$24:$O$32,MATCH(I$21,'4. Reduktionsfaktorer, LENI-tal'!$H$24:$H$32,0),5), I$19='4. Reduktionsfaktorer, LENI-tal'!$S$12,INDEX('4. Reduktionsfaktorer, LENI-tal'!$H$33:$O$37,MATCH(I$21,'4. Reduktionsfaktorer, LENI-tal'!$H$33:$H$37,0),5), I$19='4. Reduktionsfaktorer, LENI-tal'!$T$12,INDEX('4. Reduktionsfaktorer, LENI-tal'!$H$38:$O$45,MATCH(I$21,'4. Reduktionsfaktorer, LENI-tal'!$H$38:$H$45,0),5), I$19='4. Reduktionsfaktorer, LENI-tal'!$U$12,INDEX('4. Reduktionsfaktorer, LENI-tal'!$H$46:$O$54,MATCH(I$21,'4. Reduktionsfaktorer, LENI-tal'!$H$46:$H$54,0),5)), IFERROR( INDEX( tblStrings[], MATCH( 1, (tblStrings[[Cell]:[Cell]]=AllStrings!$D$350) * (tblStrings[[Sheet]:[Sheet]]=AllStrings!$C$433), 0 ), MATCH(Språkval, tblStrings[#Headers], 0) ), ))} -> Fyll i byggnads- och rumstyp ovan | J34: {=IFERROR(_xlfn.IFS(J$19='4. Reduktionsfaktorer, LENI-tal'!$Q$12,INDEX('4. Reduktionsfaktorer, LENI-tal'!$H$13:$O$23,MATCH(J$21,'4. Reduktionsfaktorer, LENI-tal'!$H$13:$H$23,0),5), J$19='4. Reduktionsfaktorer, LENI-tal'!$R$12,INDEX('4. Reduktionsfaktorer, LENI-tal'!$H$24:$O$32,MATCH(J$21,'4. Reduktionsfaktorer, LENI-tal'!$H$24:$H$32,0),5), J$19='4. Reduktionsfaktorer, LENI-tal'!$S$12,INDEX('4. Reduktionsfaktorer, LENI-tal'!$H$33:$O$37,MATCH(J$21,'4. Reduktionsfaktorer, LENI-tal'!$H$33:$H$37,0),5), J$19='4. Reduktionsfaktorer, LENI-tal'!$T$12,INDEX('4. Reduktionsfaktorer, LENI-tal'!$H$38:$O$45,MATCH(J$21,'4. Reduktionsfaktorer, LENI-tal'!$H$38:$H$45,0),5), J$19='4. Reduktionsfaktorer, LENI-tal'!$U$12,INDEX('4. Reduktionsfaktorer, LENI-tal'!$H$46:$O$54,MATCH(J$21,'4. Reduktionsfaktorer, LENI-tal'!$H$46:$H$54,0),5)), IFERROR( INDEX( tblStrings[], MATCH( 1, (tblStrings[[Cell]:[Cell]]=AllStrings!$D$350) * (tblStrings[[Sheet]:[Sheet]]=AllStrings!$C$433), 0 ), MATCH(Språkval, tblStrings[#Headers], 0) ), ))} -> Fyll i byggnads- och rumstyp ovan | K34: {=IFERROR(_xlfn.IFS(K$19='4. Reduktionsfaktorer, LENI-tal'!$Q$12,INDEX('4. Reduktionsfaktorer, LENI-tal'!$H$13:$O$23,MATCH(K$21,'4. Reduktionsfaktorer, LENI-tal'!$H$13:$H$23,0),5), K$19='4. Reduktionsfaktorer, LENI-tal'!$R$12,INDEX('4. Reduktionsfaktorer, LENI-tal'!$H$24:$O$32,MATCH(K$21,'4. Reduktionsfaktorer, LENI-tal'!$H$24:$H$32,0),5), K$19='4. Reduktionsfaktorer, LENI-tal'!$S$12,INDEX('4. Reduktionsfaktorer, LENI-tal'!$H$33:$O$37,MATCH(K$21,'4. Reduktionsfaktorer, LENI-tal'!$H$33:$H$37,0),5), K$19='4. Reduktionsfaktorer, LENI-tal'!$T$12,INDEX('4. Reduktionsfaktorer, LENI-tal'!$H$38:$O$45,MATCH(K$21,'4. Reduktionsfaktorer, LENI-tal'!$H$38:$H$45,0),5), K$19='4. Reduktionsfaktorer, LENI-tal'!$U$12,INDEX('4. Reduktionsfaktorer, LENI-tal'!$H$46:$O$54,MATCH(K$21,'4. Reduktionsfaktorer, LENI-tal'!$H$46:$H$54,0),5)), IFERROR( INDEX( tblStrings[], MATCH( 1, (tblStrings[[Cell]:[Cell]]=AllStrings!$D$350) * (tblStrings[[Sheet]:[Sheet]]=AllStrings!$C$433), 0 ), MATCH(Språkval, tblStrings[#Headers], 0) ), ))} -> Fyll i byggnads- och rumstyp ovan | L34: {=IFERROR(_xlfn.IFS(L$19='4. Reduktionsfaktorer, LENI-tal'!$Q$12,INDEX('4. Reduktionsfaktorer, LENI-tal'!$H$13:$O$23,MATCH(L$21,'4. Reduktionsfaktorer, LENI-tal'!$H$13:$H$23,0),5), L$19='4. Reduktionsfaktorer, LENI-tal'!$R$12,INDEX('4. Reduktionsfaktorer, LENI-tal'!$H$24:$O$32,MATCH(L$21,'4. Reduktionsfaktorer, LENI-tal'!$H$24:$H$32,0),5), L$19='4. Reduktionsfaktorer, LENI-tal'!$S$12,INDEX('4. Reduktionsfaktorer, LENI-tal'!$H$33:$O$37,MATCH(L$21,'4. Reduktionsfaktorer, LENI-tal'!$H$33:$H$37,0),5), L$19='4. Reduktionsfaktorer, LENI-tal'!$T$12,INDEX('4. Reduktionsfaktorer, LENI-tal'!$H$38:$O$45,MATCH(L$21,'4. Reduktionsfaktorer, LENI-tal'!$H$38:$H$45,0),5), L$19='4. Reduktionsfaktorer, LENI-tal'!$U$12,INDEX('4. Reduktionsfaktorer, LENI-tal'!$H$46:$O$54,MATCH(L$21,'4. Reduktionsfaktorer, LENI-tal'!$H$46:$H$54,0),5)), IFERROR( INDEX( tblStrings[], MATCH( 1, (tblStrings[[Cell]:[Cell]]=AllStrings!$D$350) * (tblStrings[[Sheet]:[Sheet]]=AllStrings!$C$433), 0 ), MATCH(Språkval, tblStrings[#Headers], 0) ), ))} -> Fyll i byggnads- och rumstyp ovan | M34: {=IFERROR(_xlfn.IFS(M$19='4. Reduktionsfaktorer, LENI-tal'!$Q$12,INDEX('4. Reduktionsfaktorer, LENI-tal'!$H$13:$O$23,MATCH(M$21,'4. Reduktionsfaktorer, LENI-tal'!$H$13:$H$23,0),5), M$19='4. Reduktionsfaktorer, LENI-tal'!$R$12,INDEX('4. Reduktionsfaktorer, LENI-tal'!$H$24:$O$32,MATCH(M$21,'4. Reduktionsfaktorer, LENI-tal'!$H$24:$H$32,0),5), M$19='4. Reduktionsfaktorer, LENI-tal'!$S$12,INDEX('4. Reduktionsfaktorer, LENI-tal'!$H$33:$O$37,MATCH(M$21,'4. Reduktionsfaktorer, LENI-tal'!$H$33:$H$37,0),5), M$19='4. Reduktionsfaktorer, LENI-tal'!$T$12,INDEX('4. Reduktionsfaktorer, LENI-tal'!$H$38:$O$45,MATCH(M$21,'4. Reduktionsfaktorer, LENI-tal'!$H$38:$H$45,0),5), M$19='4. Reduktionsfaktorer, LENI-tal'!$U$12,INDEX('4. Reduktionsfaktorer, LENI-tal'!$H$46:$O$54,MATCH(M$21,'4. Reduktionsfaktorer, LENI-tal'!$H$46:$H$54,0),5)), IFERROR( INDEX( tblStrings[], MATCH( 1, (tblStrings[[Cell]:[Cell]]=AllStrings!$D$350) * (tblStrings[[Sheet]:[Sheet]]=AllStrings!$C$433), 0 ), MATCH(Språkval, tblStrings[#Headers], 0) ), ))} -> Fyll i byggnads- och rumstyp ovan | N34: {=IFERROR(_xlfn.IFS(N$19='4. Reduktionsfaktorer, LENI-tal'!$Q$12,INDEX('4. Reduktionsfaktorer, LENI-tal'!$H$13:$O$23,MATCH(N$21,'4. Reduktionsfaktorer, LENI-tal'!$H$13:$H$23,0),5), N$19='4. Reduktionsfaktorer, LENI-tal'!$R$12,INDEX('4. Reduktionsfaktorer, LENI-tal'!$H$24:$O$32,MATCH(N$21,'4. Reduktionsfaktorer, LENI-tal'!$H$24:$H$32,0),5), N$19='4. Reduktionsfaktorer, LENI-tal'!$S$12,INDEX('4. Reduktionsfaktorer, LENI-tal'!$H$33:$O$37,MATCH(N$21,'4. Reduktionsfaktorer, LENI-tal'!$H$33:$H$37,0),5), N$19='4. Reduktionsfaktorer, LENI-tal'!$T$12,INDEX('4. Reduktionsfaktorer, LENI-tal'!$H$38:$O$45,MATCH(N$21,'4. Reduktionsfaktorer, LENI-tal'!$H$38:$H$45,0),5), N$19='4. Reduktionsfaktorer, LENI-tal'!$U$12,INDEX('4. Reduktionsfaktorer, LENI-tal'!$H$46:$O$54,MATCH(N$21,'4. Reduktionsfaktorer, LENI-tal'!$H$46:$H$54,0),5)), IFERROR( INDEX( tblStrings[], MATCH( 1, (tblStrings[[Cell]:[Cell]]=AllStrings!$D$350) * (tblStrings[[Sheet]:[Sheet]]=AllStrings!$C$433), 0 ), MATCH(Språkval, tblStrings[#Headers], 0) ), ))} -> Fyll i byggnads- och rumstyp ovan | O34: {=IFERROR(_xlfn.IFS(O$19='4. Reduktionsfaktorer, LENI-tal'!$Q$12,INDEX('4. Reduktionsfaktorer, LENI-tal'!$H$13:$O$23,MATCH(O$21,'4. Reduktionsfaktorer, LENI-tal'!$H$13:$H$23,0),5), O$19='4. Reduktionsfaktorer, LENI-tal'!$R$12,INDEX('4. Reduktionsfaktorer, LENI-tal'!$H$24:$O$32,MATCH(O$21,'4. Reduktionsfaktorer, LENI-tal'!$H$24:$H$32,0),5), O$19='4. Reduktionsfaktorer, LENI-tal'!$S$12,INDEX('4. Reduktionsfaktorer, LENI-tal'!$H$33:$O$37,MATCH(O$21,'4. Reduktionsfaktorer, LENI-tal'!$H$33:$H$37,0),5), O$19='4. Reduktionsfaktorer, LENI-tal'!$T$12,INDEX('4. Reduktionsfaktorer, LENI-tal'!$H$38:$O$45,MATCH(O$21,'4. Reduktionsfaktorer, LENI-tal'!$H$38:$H$45,0),5), O$19='4. Reduktionsfaktorer, LENI-tal'!$U$12,INDEX('4. Reduktionsfaktorer, LENI-tal'!$H$46:$O$54,MATCH(O$21,'4. Reduktionsfaktorer, LENI-tal'!$H$46:$H$54,0),5)), IFERROR( INDEX( tblStrings[], MATCH( 1, (tblStrings[[Cell]:[Cell]]=AllStrings!$D$350) * (tblStrings[[Sheet]:[Sheet]]=AllStrings!$C$433), 0 ), MATCH(Språkval, tblStrings[#Headers], 0) ), ))} -> Fyll i byggnads- och rumstyp ovan | P34: {=IFERROR(_xlfn.IFS(P$19='4. Reduktionsfaktorer, LENI-tal'!$Q$12,INDEX('4. Reduktionsfaktorer, LENI-tal'!$H$13:$O$23,MATCH(P$21,'4. Reduktionsfaktorer, LENI-tal'!$H$13:$H$23,0),5), P$19='4. Reduktionsfaktorer, LENI-tal'!$R$12,INDEX('4. Reduktionsfaktorer, LENI-tal'!$H$24:$O$32,MATCH(P$21,'4. Reduktionsfaktorer, LENI-tal'!$H$24:$H$32,0),5), P$19='4. Reduktionsfaktorer, LENI-tal'!$S$12,INDEX('4. Reduktionsfaktorer, LENI-tal'!$H$33:$O$37,MATCH(P$21,'4. Reduktionsfaktorer, LENI-tal'!$H$33:$H$37,0),5), P$19='4. Reduktionsfaktorer, LENI-tal'!$T$12,INDEX('4. Reduktionsfaktorer, LENI-tal'!$H$38:$O$45,MATCH(P$21,'4. Reduktionsfaktorer, LENI-tal'!$H$38:$H$45,0),5), P$19='4. Reduktionsfaktorer, LENI-tal'!$U$12,INDEX('4. Reduktionsfaktorer, LENI-tal'!$H$46:$O$54,MATCH(P$21,'4. Reduktionsfaktorer, LENI-tal'!$H$46:$H$54,0),5)), IFERROR( INDEX( tblStrings[], MATCH( 1, (tblStrings[[Cell]:[Cell]]=AllStrings!$D$350) * (tblStrings[[Sheet]:[Sheet]]=AllStrings!$C$433), 0 ), MATCH(Språkval, tblStrings[#Headers], 0) ), ))} -> Fyll i byggnads- och rumstyp ovan | ... R34: {=IFERROR(_xlfn.IFS(R$19='4. Reduktionsfaktorer, LENI-tal'!$Q$12,INDEX('4. Reduktionsfaktorer, LENI-tal'!$H$13:$O$23,MATCH(R$21,'4. Reduktionsfaktorer, LENI-tal'!$H$13:$H$23,0),5), R$19='4. Reduktionsfaktorer, LENI-tal'!$R$12,INDEX('4. Reduktionsfaktorer, LENI-tal'!$H$24:$O$32,MATCH(R$21,'4. Reduktionsfaktorer, LENI-tal'!$H$24:$H$32,0),5), R$19='4. Reduktionsfaktorer, LENI-tal'!$S$12,INDEX('4. Reduktionsfaktorer, LENI-tal'!$H$33:$O$37,MATCH(R$21,'4. Reduktionsfaktorer, LENI-tal'!$H$33:$H$37,0),5), R$19='4. Reduktionsfaktorer, LENI-tal'!$T$12,INDEX('4. Reduktionsfaktorer, LENI-tal'!$H$38:$O$45,MATCH(R$21,'4. Reduktionsfaktorer, LENI-tal'!$H$38:$H$45,0),5), R$19='4. Reduktionsfaktorer, LENI-tal'!$U$12,INDEX('4. Reduktionsfaktorer, LENI-tal'!$H$46:$O$54,MATCH(R$21,'4. Reduktionsfaktorer, LENI-tal'!$H$46:$H$54,0),5)), IFERROR( INDEX( tblStrings[], MATCH( 1, (tblStrings[[Cell]:[Cell]]=AllStrings!$D$350) * (tblStrings[[Sheet]:[Sheet]]=AllStrings!$C$433), 0 ), MATCH(Språkval, tblStrings[#Headers], 0) ), ))} -> Fyll i byggnads- och rumstyp ovan
B35: 2.9 | C35: {=IFERROR( INDEX( tblStrings[], MATCH( 1, (tblStrings[Cell]=SUBSTITUTE(CELL("adress",INDIRECT("RC",FALSE)),"$","")) * (tblStrings[Sheet]=AllStrings!$C$433), 0 ), MATCH(Språkval, tblStrings[#Headers], 0) ), )} -> Total reduktionsfaktor för styrning | I35: =IF(IF(I31=$I$233,I32,IF(I31=$I$234,I32*I33,IF(I31=$I$235,I32*I33*I34,1)))=0,"Fyll i 2.6-2.8",IF(I31=$I$233,I32,IF(I31=$I$234,I32*I33,IF(I31=$I$235,I32*I33*I34,1)))) -> 1 | J35: =IF(IF(J31=$I$233,J32,IF(J31=$I$234,J32*J33,IF(J31=$I$235,J32*J33*J34,1)))=0,"Fyll i 2.6-2.8",IF(J31=$I$233,J32,IF(J31=$I$234,J32*J33,IF(J31=$I$235,J32*J33*J34,1)))) -> 1 | K35: =IF(IF(K31=$I$233,K32,IF(K31=$I$234,K32*K33,IF(K31=$I$235,K32*K33*K34,1)))=0,"Fyll i 2.6-2.8",IF(K31=$I$233,K32,IF(K31=$I$234,K32*K33,IF(K31=$I$235,K32*K33*K34,1)))) -> 1 | L35: =IF(IF(L31=$I$233,L32,IF(L31=$I$234,L32*L33,IF(L31=$I$235,L32*L33*L34,1)))=0,"Fyll i 2.6-2.8",IF(L31=$I$233,L32,IF(L31=$I$234,L32*L33,IF(L31=$I$235,L32*L33*L34,1)))) -> 1 | M35: =IF(IF(M31=$I$233,M32,IF(M31=$I$234,M32*M33,IF(M31=$I$235,M32*M33*M34,1)))=0,"Fyll i 2.6-2.8",IF(M31=$I$233,M32,IF(M31=$I$234,M32*M33,IF(M31=$I$235,M32*M33*M34,1)))) -> 1 | N35: =IF(IF(N31=$I$233,N32,IF(N31=$I$234,N32*N33,IF(N31=$I$235,N32*N33*N34,1)))=0,"Fyll i 2.6-2.8",IF(N31=$I$233,N32,IF(N31=$I$234,N32*N33,IF(N31=$I$235,N32*N33*N34,1)))) -> 1 | O35: =IF(IF(O31=$I$233,O32,IF(O31=$I$234,O32*O33,IF(O31=$I$235,O32*O33*O34,1)))=0,"Fyll i 2.6-2.8",IF(O31=$I$233,O32,IF(O31=$I$234,O32*O33,IF(O31=$I$235,O32*O33*O34,1)))) -> 1 | P35: =IF(IF(P31=$I$233,P32,IF(P31=$I$234,P32*P33,IF(P31=$I$235,P32*P33*P34,1)))=0,"Fyll i 2.6-2.8",IF(P31=$I$233,P32,IF(P31=$I$234,P32*P33,IF(P31=$I$235,P32*P33*P34,1)))) -> 1 | ... R35: =IF(IF(R31=$I$233,R32,IF(R31=$I$234,R32*R33,IF(R31=$I$235,R32*R33*R34,1)))=0,"Fyll i 2.6-2.8",IF(R31=$I$233,R32,IF(R31=$I$234,R32*R33,IF(R31=$I$235,R32*R33*R34,1)))) -> 1
B36: 2.10 | C36: {=IFERROR( INDEX( tblStrings[], MATCH( 1, (tblStrings[Cell]=SUBSTITUTE(CELL("adress",INDIRECT("RC",FALSE)),"$","")) * (tblStrings[Sheet]=AllStrings!$C$433), 0 ), MATCH(Språkval, tblStrings[#Headers], 0) ), )} -> Underhållskostnader | H36: {=IFERROR( INDEX( tblStrings[], MATCH( 1, (tblStrings[Cell]=SUBSTITUTE(CELL("adress",INDIRECT("RC",FALSE)),"$","")) * (tblStrings[Sheet]=AllStrings!$C$433), 0 ), MATCH(Språkval, tblStrings[#Headers], 0) ), )} -> kr/år
C38: =$C$26 -> Armaturbeteckning
B39: 2.1 | C39: =$C$27 -> Antal armaturer | H39: =$H$27 -> stk
B40: 2.2 | C40: =$C$28 -> Armaturpris | H40: =$H$28 -> kr/stk
B41: 2.3 | C41: =$C$29 -> Material- och arbetskostnader armatur | H41: =$H$29 -> kr
B42: 2.4 | C42: =$C$30 -> Effekt per armatur, inkl. driftsförluster | H42: =$H$30 -> W/stk
B43: 2.5 | C43: =$C$31 -> Typ av styrning
B44: 2.6 | C44: =$C32 -> Reduktionsfaktor manuell styrning | I44: {=IFERROR(_xlfn.IFS(I$19='4. Reduktionsfaktorer, LENI-tal'!$Q$12,INDEX('4. Reduktionsfaktorer, LENI-tal'!$H$13:$O$23,MATCH(I$21,'4. Reduktionsfaktorer, LENI-tal'!$H$13:$H$23,0),3), I$19='4. Reduktionsfaktorer, LENI-tal'!$R$12,INDEX('4. Reduktionsfaktorer, LENI-tal'!$H$24:$O$32,MATCH(I$21,'4. Reduktionsfaktorer, LENI-tal'!$H$24:$H$32,0),3), I$19='4. Reduktionsfaktorer, LENI-tal'!$S$12,INDEX('4. Reduktionsfaktorer, LENI-tal'!$H$33:$O$37,MATCH(I$21,'4. Reduktionsfaktorer, LENI-tal'!$H$33:$H$37,0),3), I$19='4. Reduktionsfaktorer, LENI-tal'!$T$12,INDEX('4. Reduktionsfaktorer, LENI-tal'!$H$38:$O$45,MATCH(I$21,'4. Reduktionsfaktorer, LENI-tal'!$H$38:$H$45,0),3), I$19='4. Reduktionsfaktorer, LENI-tal'!$U$12,INDEX('4. Reduktionsfaktorer, LENI-tal'!$H$46:$O$54,MATCH(I$21,'4. Reduktionsfaktorer, LENI-tal'!$H$46:$H$54,0),3)), IFERROR( INDEX( tblStrings[], MATCH( 1, (tblStrings[[Cell]:[Cell]]=AllStrings!$D$350) * (tblStrings[[Sheet]:[Sheet]]=AllStrings!$C$433), 0 ), MATCH(Språkval, tblStrings[#Headers], 0) ), ))} -> Fyll i byggnads- och rumstyp ovan | J44: {=IFERROR(_xlfn.IFS(J$19='4. Reduktionsfaktorer, LENI-tal'!$Q$12,INDEX('4. Reduktionsfaktorer, LENI-tal'!$H$13:$O$23,MATCH(J$21,'4. Reduktionsfaktorer, LENI-tal'!$H$13:$H$23,0),3), J$19='4. Reduktionsfaktorer, LENI-tal'!$R$12,INDEX('4. Reduktionsfaktorer, LENI-tal'!$H$24:$O$32,MATCH(J$21,'4. Reduktionsfaktorer, LENI-tal'!$H$24:$H$32,0),3), J$19='4. Reduktionsfaktorer, LENI-tal'!$S$12,INDEX('4. Reduktionsfaktorer, LENI-tal'!$H$33:$O$37,MATCH(J$21,'4. Reduktionsfaktorer, LENI-tal'!$H$33:$H$37,0),3), J$19='4. Reduktionsfaktorer, LENI-tal'!$T$12,INDEX('4. Reduktionsfaktorer, LENI-tal'!$H$38:$O$45,MATCH(J$21,'4. Reduktionsfaktorer, LENI-tal'!$H$38:$H$45,0),3), J$19='4. Reduktionsfaktorer, LENI-tal'!$U$12,INDEX('4. Reduktionsfaktorer, LENI-tal'!$H$46:$O$54,MATCH(J$21,'4. Reduktionsfaktorer, LENI-tal'!$H$46:$H$54,0),3)), IFERROR( INDEX( tblStrings[], MATCH( 1, (tblStrings[[Cell]:[Cell]]=AllStrings!$D$350) * (tblStrings[[Sheet]:[Sheet]]=AllStrings!$C$433), 0 ), MATCH(Språkval, tblStrings[#Headers], 0) ), ))} -> Fyll i byggnads- och rumstyp ovan | K44: {=IFERROR(_xlfn.IFS(K$19='4. Reduktionsfaktorer, LENI-tal'!$Q$12,INDEX('4. Reduktionsfaktorer, LENI-tal'!$H$13:$O$23,MATCH(K$21,'4. Reduktionsfaktorer, LENI-tal'!$H$13:$H$23,0),3), K$19='4. Reduktionsfaktorer, LENI-tal'!$R$12,INDEX('4. Reduktionsfaktorer, LENI-tal'!$H$24:$O$32,MATCH(K$21,'4. Reduktionsfaktorer, LENI-tal'!$H$24:$H$32,0),3), K$19='4. Reduktionsfaktorer, LENI-tal'!$S$12,INDEX('4. Reduktionsfaktorer, LENI-tal'!$H$33:$O$37,MATCH(K$21,'4. Reduktionsfaktorer, LENI-tal'!$H$33:$H$37,0),3), K$19='4. Reduktionsfaktorer, LENI-tal'!$T$12,INDEX('4. Reduktionsfaktorer, LENI-tal'!$H$38:$O$45,MATCH(K$21,'4. Reduktionsfaktorer, LENI-tal'!$H$38:$H$45,0),3), K$19='4. Reduktionsfaktorer, LENI-tal'!$U$12,INDEX('4. Reduktionsfaktorer, LENI-tal'!$H$46:$O$54,MATCH(K$21,'4. Reduktionsfaktorer, LENI-tal'!$H$46:$H$54,0),3)), IFERROR( INDEX( tblStrings[], MATCH( 1, (tblStrings[[Cell]:[Cell]]=AllStrings!$D$350) * (tblStrings[[Sheet]:[Sheet]]=AllStrings!$C$433), 0 ), MATCH(Språkval, tblStrings[#Headers], 0) ), ))} -> Fyll i byggnads- och rumstyp ovan | L44: {=IFERROR(_xlfn.IFS(L$19='4. Reduktionsfaktorer, LENI-tal'!$Q$12,INDEX('4. Reduktionsfaktorer, LENI-tal'!$H$13:$O$23,MATCH(L$21,'4. Reduktionsfaktorer, LENI-tal'!$H$13:$H$23,0),3), L$19='4. Reduktionsfaktorer, LENI-tal'!$R$12,INDEX('4. Reduktionsfaktorer, LENI-tal'!$H$24:$O$32,MATCH(L$21,'4. Reduktionsfaktorer, LENI-tal'!$H$24:$H$32,0),3), L$19='4. Reduktionsfaktorer, LENI-tal'!$S$12,INDEX('4. Reduktionsfaktorer, LENI-tal'!$H$33:$O$37,MATCH(L$21,'4. Reduktionsfaktorer, LENI-tal'!$H$33:$H$37,0),3), L$19='4. Reduktionsfaktorer, LENI-tal'!$T$12,INDEX('4. Reduktionsfaktorer, LENI-tal'!$H$38:$O$45,MATCH(L$21,'4. Reduktionsfaktorer, LENI-tal'!$H$38:$H$45,0),3), L$19='4. Reduktionsfaktorer, LENI-tal'!$U$12,INDEX('4. Reduktionsfaktorer, LENI-tal'!$H$46:$O$54,MATCH(L$21,'4. Reduktionsfaktorer, LENI-tal'!$H$46:$H$54,0),3)), IFERROR( INDEX( tblStrings[], MATCH( 1, (tblStrings[[Cell]:[Cell]]=AllStrings!$D$350) * (tblStrings[[Sheet]:[Sheet]]=AllStrings!$C$433), 0 ), MATCH(Språkval, tblStrings[#Headers], 0) ), ))} -> Fyll i byggnads- och rumstyp ovan | M44: {=IFERROR(_xlfn.IFS(M$19='4. Reduktionsfaktorer, LENI-tal'!$Q$12,INDEX('4. Reduktionsfaktorer, LENI-tal'!$H$13:$O$23,MATCH(M$21,'4. Reduktionsfaktorer, LENI-tal'!$H$13:$H$23,0),3), M$19='4. Reduktionsfaktorer, LENI-tal'!$R$12,INDEX('4. Reduktionsfaktorer, LENI-tal'!$H$24:$O$32,MATCH(M$21,'4. Reduktionsfaktorer, LENI-tal'!$H$24:$H$32,0),3), M$19='4. Reduktionsfaktorer, LENI-tal'!$S$12,INDEX('4. Reduktionsfaktorer, LENI-tal'!$H$33:$O$37,MATCH(M$21,'4. Reduktionsfaktorer, LENI-tal'!$H$33:$H$37,0),3), M$19='4. Reduktionsfaktorer, LENI-tal'!$T$12,INDEX('4. Reduktionsfaktorer, LENI-tal'!$H$38:$O$45,MATCH(M$21,'4. Reduktionsfaktorer, LENI-tal'!$H$38:$H$45,0),3), M$19='4. Reduktionsfaktorer, LENI-tal'!$U$12,INDEX('4. Reduktionsfaktorer, LENI-tal'!$H$46:$O$54,MATCH(M$21,'4. Reduktionsfaktorer, LENI-tal'!$H$46:$H$54,0),3)), IFERROR( INDEX( tblStrings[], MATCH( 1, (tblStrings[[Cell]:[Cell]]=AllStrings!$D$350) * (tblStrings[[Sheet]:[Sheet]]=AllStrings!$C$433), 0 ), MATCH(Språkval, tblStrings[#Headers], 0) ), ))} -> Fyll i byggnads- och rumstyp ovan | N44: {=IFERROR(_xlfn.IFS(N$19='4. Reduktionsfaktorer, LENI-tal'!$Q$12,INDEX('4. Reduktionsfaktorer, LENI-tal'!$H$13:$O$23,MATCH(N$21,'4. Reduktionsfaktorer, LENI-tal'!$H$13:$H$23,0),3), N$19='4. Reduktionsfaktorer, LENI-tal'!$R$12,INDEX('4. Reduktionsfaktorer, LENI-tal'!$H$24:$O$32,MATCH(N$21,'4. Reduktionsfaktorer, LENI-tal'!$H$24:$H$32,0),3), N$19='4. Reduktionsfaktorer, LENI-tal'!$S$12,INDEX('4. Reduktionsfaktorer, LENI-tal'!$H$33:$O$37,MATCH(N$21,'4. Reduktionsfaktorer, LENI-tal'!$H$33:$H$37,0),3), N$19='4. Reduktionsfaktorer, LENI-tal'!$T$12,INDEX('4. Reduktionsfaktorer, LENI-tal'!$H$38:$O$45,MATCH(N$21,'4. Reduktionsfaktorer, LENI-tal'!$H$38:$H$45,0),3), N$19='4. Reduktionsfaktorer, LENI-tal'!$U$12,INDEX('4. Reduktionsfaktorer, LENI-tal'!$H$46:$O$54,MATCH(N$21,'4. Reduktionsfaktorer, LENI-tal'!$H$46:$H$54,0),3)), IFERROR( INDEX( tblStrings[], MATCH( 1, (tblStrings[[Cell]:[Cell]]=AllStrings!$D$350) * (tblStrings[[Sheet]:[Sheet]]=AllStrings!$C$433), 0 ), MATCH(Språkval, tblStrings[#Headers], 0) ), ))} -> Fyll i byggnads- och rumstyp ovan | O44: {=IFERROR(_xlfn.IFS(O$19='4. Reduktionsfaktorer, LENI-tal'!$Q$12,INDEX('4. Reduktionsfaktorer, LENI-tal'!$H$13:$O$23,MATCH(O$21,'4. Reduktionsfaktorer, LENI-tal'!$H$13:$H$23,0),3), O$19='4. Reduktionsfaktorer, LENI-tal'!$R$12,INDEX('4. Reduktionsfaktorer, LENI-tal'!$H$24:$O$32,MATCH(O$21,'4. Reduktionsfaktorer, LENI-tal'!$H$24:$H$32,0),3), O$19='4. Reduktionsfaktorer, LENI-tal'!$S$12,INDEX('4. Reduktionsfaktorer, LENI-tal'!$H$33:$O$37,MATCH(O$21,'4. Reduktionsfaktorer, LENI-tal'!$H$33:$H$37,0),3), O$19='4. Reduktionsfaktorer, LENI-tal'!$T$12,INDEX('4. Reduktionsfaktorer, LENI-tal'!$H$38:$O$45,MATCH(O$21,'4. Reduktionsfaktorer, LENI-tal'!$H$38:$H$45,0),3), O$19='4. Reduktionsfaktorer, LENI-tal'!$U$12,INDEX('4. Reduktionsfaktorer, LENI-tal'!$H$46:$O$54,MATCH(O$21,'4. Reduktionsfaktorer, LENI-tal'!$H$46:$H$54,0),3)), IFERROR( INDEX( tblStrings[], MATCH( 1, (tblStrings[[Cell]:[Cell]]=AllStrings!$D$350) * (tblStrings[[Sheet]:[Sheet]]=AllStrings!$C$433), 0 ), MATCH(Språkval, tblStrings[#Headers], 0) ), ))} -> Fyll i byggnads- och rumstyp ovan | P44: {=IFERROR(_xlfn.IFS(P$19='4. Reduktionsfaktorer, LENI-tal'!$Q$12,INDEX('4. Reduktionsfaktorer, LENI-tal'!$H$13:$O$23,MATCH(P$21,'4. Reduktionsfaktorer, LENI-tal'!$H$13:$H$23,0),3), P$19='4. Reduktionsfaktorer, LENI-tal'!$R$12,INDEX('4. Reduktionsfaktorer, LENI-tal'!$H$24:$O$32,MATCH(P$21,'4. Reduktionsfaktorer, LENI-tal'!$H$24:$H$32,0),3), P$19='4. Reduktionsfaktorer, LENI-tal'!$S$12,INDEX('4. Reduktionsfaktorer, LENI-tal'!$H$33:$O$37,MATCH(P$21,'4. Reduktionsfaktorer, LENI-tal'!$H$33:$H$37,0),3), P$19='4. Reduktionsfaktorer, LENI-tal'!$T$12,INDEX('4. Reduktionsfaktorer, LENI-tal'!$H$38:$O$45,MATCH(P$21,'4. Reduktionsfaktorer, LENI-tal'!$H$38:$H$45,0),3), P$19='4. Reduktionsfaktorer, LENI-tal'!$U$12,INDEX('4. Reduktionsfaktorer, LENI-tal'!$H$46:$O$54,MATCH(P$21,'4. Reduktionsfaktorer, LENI-tal'!$H$46:$H$54,0),3)), IFERROR( INDEX( tblStrings[], MATCH( 1, (tblStrings[[Cell]:[Cell]]=AllStrings!$D$350) * (tblStrings[[Sheet]:[Sheet]]=AllStrings!$C$433), 0 ), MATCH(Språkval, tblStrings[#Headers], 0) ), ))} -> Fyll i byggnads- och rumstyp ovan | ... R44: {=IFERROR(_xlfn.IFS(R$19='4. Reduktionsfaktorer, LENI-tal'!$Q$12,INDEX('4. Reduktionsfaktorer, LENI-tal'!$H$13:$O$23,MATCH(R$21,'4. Reduktionsfaktorer, LENI-tal'!$H$13:$H$23,0),3), R$19='4. Reduktionsfaktorer, LENI-tal'!$R$12,INDEX('4. Reduktionsfaktorer, LENI-tal'!$H$24:$O$32,MATCH(R$21,'4. Reduktionsfaktorer, LENI-tal'!$H$24:$H$32,0),3), R$19='4. Reduktionsfaktorer, LENI-tal'!$S$12,INDEX('4. Reduktionsfaktorer, LENI-tal'!$H$33:$O$37,MATCH(R$21,'4. Reduktionsfaktorer, LENI-tal'!$H$33:$H$37,0),3), R$19='4. Reduktionsfaktorer, LENI-tal'!$T$12,INDEX('4. Reduktionsfaktorer, LENI-tal'!$H$38:$O$45,MATCH(R$21,'4. Reduktionsfaktorer, LENI-tal'!$H$38:$H$45,0),3), R$19='4. Reduktionsfaktorer, LENI-tal'!$U$12,INDEX('4. Reduktionsfaktorer, LENI-tal'!$H$46:$O$54,MATCH(R$21,'4. Reduktionsfaktorer, LENI-tal'!$H$46:$H$54,0),3)), IFERROR( INDEX( tblStrings[], MATCH( 1, (tblStrings[[Cell]:[Cell]]=AllStrings!$D$350) * (tblStrings[[Sheet]:[Sheet]]=AllStrings!$C$433), 0 ), MATCH(Språkval, tblStrings[#Headers], 0) ), ))} -> Fyll i byggnads- och rumstyp ovan
B45: 2.7 | C45: =$C33 -> Reduktionsfaktor närvaro-/frånvarostyrning | I45: {=IFERROR(_xlfn.IFS(I$19='4. Reduktionsfaktorer, LENI-tal'!$Q$12,INDEX('4. Reduktionsfaktorer, LENI-tal'!$H$13:$O$23,MATCH(I$21,'4. Reduktionsfaktorer, LENI-tal'!$H$13:$H$23,0),4), I$19='4. Reduktionsfaktorer, LENI-tal'!$R$12,INDEX('4. Reduktionsfaktorer, LENI-tal'!$H$24:$O$32,MATCH(I$21,'4. Reduktionsfaktorer, LENI-tal'!$H$24:$H$32,0),4), I$19='4. Reduktionsfaktorer, LENI-tal'!$S$12,INDEX('4. Reduktionsfaktorer, LENI-tal'!$H$33:$O$37,MATCH(I$21,'4. Reduktionsfaktorer, LENI-tal'!$H$33:$H$37,0),4), I$19='4. Reduktionsfaktorer, LENI-tal'!$T$12,INDEX('4. Reduktionsfaktorer, LENI-tal'!$H$38:$O$45,MATCH(I$21,'4. Reduktionsfaktorer, LENI-tal'!$H$38:$H$45,0),4), I$19='4. Reduktionsfaktorer, LENI-tal'!$U$12,INDEX('4. Reduktionsfaktorer, LENI-tal'!$H$46:$O$54,MATCH(I$21,'4. Reduktionsfaktorer, LENI-tal'!$H$46:$H$54,0),4)), IFERROR( INDEX( tblStrings[], MATCH( 1, (tblStrings[[Cell]:[Cell]]=AllStrings!$D$350) * (tblStrings[[Sheet]:[Sheet]]=AllStrings!$C$433), 0 ), MATCH(Språkval, tblStrings[#Headers], 0) ), ))} -> Fyll i byggnads- och rumstyp ovan | J45: {=IFERROR(_xlfn.IFS(J$19='4. Reduktionsfaktorer, LENI-tal'!$Q$12,INDEX('4. Reduktionsfaktorer, LENI-tal'!$H$13:$O$23,MATCH(J$21,'4. Reduktionsfaktorer, LENI-tal'!$H$13:$H$23,0),4), J$19='4. Reduktionsfaktorer, LENI-tal'!$R$12,INDEX('4. Reduktionsfaktorer, LENI-tal'!$H$24:$O$32,MATCH(J$21,'4. Reduktionsfaktorer, LENI-tal'!$H$24:$H$32,0),4), J$19='4. Reduktionsfaktorer, LENI-tal'!$S$12,INDEX('4. Reduktionsfaktorer, LENI-tal'!$H$33:$O$37,MATCH(J$21,'4. Reduktionsfaktorer, LENI-tal'!$H$33:$H$37,0),4), J$19='4. Reduktionsfaktorer, LENI-tal'!$T$12,INDEX('4. Reduktionsfaktorer, LENI-tal'!$H$38:$O$45,MATCH(J$21,'4. Reduktionsfaktorer, LENI-tal'!$H$38:$H$45,0),4), J$19='4. Reduktionsfaktorer, LENI-tal'!$U$12,INDEX('4. Reduktionsfaktorer, LENI-tal'!$H$46:$O$54,MATCH(J$21,'4. Reduktionsfaktorer, LENI-tal'!$H$46:$H$54,0),4)), IFERROR( INDEX( tblStrings[], MATCH( 1, (tblStrings[[Cell]:[Cell]]=AllStrings!$D$350) * (tblStrings[[Sheet]:[Sheet]]=AllStrings!$C$433), 0 ), MATCH(Språkval, tblStrings[#Headers], 0) ), ))} -> Fyll i byggnads- och rumstyp ovan | K45: {=IFERROR(_xlfn.IFS(K$19='4. Reduktionsfaktorer, LENI-tal'!$Q$12,INDEX('4. Reduktionsfaktorer, LENI-tal'!$H$13:$O$23,MATCH(K$21,'4. Reduktionsfaktorer, LENI-tal'!$H$13:$H$23,0),4), K$19='4. Reduktionsfaktorer, LENI-tal'!$R$12,INDEX('4. Reduktionsfaktorer, LENI-tal'!$H$24:$O$32,MATCH(K$21,'4. Reduktionsfaktorer, LENI-tal'!$H$24:$H$32,0),4), K$19='4. Reduktionsfaktorer, LENI-tal'!$S$12,INDEX('4. Reduktionsfaktorer, LENI-tal'!$H$33:$O$37,MATCH(K$21,'4. Reduktionsfaktorer, LENI-tal'!$H$33:$H$37,0),4), K$19='4. Reduktionsfaktorer, LENI-tal'!$T$12,INDEX('4. Reduktionsfaktorer, LENI-tal'!$H$38:$O$45,MATCH(K$21,'4. Reduktionsfaktorer, LENI-tal'!$H$38:$H$45,0),4), K$19='4. Reduktionsfaktorer, LENI-tal'!$U$12,INDEX('4. Reduktionsfaktorer, LENI-tal'!$H$46:$O$54,MATCH(K$21,'4. Reduktionsfaktorer, LENI-tal'!$H$46:$H$54,0),4)), IFERROR( INDEX( tblStrings[], MATCH( 1, (tblStrings[[Cell]:[Cell]]=AllStrings!$D$350) * (tblStrings[[Sheet]:[Sheet]]=AllStrings!$C$433), 0 ), MATCH(Språkval, tblStrings[#Headers], 0) ), ))} -> Fyll i byggnads- och rumstyp ovan | L45: {=IFERROR(_xlfn.IFS(L$19='4. Reduktionsfaktorer, LENI-tal'!$Q$12,INDEX('4. Reduktionsfaktorer, LENI-tal'!$H$13:$O$23,MATCH(L$21,'4. Reduktionsfaktorer, LENI-tal'!$H$13:$H$23,0),4), L$19='4. Reduktionsfaktorer, LENI-tal'!$R$12,INDEX('4. Reduktionsfaktorer, LENI-tal'!$H$24:$O$32,MATCH(L$21,'4. Reduktionsfaktorer, LENI-tal'!$H$24:$H$32,0),4), L$19='4. Reduktionsfaktorer, LENI-tal'!$S$12,INDEX('4. Reduktionsfaktorer, LENI-tal'!$H$33:$O$37,MATCH(L$21,'4. Reduktionsfaktorer, LENI-tal'!$H$33:$H$37,0),4), L$19='4. Reduktionsfaktorer, LENI-tal'!$T$12,INDEX('4. Reduktionsfaktorer, LENI-tal'!$H$38:$O$45,MATCH(L$21,'4. Reduktionsfaktorer, LENI-tal'!$H$38:$H$45,0),4), L$19='4. Reduktionsfaktorer, LENI-tal'!$U$12,INDEX('4. Reduktionsfaktorer, LENI-tal'!$H$46:$O$54,MATCH(L$21,'4. Reduktionsfaktorer, LENI-tal'!$H$46:$H$54,0),4)), IFERROR( INDEX( tblStrings[], MATCH( 1, (tblStrings[[Cell]:[Cell]]=AllStrings!$D$350) * (tblStrings[[Sheet]:[Sheet]]=AllStrings!$C$433), 0 ), MATCH(Språkval, tblStrings[#Headers], 0) ), ))} -> Fyll i byggnads- och rumstyp ovan | M45: {=IFERROR(_xlfn.IFS(M$19='4. Reduktionsfaktorer, LENI-tal'!$Q$12,INDEX('4. Reduktionsfaktorer, LENI-tal'!$H$13:$O$23,MATCH(M$21,'4. Reduktionsfaktorer, LENI-tal'!$H$13:$H$23,0),4), M$19='4. Reduktionsfaktorer, LENI-tal'!$R$12,INDEX('4. Reduktionsfaktorer, LENI-tal'!$H$24:$O$32,MATCH(M$21,'4. Reduktionsfaktorer, LENI-tal'!$H$24:$H$32,0),4), M$19='4. Reduktionsfaktorer, LENI-tal'!$S$12,INDEX('4. Reduktionsfaktorer, LENI-tal'!$H$33:$O$37,MATCH(M$21,'4. Reduktionsfaktorer, LENI-tal'!$H$33:$H$37,0),4), M$19='4. Reduktionsfaktorer, LENI-tal'!$T$12,INDEX('4. Reduktionsfaktorer, LENI-tal'!$H$38:$O$45,MATCH(M$21,'4. Reduktionsfaktorer, LENI-tal'!$H$38:$H$45,0),4), M$19='4. Reduktionsfaktorer, LENI-tal'!$U$12,INDEX('4. Reduktionsfaktorer, LENI-tal'!$H$46:$O$54,MATCH(M$21,'4. Reduktionsfaktorer, LENI-tal'!$H$46:$H$54,0),4)), IFERROR( INDEX( tblStrings[], MATCH( 1, (tblStrings[[Cell]:[Cell]]=AllStrings!$D$350) * (tblStrings[[Sheet]:[Sheet]]=AllStrings!$C$433), 0 ), MATCH(Språkval, tblStrings[#Headers], 0) ), ))} -> Fyll i byggnads- och rumstyp ovan | N45: {=IFERROR(_xlfn.IFS(N$19='4. Reduktionsfaktorer, LENI-tal'!$Q$12,INDEX('4. Reduktionsfaktorer, LENI-tal'!$H$13:$O$23,MATCH(N$21,'4. Reduktionsfaktorer, LENI-tal'!$H$13:$H$23,0),4), N$19='4. Reduktionsfaktorer, LENI-tal'!$R$12,INDEX('4. Reduktionsfaktorer, LENI-tal'!$H$24:$O$32,MATCH(N$21,'4. Reduktionsfaktorer, LENI-tal'!$H$24:$H$32,0),4), N$19='4. Reduktionsfaktorer, LENI-tal'!$S$12,INDEX('4. Reduktionsfaktorer, LENI-tal'!$H$33:$O$37,MATCH(N$21,'4. Reduktionsfaktorer, LENI-tal'!$H$33:$H$37,0),4), N$19='4. Reduktionsfaktorer, LENI-tal'!$T$12,INDEX('4. Reduktionsfaktorer, LENI-tal'!$H$38:$O$45,MATCH(N$21,'4. Reduktionsfaktorer, LENI-tal'!$H$38:$H$45,0),4), N$19='4. Reduktionsfaktorer, LENI-tal'!$U$12,INDEX('4. Reduktionsfaktorer, LENI-tal'!$H$46:$O$54,MATCH(N$21,'4. Reduktionsfaktorer, LENI-tal'!$H$46:$H$54,0),4)), IFERROR( INDEX( tblStrings[], MATCH( 1, (tblStrings[[Cell]:[Cell]]=AllStrings!$D$350) * (tblStrings[[Sheet]:[Sheet]]=AllStrings!$C$433), 0 ), MATCH(Språkval, tblStrings[#Headers], 0) ), ))} -> Fyll i byggnads- och rumstyp ovan | O45: {=IFERROR(_xlfn.IFS(O$19='4. Reduktionsfaktorer, LENI-tal'!$Q$12,INDEX('4. Reduktionsfaktorer, LENI-tal'!$H$13:$O$23,MATCH(O$21,'4. Reduktionsfaktorer, LENI-tal'!$H$13:$H$23,0),4), O$19='4. Reduktionsfaktorer, LENI-tal'!$R$12,INDEX('4. Reduktionsfaktorer, LENI-tal'!$H$24:$O$32,MATCH(O$21,'4. Reduktionsfaktorer, LENI-tal'!$H$24:$H$32,0),4), O$19='4. Reduktionsfaktorer, LENI-tal'!$S$12,INDEX('4. Reduktionsfaktorer, LENI-tal'!$H$33:$O$37,MATCH(O$21,'4. Reduktionsfaktorer, LENI-tal'!$H$33:$H$37,0),4), O$19='4. Reduktionsfaktorer, LENI-tal'!$T$12,INDEX('4. Reduktionsfaktorer, LENI-tal'!$H$38:$O$45,MATCH(O$21,'4. Reduktionsfaktorer, LENI-tal'!$H$38:$H$45,0),4), O$19='4. Reduktionsfaktorer, LENI-tal'!$U$12,INDEX('4. Reduktionsfaktorer, LENI-tal'!$H$46:$O$54,MATCH(O$21,'4. Reduktionsfaktorer, LENI-tal'!$H$46:$H$54,0),4)), IFERROR( INDEX( tblStrings[], MATCH( 1, (tblStrings[[Cell]:[Cell]]=AllStrings!$D$350) * (tblStrings[[Sheet]:[Sheet]]=AllStrings!$C$433), 0 ), MATCH(Språkval, tblStrings[#Headers], 0) ), ))} -> Fyll i byggnads- och rumstyp ovan | P45: {=IFERROR(_xlfn.IFS(P$19='4. Reduktionsfaktorer, LENI-tal'!$Q$12,INDEX('4. Reduktionsfaktorer, LENI-tal'!$H$13:$O$23,MATCH(P$21,'4. Reduktionsfaktorer, LENI-tal'!$H$13:$H$23,0),4), P$19='4. Reduktionsfaktorer, LENI-tal'!$R$12,INDEX('4. Reduktionsfaktorer, LENI-tal'!$H$24:$O$32,MATCH(P$21,'4. Reduktionsfaktorer, LENI-tal'!$H$24:$H$32,0),4), P$19='4. Reduktionsfaktorer, LENI-tal'!$S$12,INDEX('4. Reduktionsfaktorer, LENI-tal'!$H$33:$O$37,MATCH(P$21,'4. Reduktionsfaktorer, LENI-tal'!$H$33:$H$37,0),4), P$19='4. Reduktionsfaktorer, LENI-tal'!$T$12,INDEX('4. Reduktionsfaktorer, LENI-tal'!$H$38:$O$45,MATCH(P$21,'4. Reduktionsfaktorer, LENI-tal'!$H$38:$H$45,0),4), P$19='4. Reduktionsfaktorer, LENI-tal'!$U$12,INDEX('4. Reduktionsfaktorer, LENI-tal'!$H$46:$O$54,MATCH(P$21,'4. Reduktionsfaktorer, LENI-tal'!$H$46:$H$54,0),4)), IFERROR( INDEX( tblStrings[], MATCH( 1, (tblStrings[[Cell]:[Cell]]=AllStrings!$D$350) * (tblStrings[[Sheet]:[Sheet]]=AllStrings!$C$433), 0 ), MATCH(Språkval, tblStrings[#Headers], 0) ), ))} -> Fyll i byggnads- och rumstyp ovan | ... R45: {=IFERROR(_xlfn.IFS(R$19='4. Reduktionsfaktorer, LENI-tal'!$Q$12,INDEX('4. Reduktionsfaktorer, LENI-tal'!$H$13:$O$23,MATCH(R$21,'4. Reduktionsfaktorer, LENI-tal'!$H$13:$H$23,0),4), R$19='4. Reduktionsfaktorer, LENI-tal'!$R$12,INDEX('4. Reduktionsfaktorer, LENI-tal'!$H$24:$O$32,MATCH(R$21,'4. Reduktionsfaktorer, LENI-tal'!$H$24:$H$32,0),4), R$19='4. Reduktionsfaktorer, LENI-tal'!$S$12,INDEX('4. Reduktionsfaktorer, LENI-tal'!$H$33:$O$37,MATCH(R$21,'4. Reduktionsfaktorer, LENI-tal'!$H$33:$H$37,0),4), R$19='4. Reduktionsfaktorer, LENI-tal'!$T$12,INDEX('4. Reduktionsfaktorer, LENI-tal'!$H$38:$O$45,MATCH(R$21,'4. Reduktionsfaktorer, LENI-tal'!$H$38:$H$45,0),4), R$19='4. Reduktionsfaktorer, LENI-tal'!$U$12,INDEX('4. Reduktionsfaktorer, LENI-tal'!$H$46:$O$54,MATCH(R$21,'4. Reduktionsfaktorer, LENI-tal'!$H$46:$H$54,0),4)), IFERROR( INDEX( tblStrings[], MATCH( 1, (tblStrings[[Cell]:[Cell]]=AllStrings!$D$350) * (tblStrings[[Sheet]:[Sheet]]=AllStrings!$C$433), 0 ), MATCH(Språkval, tblStrings[#Headers], 0) ), ))} -> Fyll i byggnads- och rumstyp ovan
B46: 2.8 | C46: =$C34 -> Reduktionsfaktor dagsljusstyrning | I46: {=IFERROR(_xlfn.IFS(I$19='4. Reduktionsfaktorer, LENI-tal'!$Q$12,INDEX('4. Reduktionsfaktorer, LENI-tal'!$H$13:$O$23,MATCH(I$21,'4. Reduktionsfaktorer, LENI-tal'!$H$13:$H$23,0),5), I$19='4. Reduktionsfaktorer, LENI-tal'!$R$12,INDEX('4. Reduktionsfaktorer, LENI-tal'!$H$24:$O$32,MATCH(I$21,'4. Reduktionsfaktorer, LENI-tal'!$H$24:$H$32,0),5), I$19='4. Reduktionsfaktorer, LENI-tal'!$S$12,INDEX('4. Reduktionsfaktorer, LENI-tal'!$H$33:$O$37,MATCH(I$21,'4. Reduktionsfaktorer, LENI-tal'!$H$33:$H$37,0),5), I$19='4. Reduktionsfaktorer, LENI-tal'!$T$12,INDEX('4. Reduktionsfaktorer, LENI-tal'!$H$38:$O$45,MATCH(I$21,'4. Reduktionsfaktorer, LENI-tal'!$H$38:$H$45,0),5), I$19='4. Reduktionsfaktorer, LENI-tal'!$U$12,INDEX('4. Reduktionsfaktorer, LENI-tal'!$H$46:$O$54,MATCH(I$21,'4. Reduktionsfaktorer, LENI-tal'!$H$46:$H$54,0),5)), IFERROR( INDEX( tblStrings[], MATCH( 1, (tblStrings[[Cell]:[Cell]]=AllStrings!$D$350) * (tblStrings[[Sheet]:[Sheet]]=AllStrings!$C$433), 0 ), MATCH(Språkval, tblStrings[#Headers], 0) ), ))} -> Fyll i byggnads- och rumstyp ovan | J46: {=IFERROR(_xlfn.IFS(J$19='4. Reduktionsfaktorer, LENI-tal'!$Q$12,INDEX('4. Reduktionsfaktorer, LENI-tal'!$H$13:$O$23,MATCH(J$21,'4. Reduktionsfaktorer, LENI-tal'!$H$13:$H$23,0),5), J$19='4. Reduktionsfaktorer, LENI-tal'!$R$12,INDEX('4. Reduktionsfaktorer, LENI-tal'!$H$24:$O$32,MATCH(J$21,'4. Reduktionsfaktorer, LENI-tal'!$H$24:$H$32,0),5), J$19='4. Reduktionsfaktorer, LENI-tal'!$S$12,INDEX('4. Reduktionsfaktorer, LENI-tal'!$H$33:$O$37,MATCH(J$21,'4. Reduktionsfaktorer, LENI-tal'!$H$33:$H$37,0),5), J$19='4. Reduktionsfaktorer, LENI-tal'!$T$12,INDEX('4. Reduktionsfaktorer, LENI-tal'!$H$38:$O$45,MATCH(J$21,'4. Reduktionsfaktorer, LENI-tal'!$H$38:$H$45,0),5), J$19='4. Reduktionsfaktorer, LENI-tal'!$U$12,INDEX('4. Reduktionsfaktorer, LENI-tal'!$H$46:$O$54,MATCH(J$21,'4. Reduktionsfaktorer, LENI-tal'!$H$46:$H$54,0),5)), IFERROR( INDEX( tblStrings[], MATCH( 1, (tblStrings[[Cell]:[Cell]]=AllStrings!$D$350) * (tblStrings[[Sheet]:[Sheet]]=AllStrings!$C$433), 0 ), MATCH(Språkval, tblStrings[#Headers], 0) ), ))} -> Fyll i byggnads- och rumstyp ovan | K46: {=IFERROR(_xlfn.IFS(K$19='4. Reduktionsfaktorer, LENI-tal'!$Q$12,INDEX('4. Reduktionsfaktorer, LENI-tal'!$H$13:$O$23,MATCH(K$21,'4. Reduktionsfaktorer, LENI-tal'!$H$13:$H$23,0),5), K$19='4. Reduktionsfaktorer, LENI-tal'!$R$12,INDEX('4. Reduktionsfaktorer, LENI-tal'!$H$24:$O$32,MATCH(K$21,'4. Reduktionsfaktorer, LENI-tal'!$H$24:$H$32,0),5), K$19='4. Reduktionsfaktorer, LENI-tal'!$S$12,INDEX('4. Reduktionsfaktorer, LENI-tal'!$H$33:$O$37,MATCH(K$21,'4. Reduktionsfaktorer, LENI-tal'!$H$33:$H$37,0),5), K$19='4. Reduktionsfaktorer, LENI-tal'!$T$12,INDEX('4. Reduktionsfaktorer, LENI-tal'!$H$38:$O$45,MATCH(K$21,'4. Reduktionsfaktorer, LENI-tal'!$H$38:$H$45,0),5), K$19='4. Reduktionsfaktorer, LENI-tal'!$U$12,INDEX('4. Reduktionsfaktorer, LENI-tal'!$H$46:$O$54,MATCH(K$21,'4. Reduktionsfaktorer, LENI-tal'!$H$46:$H$54,0),5)), IFERROR( INDEX( tblStrings[], MATCH( 1, (tblStrings[[Cell]:[Cell]]=AllStrings!$D$350) * (tblStrings[[Sheet]:[Sheet]]=AllStrings!$C$433), 0 ), MATCH(Språkval, tblStrings[#Headers], 0) ), ))} -> Fyll i byggnads- och rumstyp ovan | L46: {=IFERROR(_xlfn.IFS(L$19='4. Reduktionsfaktorer, LENI-tal'!$Q$12,INDEX('4. Reduktionsfaktorer, LENI-tal'!$H$13:$O$23,MATCH(L$21,'4. Reduktionsfaktorer, LENI-tal'!$H$13:$H$23,0),5), L$19='4. Reduktionsfaktorer, LENI-tal'!$R$12,INDEX('4. Reduktionsfaktorer, LENI-tal'!$H$24:$O$32,MATCH(L$21,'4. Reduktionsfaktorer, LENI-tal'!$H$24:$H$32,0),5), L$19='4. Reduktionsfaktorer, LENI-tal'!$S$12,INDEX('4. Reduktionsfaktorer, LENI-tal'!$H$33:$O$37,MATCH(L$21,'4. Reduktionsfaktorer, LENI-tal'!$H$33:$H$37,0),5), L$19='4. Reduktionsfaktorer, LENI-tal'!$T$12,INDEX('4. Reduktionsfaktorer, LENI-tal'!$H$38:$O$45,MATCH(L$21,'4. Reduktionsfaktorer, LENI-tal'!$H$38:$H$45,0),5), L$19='4. Reduktionsfaktorer, LENI-tal'!$U$12,INDEX('4. Reduktionsfaktorer, LENI-tal'!$H$46:$O$54,MATCH(L$21,'4. Reduktionsfaktorer, LENI-tal'!$H$46:$H$54,0),5)), IFERROR( INDEX( tblStrings[], MATCH( 1, (tblStrings[[Cell]:[Cell]]=AllStrings!$D$350) * (tblStrings[[Sheet]:[Sheet]]=AllStrings!$C$433), 0 ), MATCH(Språkval, tblStrings[#Headers], 0) ), ))} -> Fyll i byggnads- och rumstyp ovan | M46: {=IFERROR(_xlfn.IFS(M$19='4. Reduktionsfaktorer, LENI-tal'!$Q$12,INDEX('4. Reduktionsfaktorer, LENI-tal'!$H$13:$O$23,MATCH(M$21,'4. Reduktionsfaktorer, LENI-tal'!$H$13:$H$23,0),5), M$19='4. Reduktionsfaktorer, LENI-tal'!$R$12,INDEX('4. Reduktionsfaktorer, LENI-tal'!$H$24:$O$32,MATCH(M$21,'4. Reduktionsfaktorer, LENI-tal'!$H$24:$H$32,0),5), M$19='4. Reduktionsfaktorer, LENI-tal'!$S$12,INDEX('4. Reduktionsfaktorer, LENI-tal'!$H$33:$O$37,MATCH(M$21,'4. Reduktionsfaktorer, LENI-tal'!$H$33:$H$37,0),5), M$19='4. Reduktionsfaktorer, LENI-tal'!$T$12,INDEX('4. Reduktionsfaktorer, LENI-tal'!$H$38:$O$45,MATCH(M$21,'4. Reduktionsfaktorer, LENI-tal'!$H$38:$H$45,0),5), M$19='4. Reduktionsfaktorer, LENI-tal'!$U$12,INDEX('4. Reduktionsfaktorer, LENI-tal'!$H$46:$O$54,MATCH(M$21,'4. Reduktionsfaktorer, LENI-tal'!$H$46:$H$54,0),5)), IFERROR( INDEX( tblStrings[], MATCH( 1, (tblStrings[[Cell]:[Cell]]=AllStrings!$D$350) * (tblStrings[[Sheet]:[Sheet]]=AllStrings!$C$433), 0 ), MATCH(Språkval, tblStrings[#Headers], 0) ), ))} -> Fyll i byggnads- och rumstyp ovan | N46: {=IFERROR(_xlfn.IFS(N$19='4. Reduktionsfaktorer, LENI-tal'!$Q$12,INDEX('4. Reduktionsfaktorer, LENI-tal'!$H$13:$O$23,MATCH(N$21,'4. Reduktionsfaktorer, LENI-tal'!$H$13:$H$23,0),5), N$19='4. Reduktionsfaktorer, LENI-tal'!$R$12,INDEX('4. Reduktionsfaktorer, LENI-tal'!$H$24:$O$32,MATCH(N$21,'4. Reduktionsfaktorer, LENI-tal'!$H$24:$H$32,0),5), N$19='4. Reduktionsfaktorer, LENI-tal'!$S$12,INDEX('4. Reduktionsfaktorer, LENI-tal'!$H$33:$O$37,MATCH(N$21,'4. Reduktionsfaktorer, LENI-tal'!$H$33:$H$37,0),5), N$19='4. Reduktionsfaktorer, LENI-tal'!$T$12,INDEX('4. Reduktionsfaktorer, LENI-tal'!$H$38:$O$45,MATCH(N$21,'4. Reduktionsfaktorer, LENI-tal'!$H$38:$H$45,0),5), N$19='4. Reduktionsfaktorer, LENI-tal'!$U$12,INDEX('4. Reduktionsfaktorer, LENI-tal'!$H$46:$O$54,MATCH(N$21,'4. Reduktionsfaktorer, LENI-tal'!$H$46:$H$54,0),5)), IFERROR( INDEX( tblStrings[], MATCH( 1, (tblStrings[[Cell]:[Cell]]=AllStrings!$D$350) * (tblStrings[[Sheet]:[Sheet]]=AllStrings!$C$433), 0 ), MATCH(Språkval, tblStrings[#Headers], 0) ), ))} -> Fyll i byggnads- och rumstyp ovan | O46: {=IFERROR(_xlfn.IFS(O$19='4. Reduktionsfaktorer, LENI-tal'!$Q$12,INDEX('4. Reduktionsfaktorer, LENI-tal'!$H$13:$O$23,MATCH(O$21,'4. Reduktionsfaktorer, LENI-tal'!$H$13:$H$23,0),5), O$19='4. Reduktionsfaktorer, LENI-tal'!$R$12,INDEX('4. Reduktionsfaktorer, LENI-tal'!$H$24:$O$32,MATCH(O$21,'4. Reduktionsfaktorer, LENI-tal'!$H$24:$H$32,0),5), O$19='4. Reduktionsfaktorer, LENI-tal'!$S$12,INDEX('4. Reduktionsfaktorer, LENI-tal'!$H$33:$O$37,MATCH(O$21,'4. Reduktionsfaktorer, LENI-tal'!$H$33:$H$37,0),5), O$19='4. Reduktionsfaktorer, LENI-tal'!$T$12,INDEX('4. Reduktionsfaktorer, LENI-tal'!$H$38:$O$45,MATCH(O$21,'4. Reduktionsfaktorer, LENI-tal'!$H$38:$H$45,0),5), O$19='4. Reduktionsfaktorer, LENI-tal'!$U$12,INDEX('4. Reduktionsfaktorer, LENI-tal'!$H$46:$O$54,MATCH(O$21,'4. Reduktionsfaktorer, LENI-tal'!$H$46:$H$54,0),5)), IFERROR( INDEX( tblStrings[], MATCH( 1, (tblStrings[[Cell]:[Cell]]=AllStrings!$D$350) * (tblStrings[[Sheet]:[Sheet]]=AllStrings!$C$433), 0 ), MATCH(Språkval, tblStrings[#Headers], 0) ), ))} -> Fyll i byggnads- och rumstyp ovan | P46: {=IFERROR(_xlfn.IFS(P$19='4. Reduktionsfaktorer, LENI-tal'!$Q$12,INDEX('4. Reduktionsfaktorer, LENI-tal'!$H$13:$O$23,MATCH(P$21,'4. Reduktionsfaktorer, LENI-tal'!$H$13:$H$23,0),5), P$19='4. Reduktionsfaktorer, LENI-tal'!$R$12,INDEX('4. Reduktionsfaktorer, LENI-tal'!$H$24:$O$32,MATCH(P$21,'4. Reduktionsfaktorer, LENI-tal'!$H$24:$H$32,0),5), P$19='4. Reduktionsfaktorer, LENI-tal'!$S$12,INDEX('4. Reduktionsfaktorer, LENI-tal'!$H$33:$O$37,MATCH(P$21,'4. Reduktionsfaktorer, LENI-tal'!$H$33:$H$37,0),5), P$19='4. Reduktionsfaktorer, LENI-tal'!$T$12,INDEX('4. Reduktionsfaktorer, LENI-tal'!$H$38:$O$45,MATCH(P$21,'4. Reduktionsfaktorer, LENI-tal'!$H$38:$H$45,0),5), P$19='4. Reduktionsfaktorer, LENI-tal'!$U$12,INDEX('4. Reduktionsfaktorer, LENI-tal'!$H$46:$O$54,MATCH(P$21,'4. Reduktionsfaktorer, LENI-tal'!$H$46:$H$54,0),5)), IFERROR( INDEX( tblStrings[], MATCH( 1, (tblStrings[[Cell]:[Cell]]=AllStrings!$D$350) * (tblStrings[[Sheet]:[Sheet]]=AllStrings!$C$433), 0 ), MATCH(Språkval, tblStrings[#Headers], 0) ), ))} -> Fyll i byggnads- och rumstyp ovan | ... R46: {=IFERROR(_xlfn.IFS(R$19='4. Reduktionsfaktorer, LENI-tal'!$Q$12,INDEX('4. Reduktionsfaktorer, LENI-tal'!$H$13:$O$23,MATCH(R$21,'4. Reduktionsfaktorer, LENI-tal'!$H$13:$H$23,0),5), R$19='4. Reduktionsfaktorer, LENI-tal'!$R$12,INDEX('4. Reduktionsfaktorer, LENI-tal'!$H$24:$O$32,MATCH(R$21,'4. Reduktionsfaktorer, LENI-tal'!$H$24:$H$32,0),5), R$19='4. Reduktionsfaktorer, LENI-tal'!$S$12,INDEX('4. Reduktionsfaktorer, LENI-tal'!$H$33:$O$37,MATCH(R$21,'4. Reduktionsfaktorer, LENI-tal'!$H$33:$H$37,0),5), R$19='4. Reduktionsfaktorer, LENI-tal'!$T$12,INDEX('4. Reduktionsfaktorer, LENI-tal'!$H$38:$O$45,MATCH(R$21,'4. Reduktionsfaktorer, LENI-tal'!$H$38:$H$45,0),5), R$19='4. Reduktionsfaktorer, LENI-tal'!$U$12,INDEX('4. Reduktionsfaktorer, LENI-tal'!$H$46:$O$54,MATCH(R$21,'4. Reduktionsfaktorer, LENI-tal'!$H$46:$H$54,0),5)), IFERROR( INDEX( tblStrings[], MATCH( 1, (tblStrings[[Cell]:[Cell]]=AllStrings!$D$350) * (tblStrings[[Sheet]:[Sheet]]=AllStrings!$C$433), 0 ), MATCH(Språkval, tblStrings[#Headers], 0) ), ))} -> Fyll i byggnads- och rumstyp ovan
B47: 2.9 | C47: =$C$35 -> Total reduktionsfaktor för styrning | I47: =IF(IF(I43=$I$233,I44,IF(I43=$I$234,I44*I45,IF(I43=$I$235,I44*I45*I46,1)))=0,"Fyll i 2.6-2.8",IF(I43=$I$233,I44,IF(I43=$I$234,I44*I45,IF(I43=$I$235,I44*I45*I46,1)))) -> 1 | J47: =IF(IF(J43=$I$233,J44,IF(J43=$I$234,J44*J45,IF(J43=$I$235,J44*J45*J46,1)))=0,"Fyll i 2.6-2.8",IF(J43=$I$233,J44,IF(J43=$I$234,J44*J45,IF(J43=$I$235,J44*J45*J46,1)))) -> 1 | K47: =IF(IF(K43=$I$233,K44,IF(K43=$I$234,K44*K45,IF(K43=$I$235,K44*K45*K46,1)))=0,"Fyll i 2.6-2.8",IF(K43=$I$233,K44,IF(K43=$I$234,K44*K45,IF(K43=$I$235,K44*K45*K46,1)))) -> 1 | L47: =IF(IF(L43=$I$233,L44,IF(L43=$I$234,L44*L45,IF(L43=$I$235,L44*L45*L46,1)))=0,"Fyll i 2.6-2.8",IF(L43=$I$233,L44,IF(L43=$I$234,L44*L45,IF(L43=$I$235,L44*L45*L46,1)))) -> 1 | M47: =IF(IF(M43=$I$233,M44,IF(M43=$I$234,M44*M45,IF(M43=$I$235,M44*M45*M46,1)))=0,"Fyll i 2.6-2.8",IF(M43=$I$233,M44,IF(M43=$I$234,M44*M45,IF(M43=$I$235,M44*M45*M46,1)))) -> 1 | N47: =IF(IF(N43=$I$233,N44,IF(N43=$I$234,N44*N45,IF(N43=$I$235,N44*N45*N46,1)))=0,"Fyll i 2.6-2.8",IF(N43=$I$233,N44,IF(N43=$I$234,N44*N45,IF(N43=$I$235,N44*N45*N46,1)))) -> 1 | O47: =IF(IF(O43=$I$233,O44,IF(O43=$I$234,O44*O45,IF(O43=$I$235,O44*O45*O46,1)))=0,"Fyll i 2.6-2.8",IF(O43=$I$233,O44,IF(O43=$I$234,O44*O45,IF(O43=$I$235,O44*O45*O46,1)))) -> 1 | P47: =IF(IF(P43=$I$233,P44,IF(P43=$I$234,P44*P45,IF(P43=$I$235,P44*P45*P46,1)))=0,"Fyll i 2.6-2.8",IF(P43=$I$233,P44,IF(P43=$I$234,P44*P45,IF(P43=$I$235,P44*P45*P46,1)))) -> 1 | ... R47: =IF(IF(R43=$I$233,R44,IF(R43=$I$234,R44*R45,IF(R43=$I$235,R44*R45*R46,1)))=0,"Fyll i 2.6-2.8",IF(R43=$I$233,R44,IF(R43=$I$234,R44*R45,IF(R43=$I$235,R44*R45*R46,1)))) -> 1
B48: 2.10 | C48: =$C$36 -> Underhållskostnader | H48: =$H$36 -> kr/år
C50: =$C$26 -> Armaturbeteckning
B51: 2.1 | C51: =$C$27 -> Antal armaturer | H51: =$H$27 -> stk
B52: 2.2 | C52: =$C$28 -> Armaturpris | H52: =$H$28 -> kr/stk
B53: 2.3 | C53: =$C$29 -> Material- och arbetskostnader armatur | H53: =$H$29 -> kr
B54: 2.4 | C54: =$C$30 -> Effekt per armatur, inkl. driftsförluster | H54: =$H$30 -> W/stk
B55: 2.5 | C55: =$C$31 -> Typ av styrning
B56: 2.6 | C56: =$C44 -> Reduktionsfaktor manuell styrning | I56: {=IFERROR(_xlfn.IFS(I$19='4. Reduktionsfaktorer, LENI-tal'!$Q$12,INDEX('4. Reduktionsfaktorer, LENI-tal'!$H$13:$O$23,MATCH(I$21,'4. Reduktionsfaktorer, LENI-tal'!$H$13:$H$23,0),3), I$19='4. Reduktionsfaktorer, LENI-tal'!$R$12,INDEX('4. Reduktionsfaktorer, LENI-tal'!$H$24:$O$32,MATCH(I$21,'4. Reduktionsfaktorer, LENI-tal'!$H$24:$H$32,0),3), I$19='4. Reduktionsfaktorer, LENI-tal'!$S$12,INDEX('4. Reduktionsfaktorer, LENI-tal'!$H$33:$O$37,MATCH(I$21,'4. Reduktionsfaktorer, LENI-tal'!$H$33:$H$37,0),3), I$19='4. Reduktionsfaktorer, LENI-tal'!$T$12,INDEX('4. Reduktionsfaktorer, LENI-tal'!$H$38:$O$45,MATCH(I$21,'4. Reduktionsfaktorer, LENI-tal'!$H$38:$H$45,0),3), I$19='4. Reduktionsfaktorer, LENI-tal'!$U$12,INDEX('4. Reduktionsfaktorer, LENI-tal'!$H$46:$O$54,MATCH(I$21,'4. Reduktionsfaktorer, LENI-tal'!$H$46:$H$54,0),3)), IFERROR( INDEX( tblStrings[], MATCH( 1, (tblStrings[[Cell]:[Cell]]=AllStrings!$D$350) * (tblStrings[[Sheet]:[Sheet]]=AllStrings!$C$433), 0 ), MATCH(Språkval, tblStrings[#Headers], 0) ), ))} -> Fyll i byggnads- och rumstyp ovan | J56: {=IFERROR(_xlfn.IFS(J$19='4. Reduktionsfaktorer, LENI-tal'!$Q$12,INDEX('4. Reduktionsfaktorer, LENI-tal'!$H$13:$O$23,MATCH(J$21,'4. Reduktionsfaktorer, LENI-tal'!$H$13:$H$23,0),3), J$19='4. Reduktionsfaktorer, LENI-tal'!$R$12,INDEX('4. Reduktionsfaktorer, LENI-tal'!$H$24:$O$32,MATCH(J$21,'4. Reduktionsfaktorer, LENI-tal'!$H$24:$H$32,0),3), J$19='4. Reduktionsfaktorer, LENI-tal'!$S$12,INDEX('4. Reduktionsfaktorer, LENI-tal'!$H$33:$O$37,MATCH(J$21,'4. Reduktionsfaktorer, LENI-tal'!$H$33:$H$37,0),3), J$19='4. Reduktionsfaktorer, LENI-tal'!$T$12,INDEX('4. Reduktionsfaktorer, LENI-tal'!$H$38:$O$45,MATCH(J$21,'4. Reduktionsfaktorer, LENI-tal'!$H$38:$H$45,0),3), J$19='4. Reduktionsfaktorer, LENI-tal'!$U$12,INDEX('4. Reduktionsfaktorer, LENI-tal'!$H$46:$O$54,MATCH(J$21,'4. Reduktionsfaktorer, LENI-tal'!$H$46:$H$54,0),3)), IFERROR( INDEX( tblStrings[], MATCH( 1, (tblStrings[[Cell]:[Cell]]=AllStrings!$D$350) * (tblStrings[[Sheet]:[Sheet]]=AllStrings!$C$433), 0 ), MATCH(Språkval, tblStrings[#Headers], 0) ), ))} -> Fyll i byggnads- och rumstyp ovan | K56: {=IFERROR(_xlfn.IFS(K$19='4. Reduktionsfaktorer, LENI-tal'!$Q$12,INDEX('4. Reduktionsfaktorer, LENI-tal'!$H$13:$O$23,MATCH(K$21,'4. Reduktionsfaktorer, LENI-tal'!$H$13:$H$23,0),3), K$19='4. Reduktionsfaktorer, LENI-tal'!$R$12,INDEX('4. Reduktionsfaktorer, LENI-tal'!$H$24:$O$32,MATCH(K$21,'4. Reduktionsfaktorer, LENI-tal'!$H$24:$H$32,0),3), K$19='4. Reduktionsfaktorer, LENI-tal'!$S$12,INDEX('4. Reduktionsfaktorer, LENI-tal'!$H$33:$O$37,MATCH(K$21,'4. Reduktionsfaktorer, LENI-tal'!$H$33:$H$37,0),3), K$19='4. Reduktionsfaktorer, LENI-tal'!$T$12,INDEX('4. Reduktionsfaktorer, LENI-tal'!$H$38:$O$45,MATCH(K$21,'4. Reduktionsfaktorer, LENI-tal'!$H$38:$H$45,0),3), K$19='4. Reduktionsfaktorer, LENI-tal'!$U$12,INDEX('4. Reduktionsfaktorer, LENI-tal'!$H$46:$O$54,MATCH(K$21,'4. Reduktionsfaktorer, LENI-tal'!$H$46:$H$54,0),3)), IFERROR( INDEX( tblStrings[], MATCH( 1, (tblStrings[[Cell]:[Cell]]=AllStrings!$D$350) * (tblStrings[[Sheet]:[Sheet]]=AllStrings!$C$433), 0 ), MATCH(Språkval, tblStrings[#Headers], 0) ), ))} -> Fyll i byggnads- och rumstyp ovan | L56: {=IFERROR(_xlfn.IFS(L$19='4. Reduktionsfaktorer, LENI-tal'!$Q$12,INDEX('4. Reduktionsfaktorer, LENI-tal'!$H$13:$O$23,MATCH(L$21,'4. Reduktionsfaktorer, LENI-tal'!$H$13:$H$23,0),3), L$19='4. Reduktionsfaktorer, LENI-tal'!$R$12,INDEX('4. Reduktionsfaktorer, LENI-tal'!$H$24:$O$32,MATCH(L$21,'4. Reduktionsfaktorer, LENI-tal'!$H$24:$H$32,0),3), L$19='4. Reduktionsfaktorer, LENI-tal'!$S$12,INDEX('4. Reduktionsfaktorer, LENI-tal'!$H$33:$O$37,MATCH(L$21,'4. Reduktionsfaktorer, LENI-tal'!$H$33:$H$37,0),3), L$19='4. Reduktionsfaktorer, LENI-tal'!$T$12,INDEX('4. Reduktionsfaktorer, LENI-tal'!$H$38:$O$45,MATCH(L$21,'4. Reduktionsfaktorer, LENI-tal'!$H$38:$H$45,0),3), L$19='4. Reduktionsfaktorer, LENI-tal'!$U$12,INDEX('4. Reduktionsfaktorer, LENI-tal'!$H$46:$O$54,MATCH(L$21,'4. Reduktionsfaktorer, LENI-tal'!$H$46:$H$54,0),3)), IFERROR( INDEX( tblStrings[], MATCH( 1, (tblStrings[[Cell]:[Cell]]=AllStrings!$D$350) * (tblStrings[[Sheet]:[Sheet]]=AllStrings!$C$433), 0 ), MATCH(Språkval, tblStrings[#Headers], 0) ), ))} -> Fyll i byggnads- och rumstyp ovan | M56: {=IFERROR(_xlfn.IFS(M$19='4. Reduktionsfaktorer, LENI-tal'!$Q$12,INDEX('4. Reduktionsfaktorer, LENI-tal'!$H$13:$O$23,MATCH(M$21,'4. Reduktionsfaktorer, LENI-tal'!$H$13:$H$23,0),3), M$19='4. Reduktionsfaktorer, LENI-tal'!$R$12,INDEX('4. Reduktionsfaktorer, LENI-tal'!$H$24:$O$32,MATCH(M$21,'4. Reduktionsfaktorer, LENI-tal'!$H$24:$H$32,0),3), M$19='4. Reduktionsfaktorer, LENI-tal'!$S$12,INDEX('4. Reduktionsfaktorer, LENI-tal'!$H$33:$O$37,MATCH(M$21,'4. Reduktionsfaktorer, LENI-tal'!$H$33:$H$37,0),3), M$19='4. Reduktionsfaktorer, LENI-tal'!$T$12,INDEX('4. Reduktionsfaktorer, LENI-tal'!$H$38:$O$45,MATCH(M$21,'4. Reduktionsfaktorer, LENI-tal'!$H$38:$H$45,0),3), M$19='4. Reduktionsfaktorer, LENI-tal'!$U$12,INDEX('4. Reduktionsfaktorer, LENI-tal'!$H$46:$O$54,MATCH(M$21,'4. Reduktionsfaktorer, LENI-tal'!$H$46:$H$54,0),3)), IFERROR( INDEX( tblStrings[], MATCH( 1, (tblStrings[[Cell]:[Cell]]=AllStrings!$D$350) * (tblStrings[[Sheet]:[Sheet]]=AllStrings!$C$433), 0 ), MATCH(Språkval, tblStrings[#Headers], 0) ), ))} -> Fyll i byggnads- och rumstyp ovan | N56: {=IFERROR(_xlfn.IFS(N$19='4. Reduktionsfaktorer, LENI-tal'!$Q$12,INDEX('4. Reduktionsfaktorer, LENI-tal'!$H$13:$O$23,MATCH(N$21,'4. Reduktionsfaktorer, LENI-tal'!$H$13:$H$23,0),3), N$19='4. Reduktionsfaktorer, LENI-tal'!$R$12,INDEX('4. Reduktionsfaktorer, LENI-tal'!$H$24:$O$32,MATCH(N$21,'4. Reduktionsfaktorer, LENI-tal'!$H$24:$H$32,0),3), N$19='4. Reduktionsfaktorer, LENI-tal'!$S$12,INDEX('4. Reduktionsfaktorer, LENI-tal'!$H$33:$O$37,MATCH(N$21,'4. Reduktionsfaktorer, LENI-tal'!$H$33:$H$37,0),3), N$19='4. Reduktionsfaktorer, LENI-tal'!$T$12,INDEX('4. Reduktionsfaktorer, LENI-tal'!$H$38:$O$45,MATCH(N$21,'4. Reduktionsfaktorer, LENI-tal'!$H$38:$H$45,0),3), N$19='4. Reduktionsfaktorer, LENI-tal'!$U$12,INDEX('4. Reduktionsfaktorer, LENI-tal'!$H$46:$O$54,MATCH(N$21,'4. Reduktionsfaktorer, LENI-tal'!$H$46:$H$54,0),3)), IFERROR( INDEX( tblStrings[], MATCH( 1, (tblStrings[[Cell]:[Cell]]=AllStrings!$D$350) * (tblStrings[[Sheet]:[Sheet]]=AllStrings!$C$433), 0 ), MATCH(Språkval, tblStrings[#Headers], 0) ), ))} -> Fyll i byggnads- och rumstyp ovan | O56: {=IFERROR(_xlfn.IFS(O$19='4. Reduktionsfaktorer, LENI-tal'!$Q$12,INDEX('4. Reduktionsfaktorer, LENI-tal'!$H$13:$O$23,MATCH(O$21,'4. Reduktionsfaktorer, LENI-tal'!$H$13:$H$23,0),3), O$19='4. Reduktionsfaktorer, LENI-tal'!$R$12,INDEX('4. Reduktionsfaktorer, LENI-tal'!$H$24:$O$32,MATCH(O$21,'4. Reduktionsfaktorer, LENI-tal'!$H$24:$H$32,0),3), O$19='4. Reduktionsfaktorer, LENI-tal'!$S$12,INDEX('4. Reduktionsfaktorer, LENI-tal'!$H$33:$O$37,MATCH(O$21,'4. Reduktionsfaktorer, LENI-tal'!$H$33:$H$37,0),3), O$19='4. Reduktionsfaktorer, LENI-tal'!$T$12,INDEX('4. Reduktionsfaktorer, LENI-tal'!$H$38:$O$45,MATCH(O$21,'4. Reduktionsfaktorer, LENI-tal'!$H$38:$H$45,0),3), O$19='4. Reduktionsfaktorer, LENI-tal'!$U$12,INDEX('4. Reduktionsfaktorer, LENI-tal'!$H$46:$O$54,MATCH(O$21,'4. Reduktionsfaktorer, LENI-tal'!$H$46:$H$54,0),3)), IFERROR( INDEX( tblStrings[], MATCH( 1, (tblStrings[[Cell]:[Cell]]=AllStrings!$D$350) * (tblStrings[[Sheet]:[Sheet]]=AllStrings!$C$433), 0 ), MATCH(Språkval, tblStrings[#Headers], 0) ), ))} -> Fyll i byggnads- och rumstyp ovan | P56: {=IFERROR(_xlfn.IFS(P$19='4. Reduktionsfaktorer, LENI-tal'!$Q$12,INDEX('4. Reduktionsfaktorer, LENI-tal'!$H$13:$O$23,MATCH(P$21,'4. Reduktionsfaktorer, LENI-tal'!$H$13:$H$23,0),3), P$19='4. Reduktionsfaktorer, LENI-tal'!$R$12,INDEX('4. Reduktionsfaktorer, LENI-tal'!$H$24:$O$32,MATCH(P$21,'4. Reduktionsfaktorer, LENI-tal'!$H$24:$H$32,0),3), P$19='4. Reduktionsfaktorer, LENI-tal'!$S$12,INDEX('4. Reduktionsfaktorer, LENI-tal'!$H$33:$O$37,MATCH(P$21,'4. Reduktionsfaktorer, LENI-tal'!$H$33:$H$37,0),3), P$19='4. Reduktionsfaktorer, LENI-tal'!$T$12,INDEX('4. Reduktionsfaktorer, LENI-tal'!$H$38:$O$45,MATCH(P$21,'4. Reduktionsfaktorer, LENI-tal'!$H$38:$H$45,0),3), P$19='4. Reduktionsfaktorer, LENI-tal'!$U$12,INDEX('4. Reduktionsfaktorer, LENI-tal'!$H$46:$O$54,MATCH(P$21,'4. Reduktionsfaktorer, LENI-tal'!$H$46:$H$54,0),3)), IFERROR( INDEX( tblStrings[], MATCH( 1, (tblStrings[[Cell]:[Cell]]=AllStrings!$D$350) * (tblStrings[[Sheet]:[Sheet]]=AllStrings!$C$433), 0 ), MATCH(Språkval, tblStrings[#Headers], 0) ), ))} -> Fyll i byggnads- och rumstyp ovan | ... R56: {=IFERROR(_xlfn.IFS(R$19='4. Reduktionsfaktorer, LENI-tal'!$Q$12,INDEX('4. Reduktionsfaktorer, LENI-tal'!$H$13:$O$23,MATCH(R$21,'4. Reduktionsfaktorer, LENI-tal'!$H$13:$H$23,0),3), R$19='4. Reduktionsfaktorer, LENI-tal'!$R$12,INDEX('4. Reduktionsfaktorer, LENI-tal'!$H$24:$O$32,MATCH(R$21,'4. Reduktionsfaktorer, LENI-tal'!$H$24:$H$32,0),3), R$19='4. Reduktionsfaktorer, LENI-tal'!$S$12,INDEX('4. Reduktionsfaktorer, LENI-tal'!$H$33:$O$37,MATCH(R$21,'4. Reduktionsfaktorer, LENI-tal'!$H$33:$H$37,0),3), R$19='4. Reduktionsfaktorer, LENI-tal'!$T$12,INDEX('4. Reduktionsfaktorer, LENI-tal'!$H$38:$O$45,MATCH(R$21,'4. Reduktionsfaktorer, LENI-tal'!$H$38:$H$45,0),3), R$19='4. Reduktionsfaktorer, LENI-tal'!$U$12,INDEX('4. Reduktionsfaktorer, LENI-tal'!$H$46:$O$54,MATCH(R$21,'4. Reduktionsfaktorer, LENI-tal'!$H$46:$H$54,0),3)), IFERROR( INDEX( tblStrings[], MATCH( 1, (tblStrings[[Cell]:[Cell]]=AllStrings!$D$350) * (tblStrings[[Sheet]:[Sheet]]=AllStrings!$C$433), 0 ), MATCH(Språkval, tblStrings[#Headers], 0) ), ))} -> Fyll i byggnads- och rumstyp ovan
B57: 2.7 | C57: =$C45 -> Reduktionsfaktor närvaro-/frånvarostyrning | I57: {=IFERROR(_xlfn.IFS(I$19='4. Reduktionsfaktorer, LENI-tal'!$Q$12,INDEX('4. Reduktionsfaktorer, LENI-tal'!$H$13:$O$23,MATCH(I$21,'4. Reduktionsfaktorer, LENI-tal'!$H$13:$H$23,0),4), I$19='4. Reduktionsfaktorer, LENI-tal'!$R$12,INDEX('4. Reduktionsfaktorer, LENI-tal'!$H$24:$O$32,MATCH(I$21,'4. Reduktionsfaktorer, LENI-tal'!$H$24:$H$32,0),4), I$19='4. Reduktionsfaktorer, LENI-tal'!$S$12,INDEX('4. Reduktionsfaktorer, LENI-tal'!$H$33:$O$37,MATCH(I$21,'4. Reduktionsfaktorer, LENI-tal'!$H$33:$H$37,0),4), I$19='4. Reduktionsfaktorer, LENI-tal'!$T$12,INDEX('4. Reduktionsfaktorer, LENI-tal'!$H$38:$O$45,MATCH(I$21,'4. Reduktionsfaktorer, LENI-tal'!$H$38:$H$45,0),4), I$19='4. Reduktionsfaktorer, LENI-tal'!$U$12,INDEX('4. Reduktionsfaktorer, LENI-tal'!$H$46:$O$54,MATCH(I$21,'4. Reduktionsfaktorer, LENI-tal'!$H$46:$H$54,0),4)), IFERROR( INDEX( tblStrings[], MATCH( 1, (tblStrings[[Cell]:[Cell]]=AllStrings!$D$350) * (tblStrings[[Sheet]:[Sheet]]=AllStrings!$C$433), 0 ), MATCH(Språkval, tblStrings[#Headers], 0) ), ))} -> Fyll i byggnads- och rumstyp ovan | J57: {=IFERROR(_xlfn.IFS(J$19='4. Reduktionsfaktorer, LENI-tal'!$Q$12,INDEX('4. Reduktionsfaktorer, LENI-tal'!$H$13:$O$23,MATCH(J$21,'4. Reduktionsfaktorer, LENI-tal'!$H$13:$H$23,0),4), J$19='4. Reduktionsfaktorer, LENI-tal'!$R$12,INDEX('4. Reduktionsfaktorer, LENI-tal'!$H$24:$O$32,MATCH(J$21,'4. Reduktionsfaktorer, LENI-tal'!$H$24:$H$32,0),4), J$19='4. Reduktionsfaktorer, LENI-tal'!$S$12,INDEX('4. Reduktionsfaktorer, LENI-tal'!$H$33:$O$37,MATCH(J$21,'4. Reduktionsfaktorer, LENI-tal'!$H$33:$H$37,0),4), J$19='4. Reduktionsfaktorer, LENI-tal'!$T$12,INDEX('4. Reduktionsfaktorer, LENI-tal'!$H$38:$O$45,MATCH(J$21,'4. Reduktionsfaktorer, LENI-tal'!$H$38:$H$45,0),4), J$19='4. Reduktionsfaktorer, LENI-tal'!$U$12,INDEX('4. Reduktionsfaktorer, LENI-tal'!$H$46:$O$54,MATCH(J$21,'4. Reduktionsfaktorer, LENI-tal'!$H$46:$H$54,0),4)), IFERROR( INDEX( tblStrings[], MATCH( 1, (tblStrings[[Cell]:[Cell]]=AllStrings!$D$350) * (tblStrings[[Sheet]:[Sheet]]=AllStrings!$C$433), 0 ), MATCH(Språkval, tblStrings[#Headers], 0) ), ))} -> Fyll i byggnads- och rumstyp ovan | K57: {=IFERROR(_xlfn.IFS(K$19='4. Reduktionsfaktorer, LENI-tal'!$Q$12,INDEX('4. Reduktionsfaktorer, LENI-tal'!$H$13:$O$23,MATCH(K$21,'4. Reduktionsfaktorer, LENI-tal'!$H$13:$H$23,0),4), K$19='4. Reduktionsfaktorer, LENI-tal'!$R$12,INDEX('4. Reduktionsfaktorer, LENI-tal'!$H$24:$O$32,MATCH(K$21,'4. Reduktionsfaktorer, LENI-tal'!$H$24:$H$32,0),4), K$19='4. Reduktionsfaktorer, LENI-tal'!$S$12,INDEX('4. Reduktionsfaktorer, LENI-tal'!$H$33:$O$37,MATCH(K$21,'4. Reduktionsfaktorer, LENI-tal'!$H$33:$H$37,0),4), K$19='4. Reduktionsfaktorer, LENI-tal'!$T$12,INDEX('4. Reduktionsfaktorer, LENI-tal'!$H$38:$O$45,MATCH(K$21,'4. Reduktionsfaktorer, LENI-tal'!$H$38:$H$45,0),4), K$19='4. Reduktionsfaktorer, LENI-tal'!$U$12,INDEX('4. Reduktionsfaktorer, LENI-tal'!$H$46:$O$54,MATCH(K$21,'4. Reduktionsfaktorer, LENI-tal'!$H$46:$H$54,0),4)), IFERROR( INDEX( tblStrings[], MATCH( 1, (tblStrings[[Cell]:[Cell]]=AllStrings!$D$350) * (tblStrings[[Sheet]:[Sheet]]=AllStrings!$C$433), 0 ), MATCH(Språkval, tblStrings[#Headers], 0) ), ))} -> Fyll i byggnads- och rumstyp ovan | L57: {=IFERROR(_xlfn.IFS(L$19='4. Reduktionsfaktorer, LENI-tal'!$Q$12,INDEX('4. Reduktionsfaktorer, LENI-tal'!$H$13:$O$23,MATCH(L$21,'4. Reduktionsfaktorer, LENI-tal'!$H$13:$H$23,0),4), L$19='4. Reduktionsfaktorer, LENI-tal'!$R$12,INDEX('4. Reduktionsfaktorer, LENI-tal'!$H$24:$O$32,MATCH(L$21,'4. Reduktionsfaktorer, LENI-tal'!$H$24:$H$32,0),4), L$19='4. Reduktionsfaktorer, LENI-tal'!$S$12,INDEX('4. Reduktionsfaktorer, LENI-tal'!$H$33:$O$37,MATCH(L$21,'4. Reduktionsfaktorer, LENI-tal'!$H$33:$H$37,0),4), L$19='4. Reduktionsfaktorer, LENI-tal'!$T$12,INDEX('4. Reduktionsfaktorer, LENI-tal'!$H$38:$O$45,MATCH(L$21,'4. Reduktionsfaktorer, LENI-tal'!$H$38:$H$45,0),4), L$19='4. Reduktionsfaktorer, LENI-tal'!$U$12,INDEX('4. Reduktionsfaktorer, LENI-tal'!$H$46:$O$54,MATCH(L$21,'4. Reduktionsfaktorer, LENI-tal'!$H$46:$H$54,0),4)), IFERROR( INDEX( tblStrings[], MATCH( 1, (tblStrings[[Cell]:[Cell]]=AllStrings!$D$350) * (tblStrings[[Sheet]:[Sheet]]=AllStrings!$C$433), 0 ), MATCH(Språkval, tblStrings[#Headers], 0) ), ))} -> Fyll i byggnads- och rumstyp ovan | M57: {=IFERROR(_xlfn.IFS(M$19='4. Reduktionsfaktorer, LENI-tal'!$Q$12,INDEX('4. Reduktionsfaktorer, LENI-tal'!$H$13:$O$23,MATCH(M$21,'4. Reduktionsfaktorer, LENI-tal'!$H$13:$H$23,0),4), M$19='4. Reduktionsfaktorer, LENI-tal'!$R$12,INDEX('4. Reduktionsfaktorer, LENI-tal'!$H$24:$O$32,MATCH(M$21,'4. Reduktionsfaktorer, LENI-tal'!$H$24:$H$32,0),4), M$19='4. Reduktionsfaktorer, LENI-tal'!$S$12,INDEX('4. Reduktionsfaktorer, LENI-tal'!$H$33:$O$37,MATCH(M$21,'4. Reduktionsfaktorer, LENI-tal'!$H$33:$H$37,0),4), M$19='4. Reduktionsfaktorer, LENI-tal'!$T$12,INDEX('4. Reduktionsfaktorer, LENI-tal'!$H$38:$O$45,MATCH(M$21,'4. Reduktionsfaktorer, LENI-tal'!$H$38:$H$45,0),4), M$19='4. Reduktionsfaktorer, LENI-tal'!$U$12,INDEX('4. Reduktionsfaktorer, LENI-tal'!$H$46:$O$54,MATCH(M$21,'4. Reduktionsfaktorer, LENI-tal'!$H$46:$H$54,0),4)), IFERROR( INDEX( tblStrings[], MATCH( 1, (tblStrings[[Cell]:[Cell]]=AllStrings!$D$350) * (tblStrings[[Sheet]:[Sheet]]=AllStrings!$C$433), 0 ), MATCH(Språkval, tblStrings[#Headers], 0) ), ))} -> Fyll i byggnads- och rumstyp ovan | N57: {=IFERROR(_xlfn.IFS(N$19='4. Reduktionsfaktorer, LENI-tal'!$Q$12,INDEX('4. Reduktionsfaktorer, LENI-tal'!$H$13:$O$23,MATCH(N$21,'4. Reduktionsfaktorer, LENI-tal'!$H$13:$H$23,0),4), N$19='4. Reduktionsfaktorer, LENI-tal'!$R$12,INDEX('4. Reduktionsfaktorer, LENI-tal'!$H$24:$O$32,MATCH(N$21,'4. Reduktionsfaktorer, LENI-tal'!$H$24:$H$32,0),4), N$19='4. Reduktionsfaktorer, LENI-tal'!$S$12,INDEX('4. Reduktionsfaktorer, LENI-tal'!$H$33:$O$37,MATCH(N$21,'4. Reduktionsfaktorer, LENI-tal'!$H$33:$H$37,0),4), N$19='4. Reduktionsfaktorer, LENI-tal'!$T$12,INDEX('4. Reduktionsfaktorer, LENI-tal'!$H$38:$O$45,MATCH(N$21,'4. Reduktionsfaktorer, LENI-tal'!$H$38:$H$45,0),4), N$19='4. Reduktionsfaktorer, LENI-tal'!$U$12,INDEX('4. Reduktionsfaktorer, LENI-tal'!$H$46:$O$54,MATCH(N$21,'4. Reduktionsfaktorer, LENI-tal'!$H$46:$H$54,0),4)), IFERROR( INDEX( tblStrings[], MATCH( 1, (tblStrings[[Cell]:[Cell]]=AllStrings!$D$350) * (tblStrings[[Sheet]:[Sheet]]=AllStrings!$C$433), 0 ), MATCH(Språkval, tblStrings[#Headers], 0) ), ))} -> Fyll i byggnads- och rumstyp ovan | O57: {=IFERROR(_xlfn.IFS(O$19='4. Reduktionsfaktorer, LENI-tal'!$Q$12,INDEX('4. Reduktionsfaktorer, LENI-tal'!$H$13:$O$23,MATCH(O$21,'4. Reduktionsfaktorer, LENI-tal'!$H$13:$H$23,0),4), O$19='4. Reduktionsfaktorer, LENI-tal'!$R$12,INDEX('4. Reduktionsfaktorer, LENI-tal'!$H$24:$O$32,MATCH(O$21,'4. Reduktionsfaktorer, LENI-tal'!$H$24:$H$32,0),4), O$19='4. Reduktionsfaktorer, LENI-tal'!$S$12,INDEX('4. Reduktionsfaktorer, LENI-tal'!$H$33:$O$37,MATCH(O$21,'4. Reduktionsfaktorer, LENI-tal'!$H$33:$H$37,0),4), O$19='4. Reduktionsfaktorer, LENI-tal'!$T$12,INDEX('4. Reduktionsfaktorer, LENI-tal'!$H$38:$O$45,MATCH(O$21,'4. Reduktionsfaktorer, LENI-tal'!$H$38:$H$45,0),4), O$19='4. Reduktionsfaktorer, LENI-tal'!$U$12,INDEX('4. Reduktionsfaktorer, LENI-tal'!$H$46:$O$54,MATCH(O$21,'4. Reduktionsfaktorer, LENI-tal'!$H$46:$H$54,0),4)), IFERROR( INDEX( tblStrings[], MATCH( 1, (tblStrings[[Cell]:[Cell]]=AllStrings!$D$350) * (tblStrings[[Sheet]:[Sheet]]=AllStrings!$C$433), 0 ), MATCH(Språkval, tblStrings[#Headers], 0) ), ))} -> Fyll i byggnads- och rumstyp ovan | P57: {=IFERROR(_xlfn.IFS(P$19='4. Reduktionsfaktorer, LENI-tal'!$Q$12,INDEX('4. Reduktionsfaktorer, LENI-tal'!$H$13:$O$23,MATCH(P$21,'4. Reduktionsfaktorer, LENI-tal'!$H$13:$H$23,0),4), P$19='4. Reduktionsfaktorer, LENI-tal'!$R$12,INDEX('4. Reduktionsfaktorer, LENI-tal'!$H$24:$O$32,MATCH(P$21,'4. Reduktionsfaktorer, LENI-tal'!$H$24:$H$32,0),4), P$19='4. Reduktionsfaktorer, LENI-tal'!$S$12,INDEX('4. Reduktionsfaktorer, LENI-tal'!$H$33:$O$37,MATCH(P$21,'4. Reduktionsfaktorer, LENI-tal'!$H$33:$H$37,0),4), P$19='4. Reduktionsfaktorer, LENI-tal'!$T$12,INDEX('4. Reduktionsfaktorer, LENI-tal'!$H$38:$O$45,MATCH(P$21,'4. Reduktionsfaktorer, LENI-tal'!$H$38:$H$45,0),4), P$19='4. Reduktionsfaktorer, LENI-tal'!$U$12,INDEX('4. Reduktionsfaktorer, LENI-tal'!$H$46:$O$54,MATCH(P$21,'4. Reduktionsfaktorer, LENI-tal'!$H$46:$H$54,0),4)), IFERROR( INDEX( tblStrings[], MATCH( 1, (tblStrings[[Cell]:[Cell]]=AllStrings!$D$350) * (tblStrings[[Sheet]:[Sheet]]=AllStrings!$C$433), 0 ), MATCH(Språkval, tblStrings[#Headers], 0) ), ))} -> Fyll i byggnads- och rumstyp ovan | ... R57: {=IFERROR(_xlfn.IFS(R$19='4. Reduktionsfaktorer, LENI-tal'!$Q$12,INDEX('4. Reduktionsfaktorer, LENI-tal'!$H$13:$O$23,MATCH(R$21,'4. Reduktionsfaktorer, LENI-tal'!$H$13:$H$23,0),4), R$19='4. Reduktionsfaktorer, LENI-tal'!$R$12,INDEX('4. Reduktionsfaktorer, LENI-tal'!$H$24:$O$32,MATCH(R$21,'4. Reduktionsfaktorer, LENI-tal'!$H$24:$H$32,0),4), R$19='4. Reduktionsfaktorer, LENI-tal'!$S$12,INDEX('4. Reduktionsfaktorer, LENI-tal'!$H$33:$O$37,MATCH(R$21,'4. Reduktionsfaktorer, LENI-tal'!$H$33:$H$37,0),4), R$19='4. Reduktionsfaktorer, LENI-tal'!$T$12,INDEX('4. Reduktionsfaktorer, LENI-tal'!$H$38:$O$45,MATCH(R$21,'4. Reduktionsfaktorer, LENI-tal'!$H$38:$H$45,0),4), R$19='4. Reduktionsfaktorer, LENI-tal'!$U$12,INDEX('4. Reduktionsfaktorer, LENI-tal'!$H$46:$O$54,MATCH(R$21,'4. Reduktionsfaktorer, LENI-tal'!$H$46:$H$54,0),4)), IFERROR( INDEX( tblStrings[], MATCH( 1, (tblStrings[[Cell]:[Cell]]=AllStrings!$D$350) * (tblStrings[[Sheet]:[Sheet]]=AllStrings!$C$433), 0 ), MATCH(Språkval, tblStrings[#Headers], 0) ), ))} -> Fyll i byggnads- och rumstyp ovan
B58: 2.8 | C58: =$C46 -> Reduktionsfaktor dagsljusstyrning | I58: {=IFERROR(_xlfn.IFS(I$19='4. Reduktionsfaktorer, LENI-tal'!$Q$12,INDEX('4. Reduktionsfaktorer, LENI-tal'!$H$13:$O$23,MATCH(I$21,'4. Reduktionsfaktorer, LENI-tal'!$H$13:$H$23,0),5), I$19='4. Reduktionsfaktorer, LENI-tal'!$R$12,INDEX('4. Reduktionsfaktorer, LENI-tal'!$H$24:$O$32,MATCH(I$21,'4. Reduktionsfaktorer, LENI-tal'!$H$24:$H$32,0),5), I$19='4. Reduktionsfaktorer, LENI-tal'!$S$12,INDEX('4. Reduktionsfaktorer, LENI-tal'!$H$33:$O$37,MATCH(I$21,'4. Reduktionsfaktorer, LENI-tal'!$H$33:$H$37,0),5), I$19='4. Reduktionsfaktorer, LENI-tal'!$T$12,INDEX('4. Reduktionsfaktorer, LENI-tal'!$H$38:$O$45,MATCH(I$21,'4. Reduktionsfaktorer, LENI-tal'!$H$38:$H$45,0),5), I$19='4. Reduktionsfaktorer, LENI-tal'!$U$12,INDEX('4. Reduktionsfaktorer, LENI-tal'!$H$46:$O$54,MATCH(I$21,'4. Reduktionsfaktorer, LENI-tal'!$H$46:$H$54,0),5)), IFERROR( INDEX( tblStrings[], MATCH( 1, (tblStrings[[Cell]:[Cell]]=AllStrings!$D$350) * (tblStrings[[Sheet]:[Sheet]]=AllStrings!$C$433), 0 ), MATCH(Språkval, tblStrings[#Headers], 0) ), ))} -> Fyll i byggnads- och rumstyp ovan | J58: {=IFERROR(_xlfn.IFS(J$19='4. Reduktionsfaktorer, LENI-tal'!$Q$12,INDEX('4. Reduktionsfaktorer, LENI-tal'!$H$13:$O$23,MATCH(J$21,'4. Reduktionsfaktorer, LENI-tal'!$H$13:$H$23,0),5), J$19='4. Reduktionsfaktorer, LENI-tal'!$R$12,INDEX('4. Reduktionsfaktorer, LENI-tal'!$H$24:$O$32,MATCH(J$21,'4. Reduktionsfaktorer, LENI-tal'!$H$24:$H$32,0),5), J$19='4. Reduktionsfaktorer, LENI-tal'!$S$12,INDEX('4. Reduktionsfaktorer, LENI-tal'!$H$33:$O$37,MATCH(J$21,'4. Reduktionsfaktorer, LENI-tal'!$H$33:$H$37,0),5), J$19='4. Reduktionsfaktorer, LENI-tal'!$T$12,INDEX('4. Reduktionsfaktorer, LENI-tal'!$H$38:$O$45,MATCH(J$21,'4. Reduktionsfaktorer, LENI-tal'!$H$38:$H$45,0),5), J$19='4. Reduktionsfaktorer, LENI-tal'!$U$12,INDEX('4. Reduktionsfaktorer, LENI-tal'!$H$46:$O$54,MATCH(J$21,'4. Reduktionsfaktorer, LENI-tal'!$H$46:$H$54,0),5)), IFERROR( INDEX( tblStrings[], MATCH( 1, (tblStrings[[Cell]:[Cell]]=AllStrings!$D$350) * (tblStrings[[Sheet]:[Sheet]]=AllStrings!$C$433), 0 ), MATCH(Språkval, tblStrings[#Headers], 0) ), ))} -> Fyll i byggnads- och rumstyp ovan | K58: {=IFERROR(_xlfn.IFS(K$19='4. Reduktionsfaktorer, LENI-tal'!$Q$12,INDEX('4. Reduktionsfaktorer, LENI-tal'!$H$13:$O$23,MATCH(K$21,'4. Reduktionsfaktorer, LENI-tal'!$H$13:$H$23,0),5), K$19='4. Reduktionsfaktorer, LENI-tal'!$R$12,INDEX('4. Reduktionsfaktorer, LENI-tal'!$H$24:$O$32,MATCH(K$21,'4. Reduktionsfaktorer, LENI-tal'!$H$24:$H$32,0),5), K$19='4. Reduktionsfaktorer, LENI-tal'!$S$12,INDEX('4. Reduktionsfaktorer, LENI-tal'!$H$33:$O$37,MATCH(K$21,'4. Reduktionsfaktorer, LENI-tal'!$H$33:$H$37,0),5), K$19='4. Reduktionsfaktorer, LENI-tal'!$T$12,INDEX('4. Reduktionsfaktorer, LENI-tal'!$H$38:$O$45,MATCH(K$21,'4. Reduktionsfaktorer, LENI-tal'!$H$38:$H$45,0),5), K$19='4. Reduktionsfaktorer, LENI-tal'!$U$12,INDEX('4. Reduktionsfaktorer, LENI-tal'!$H$46:$O$54,MATCH(K$21,'4. Reduktionsfaktorer, LENI-tal'!$H$46:$H$54,0),5)), IFERROR( INDEX( tblStrings[], MATCH( 1, (tblStrings[[Cell]:[Cell]]=AllStrings!$D$350) * (tblStrings[[Sheet]:[Sheet]]=AllStrings!$C$433), 0 ), MATCH(Språkval, tblStrings[#Headers], 0) ), ))} -> Fyll i byggnads- och rumstyp ovan | L58: {=IFERROR(_xlfn.IFS(L$19='4. Reduktionsfaktorer, LENI-tal'!$Q$12,INDEX('4. Reduktionsfaktorer, LENI-tal'!$H$13:$O$23,MATCH(L$21,'4. Reduktionsfaktorer, LENI-tal'!$H$13:$H$23,0),5), L$19='4. Reduktionsfaktorer, LENI-tal'!$R$12,INDEX('4. Reduktionsfaktorer, LENI-tal'!$H$24:$O$32,MATCH(L$21,'4. Reduktionsfaktorer, LENI-tal'!$H$24:$H$32,0),5), L$19='4. Reduktionsfaktorer, LENI-tal'!$S$12,INDEX('4. Reduktionsfaktorer, LENI-tal'!$H$33:$O$37,MATCH(L$21,'4. Reduktionsfaktorer, LENI-tal'!$H$33:$H$37,0),5), L$19='4. Reduktionsfaktorer, LENI-tal'!$T$12,INDEX('4. Reduktionsfaktorer, LENI-tal'!$H$38:$O$45,MATCH(L$21,'4. Reduktionsfaktorer, LENI-tal'!$H$38:$H$45,0),5), L$19='4. Reduktionsfaktorer, LENI-tal'!$U$12,INDEX('4. Reduktionsfaktorer, LENI-tal'!$H$46:$O$54,MATCH(L$21,'4. Reduktionsfaktorer, LENI-tal'!$H$46:$H$54,0),5)), IFERROR( INDEX( tblStrings[], MATCH( 1, (tblStrings[[Cell]:[Cell]]=AllStrings!$D$350) * (tblStrings[[Sheet]:[Sheet]]=AllStrings!$C$433), 0 ), MATCH(Språkval, tblStrings[#Headers], 0) ), ))} -> Fyll i byggnads- och rumstyp ovan | M58: {=IFERROR(_xlfn.IFS(M$19='4. Reduktionsfaktorer, LENI-tal'!$Q$12,INDEX('4. Reduktionsfaktorer, LENI-tal'!$H$13:$O$23,MATCH(M$21,'4. Reduktionsfaktorer, LENI-tal'!$H$13:$H$23,0),5), M$19='4. Reduktionsfaktorer, LENI-tal'!$R$12,INDEX('4. Reduktionsfaktorer, LENI-tal'!$H$24:$O$32,MATCH(M$21,'4. Reduktionsfaktorer, LENI-tal'!$H$24:$H$32,0),5), M$19='4. Reduktionsfaktorer, LENI-tal'!$S$12,INDEX('4. Reduktionsfaktorer, LENI-tal'!$H$33:$O$37,MATCH(M$21,'4. Reduktionsfaktorer, LENI-tal'!$H$33:$H$37,0),5), M$19='4. Reduktionsfaktorer, LENI-tal'!$T$12,INDEX('4. Reduktionsfaktorer, LENI-tal'!$H$38:$O$45,MATCH(M$21,'4. Reduktionsfaktorer, LENI-tal'!$H$38:$H$45,0),5), M$19='4. Reduktionsfaktorer, LENI-tal'!$U$12,INDEX('4. Reduktionsfaktorer, LENI-tal'!$H$46:$O$54,MATCH(M$21,'4. Reduktionsfaktorer, LENI-tal'!$H$46:$H$54,0),5)), IFERROR( INDEX( tblStrings[], MATCH( 1, (tblStrings[[Cell]:[Cell]]=AllStrings!$D$350) * (tblStrings[[Sheet]:[Sheet]]=AllStrings!$C$433), 0 ), MATCH(Språkval, tblStrings[#Headers], 0) ), ))} -> Fyll i byggnads- och rumstyp ovan | N58: {=IFERROR(_xlfn.IFS(N$19='4. Reduktionsfaktorer, LENI-tal'!$Q$12,INDEX('4. Reduktionsfaktorer, LENI-tal'!$H$13:$O$23,MATCH(N$21,'4. Reduktionsfaktorer, LENI-tal'!$H$13:$H$23,0),5), N$19='4. Reduktionsfaktorer, LENI-tal'!$R$12,INDEX('4. Reduktionsfaktorer, LENI-tal'!$H$24:$O$32,MATCH(N$21,'4. Reduktionsfaktorer, LENI-tal'!$H$24:$H$32,0),5), N$19='4. Reduktionsfaktorer, LENI-tal'!$S$12,INDEX('4. Reduktionsfaktorer, LENI-tal'!$H$33:$O$37,MATCH(N$21,'4. Reduktionsfaktorer, LENI-tal'!$H$33:$H$37,0),5), N$19='4. Reduktionsfaktorer, LENI-tal'!$T$12,INDEX('4. Reduktionsfaktorer, LENI-tal'!$H$38:$O$45,MATCH(N$21,'4. Reduktionsfaktorer, LENI-tal'!$H$38:$H$45,0),5), N$19='4. Reduktionsfaktorer, LENI-tal'!$U$12,INDEX('4. Reduktionsfaktorer, LENI-tal'!$H$46:$O$54,MATCH(N$21,'4. Reduktionsfaktorer, LENI-tal'!$H$46:$H$54,0),5)), IFERROR( INDEX( tblStrings[], MATCH( 1, (tblStrings[[Cell]:[Cell]]=AllStrings!$D$350) * (tblStrings[[Sheet]:[Sheet]]=AllStrings!$C$433), 0 ), MATCH(Språkval, tblStrings[#Headers], 0) ), ))} -> Fyll i byggnads- och rumstyp ovan | O58: {=IFERROR(_xlfn.IFS(O$19='4. Reduktionsfaktorer, LENI-tal'!$Q$12,INDEX('4. Reduktionsfaktorer, LENI-tal'!$H$13:$O$23,MATCH(O$21,'4. Reduktionsfaktorer, LENI-tal'!$H$13:$H$23,0),5), O$19='4. Reduktionsfaktorer, LENI-tal'!$R$12,INDEX('4. Reduktionsfaktorer, LENI-tal'!$H$24:$O$32,MATCH(O$21,'4. Reduktionsfaktorer, LENI-tal'!$H$24:$H$32,0),5), O$19='4. Reduktionsfaktorer, LENI-tal'!$S$12,INDEX('4. Reduktionsfaktorer, LENI-tal'!$H$33:$O$37,MATCH(O$21,'4. Reduktionsfaktorer, LENI-tal'!$H$33:$H$37,0),5), O$19='4. Reduktionsfaktorer, LENI-tal'!$T$12,INDEX('4. Reduktionsfaktorer, LENI-tal'!$H$38:$O$45,MATCH(O$21,'4. Reduktionsfaktorer, LENI-tal'!$H$38:$H$45,0),5), O$19='4. Reduktionsfaktorer, LENI-tal'!$U$12,INDEX('4. Reduktionsfaktorer, LENI-tal'!$H$46:$O$54,MATCH(O$21,'4. Reduktionsfaktorer, LENI-tal'!$H$46:$H$54,0),5)), IFERROR( INDEX( tblStrings[], MATCH( 1, (tblStrings[[Cell]:[Cell]]=AllStrings!$D$350) * (tblStrings[[Sheet]:[Sheet]]=AllStrings!$C$433), 0 ), MATCH(Språkval, tblStrings[#Headers], 0) ), ))} -> Fyll i byggnads- och rumstyp ovan | P58: {=IFERROR(_xlfn.IFS(P$19='4. Reduktionsfaktorer, LENI-tal'!$Q$12,INDEX('4. Reduktionsfaktorer, LENI-tal'!$H$13:$O$23,MATCH(P$21,'4. Reduktionsfaktorer, LENI-tal'!$H$13:$H$23,0),5), P$19='4. Reduktionsfaktorer, LENI-tal'!$R$12,INDEX('4. Reduktionsfaktorer, LENI-tal'!$H$24:$O$32,MATCH(P$21,'4. Reduktionsfaktorer, LENI-tal'!$H$24:$H$32,0),5), P$19='4. Reduktionsfaktorer, LENI-tal'!$S$12,INDEX('4. Reduktionsfaktorer, LENI-tal'!$H$33:$O$37,MATCH(P$21,'4. Reduktionsfaktorer, LENI-tal'!$H$33:$H$37,0),5), P$19='4. Reduktionsfaktorer, LENI-tal'!$T$12,INDEX('4. Reduktionsfaktorer, LENI-tal'!$H$38:$O$45,MATCH(P$21,'4. Reduktionsfaktorer, LENI-tal'!$H$38:$H$45,0),5), P$19='4. Reduktionsfaktorer, LENI-tal'!$U$12,INDEX('4. Reduktionsfaktorer, LENI-tal'!$H$46:$O$54,MATCH(P$21,'4. Reduktionsfaktorer, LENI-tal'!$H$46:$H$54,0),5)), IFERROR( INDEX( tblStrings[], MATCH( 1, (tblStrings[[Cell]:[Cell]]=AllStrings!$D$350) * (tblStrings[[Sheet]:[Sheet]]=AllStrings!$C$433), 0 ), MATCH(Språkval, tblStrings[#Headers], 0) ), ))} -> Fyll i byggnads- och rumstyp ovan | ... R58: {=IFERROR(_xlfn.IFS(R$19='4. Reduktionsfaktorer, LENI-tal'!$Q$12,INDEX('4. Reduktionsfaktorer, LENI-tal'!$H$13:$O$23,MATCH(R$21,'4. Reduktionsfaktorer, LENI-tal'!$H$13:$H$23,0),5), R$19='4. Reduktionsfaktorer, LENI-tal'!$R$12,INDEX('4. Reduktionsfaktorer, LENI-tal'!$H$24:$O$32,MATCH(R$21,'4. Reduktionsfaktorer, LENI-tal'!$H$24:$H$32,0),5), R$19='4. Reduktionsfaktorer, LENI-tal'!$S$12,INDEX('4. Reduktionsfaktorer, LENI-tal'!$H$33:$O$37,MATCH(R$21,'4. Reduktionsfaktorer, LENI-tal'!$H$33:$H$37,0),5), R$19='4. Reduktionsfaktorer, LENI-tal'!$T$12,INDEX('4. Reduktionsfaktorer, LENI-tal'!$H$38:$O$45,MATCH(R$21,'4. Reduktionsfaktorer, LENI-tal'!$H$38:$H$45,0),5), R$19='4. Reduktionsfaktorer, LENI-tal'!$U$12,INDEX('4. Reduktionsfaktorer, LENI-tal'!$H$46:$O$54,MATCH(R$21,'4. Reduktionsfaktorer, LENI-tal'!$H$46:$H$54,0),5)), IFERROR( INDEX( tblStrings[], MATCH( 1, (tblStrings[[Cell]:[Cell]]=AllStrings!$D$350) * (tblStrings[[Sheet]:[Sheet]]=AllStrings!$C$433), 0 ), MATCH(Språkval, tblStrings[#Headers], 0) ), ))} -> Fyll i byggnads- och rumstyp ovan
B59: 2.9 | C59: =$C$35 -> Total reduktionsfaktor för styrning | I59: =IF(IF(I55=$I$233,I56,IF(I55=$I$234,I56*I57,IF(I55=$I$235,I56*I57*I58,1)))=0,"Fyll i 2.6-2.8",IF(I55=$I$233,I56,IF(I55=$I$234,I56*I57,IF(I55=$I$235,I56*I57*I58,1)))) -> 1 | J59: =IF(IF(J55=$I$233,J56,IF(J55=$I$234,J56*J57,IF(J55=$I$235,J56*J57*J58,1)))=0,"Fyll i 2.6-2.8",IF(J55=$I$233,J56,IF(J55=$I$234,J56*J57,IF(J55=$I$235,J56*J57*J58,1)))) -> 1 | K59: =IF(IF(K55=$I$233,K56,IF(K55=$I$234,K56*K57,IF(K55=$I$235,K56*K57*K58,1)))=0,"Fyll i 2.6-2.8",IF(K55=$I$233,K56,IF(K55=$I$234,K56*K57,IF(K55=$I$235,K56*K57*K58,1)))) -> 1 | L59: =IF(IF(L55=$I$233,L56,IF(L55=$I$234,L56*L57,IF(L55=$I$235,L56*L57*L58,1)))=0,"Fyll i 2.6-2.8",IF(L55=$I$233,L56,IF(L55=$I$234,L56*L57,IF(L55=$I$235,L56*L57*L58,1)))) -> 1 | M59: =IF(IF(M55=$I$233,M56,IF(M55=$I$234,M56*M57,IF(M55=$I$235,M56*M57*M58,1)))=0,"Fyll i 2.6-2.8",IF(M55=$I$233,M56,IF(M55=$I$234,M56*M57,IF(M55=$I$235,M56*M57*M58,1)))) -> 1 | N59: =IF(IF(N55=$I$233,N56,IF(N55=$I$234,N56*N57,IF(N55=$I$235,N56*N57*N58,1)))=0,"Fyll i 2.6-2.8",IF(N55=$I$233,N56,IF(N55=$I$234,N56*N57,IF(N55=$I$235,N56*N57*N58,1)))) -> 1 | O59: =IF(IF(O55=$I$233,O56,IF(O55=$I$234,O56*O57,IF(O55=$I$235,O56*O57*O58,1)))=0,"Fyll i 2.6-2.8",IF(O55=$I$233,O56,IF(O55=$I$234,O56*O57,IF(O55=$I$235,O56*O57*O58,1)))) -> 1 | P59: =IF(IF(P55=$I$233,P56,IF(P55=$I$234,P56*P57,IF(P55=$I$235,P56*P57*P58,1)))=0,"Fyll i 2.6-2.8",IF(P55=$I$233,P56,IF(P55=$I$234,P56*P57,IF(P55=$I$235,P56*P57*P58,1)))) -> 1 | ... R59: =IF(IF(R55=$I$233,R56,IF(R55=$I$234,R56*R57,IF(R55=$I$235,R56*R57*R58,1)))=0,"Fyll i 2.6-2.8",IF(R55=$I$233,R56,IF(R55=$I$234,R56*R57,IF(R55=$I$235,R56*R57*R58,1)))) -> 1
B60: 2.10 | C60: =$C$36 -> Underhållskostnader | H60: =$H$36 -> kr/år
C62: =$C$26 -> Armaturbeteckning
B63: 2.1 | C63: =$C$27 -> Antal armaturer | H63: =$H$27 -> stk
B64: 2.2 | C64: =$C$28 -> Armaturpris | H64: =$H$28 -> kr/stk
B65: 2.3 | C65: =$C$29 -> Material- och arbetskostnader armatur | H65: =$H$29 -> kr
B66: 2.4 | C66: =$C$30 -> Effekt per armatur, inkl. driftsförluster | H66: =$H$30 -> W/stk
B67: 2.5 | C67: =$C$31 -> Typ av styrning
B68: 2.6 | C68: =$C56 -> Reduktionsfaktor manuell styrning | I68: {=IFERROR(_xlfn.IFS(I$19='4. Reduktionsfaktorer, LENI-tal'!$Q$12,INDEX('4. Reduktionsfaktorer, LENI-tal'!$H$13:$O$23,MATCH(I$21,'4. Reduktionsfaktorer, LENI-tal'!$H$13:$H$23,0),3), I$19='4. Reduktionsfaktorer, LENI-tal'!$R$12,INDEX('4. Reduktionsfaktorer, LENI-tal'!$H$24:$O$32,MATCH(I$21,'4. Reduktionsfaktorer, LENI-tal'!$H$24:$H$32,0),3), I$19='4. Reduktionsfaktorer, LENI-tal'!$S$12,INDEX('4. Reduktionsfaktorer, LENI-tal'!$H$33:$O$37,MATCH(I$21,'4. Reduktionsfaktorer, LENI-tal'!$H$33:$H$37,0),3), I$19='4. Reduktionsfaktorer, LENI-tal'!$T$12,INDEX('4. Reduktionsfaktorer, LENI-tal'!$H$38:$O$45,MATCH(I$21,'4. Reduktionsfaktorer, LENI-tal'!$H$38:$H$45,0),3), I$19='4. Reduktionsfaktorer, LENI-tal'!$U$12,INDEX('4. Reduktionsfaktorer, LENI-tal'!$H$46:$O$54,MATCH(I$21,'4. Reduktionsfaktorer, LENI-tal'!$H$46:$H$54,0),3)), IFERROR( INDEX( tblStrings[], MATCH( 1, (tblStrings[[Cell]:[Cell]]=AllStrings!$D$350) * (tblStrings[[Sheet]:[Sheet]]=AllStrings!$C$433), 0 ), MATCH(Språkval, tblStrings[#Headers], 0) ), ))} -> Fyll i byggnads- och rumstyp ovan | J68: {=IFERROR(_xlfn.IFS(J$19='4. Reduktionsfaktorer, LENI-tal'!$Q$12,INDEX('4. Reduktionsfaktorer, LENI-tal'!$H$13:$O$23,MATCH(J$21,'4. Reduktionsfaktorer, LENI-tal'!$H$13:$H$23,0),3), J$19='4. Reduktionsfaktorer, LENI-tal'!$R$12,INDEX('4. Reduktionsfaktorer, LENI-tal'!$H$24:$O$32,MATCH(J$21,'4. Reduktionsfaktorer, LENI-tal'!$H$24:$H$32,0),3), J$19='4. Reduktionsfaktorer, LENI-tal'!$S$12,INDEX('4. Reduktionsfaktorer, LENI-tal'!$H$33:$O$37,MATCH(J$21,'4. Reduktionsfaktorer, LENI-tal'!$H$33:$H$37,0),3), J$19='4. Reduktionsfaktorer, LENI-tal'!$T$12,INDEX('4. Reduktionsfaktorer, LENI-tal'!$H$38:$O$45,MATCH(J$21,'4. Reduktionsfaktorer, LENI-tal'!$H$38:$H$45,0),3), J$19='4. Reduktionsfaktorer, LENI-tal'!$U$12,INDEX('4. Reduktionsfaktorer, LENI-tal'!$H$46:$O$54,MATCH(J$21,'4. Reduktionsfaktorer, LENI-tal'!$H$46:$H$54,0),3)), IFERROR( INDEX( tblStrings[], MATCH( 1, (tblStrings[[Cell]:[Cell]]=AllStrings!$D$350) * (tblStrings[[Sheet]:[Sheet]]=AllStrings!$C$433), 0 ), MATCH(Språkval, tblStrings[#Headers], 0) ), ))} -> Fyll i byggnads- och rumstyp ovan | K68: {=IFERROR(_xlfn.IFS(K$19='4. Reduktionsfaktorer, LENI-tal'!$Q$12,INDEX('4. Reduktionsfaktorer, LENI-tal'!$H$13:$O$23,MATCH(K$21,'4. Reduktionsfaktorer, LENI-tal'!$H$13:$H$23,0),3), K$19='4. Reduktionsfaktorer, LENI-tal'!$R$12,INDEX('4. Reduktionsfaktorer, LENI-tal'!$H$24:$O$32,MATCH(K$21,'4. Reduktionsfaktorer, LENI-tal'!$H$24:$H$32,0),3), K$19='4. Reduktionsfaktorer, LENI-tal'!$S$12,INDEX('4. Reduktionsfaktorer, LENI-tal'!$H$33:$O$37,MATCH(K$21,'4. Reduktionsfaktorer, LENI-tal'!$H$33:$H$37,0),3), K$19='4. Reduktionsfaktorer, LENI-tal'!$T$12,INDEX('4. Reduktionsfaktorer, LENI-tal'!$H$38:$O$45,MATCH(K$21,'4. Reduktionsfaktorer, LENI-tal'!$H$38:$H$45,0),3), K$19='4. Reduktionsfaktorer, LENI-tal'!$U$12,INDEX('4. Reduktionsfaktorer, LENI-tal'!$H$46:$O$54,MATCH(K$21,'4. Reduktionsfaktorer, LENI-tal'!$H$46:$H$54,0),3)), IFERROR( INDEX( tblStrings[], MATCH( 1, (tblStrings[[Cell]:[Cell]]=AllStrings!$D$350) * (tblStrings[[Sheet]:[Sheet]]=AllStrings!$C$433), 0 ), MATCH(Språkval, tblStrings[#Headers], 0) ), ))} -> Fyll i byggnads- och rumstyp ovan | L68: {=IFERROR(_xlfn.IFS(L$19='4. Reduktionsfaktorer, LENI-tal'!$Q$12,INDEX('4. Reduktionsfaktorer, LENI-tal'!$H$13:$O$23,MATCH(L$21,'4. Reduktionsfaktorer, LENI-tal'!$H$13:$H$23,0),3), L$19='4. Reduktionsfaktorer, LENI-tal'!$R$12,INDEX('4. Reduktionsfaktorer, LENI-tal'!$H$24:$O$32,MATCH(L$21,'4. Reduktionsfaktorer, LENI-tal'!$H$24:$H$32,0),3), L$19='4. Reduktionsfaktorer, LENI-tal'!$S$12,INDEX('4. Reduktionsfaktorer, LENI-tal'!$H$33:$O$37,MATCH(L$21,'4. Reduktionsfaktorer, LENI-tal'!$H$33:$H$37,0),3), L$19='4. Reduktionsfaktorer, LENI-tal'!$T$12,INDEX('4. Reduktionsfaktorer, LENI-tal'!$H$38:$O$45,MATCH(L$21,'4. Reduktionsfaktorer, LENI-tal'!$H$38:$H$45,0),3), L$19='4. Reduktionsfaktorer, LENI-tal'!$U$12,INDEX('4. Reduktionsfaktorer, LENI-tal'!$H$46:$O$54,MATCH(L$21,'4. Reduktionsfaktorer, LENI-tal'!$H$46:$H$54,0),3)), IFERROR( INDEX( tblStrings[], MATCH( 1, (tblStrings[[Cell]:[Cell]]=AllStrings!$D$350) * (tblStrings[[Sheet]:[Sheet]]=AllStrings!$C$433), 0 ), MATCH(Språkval, tblStrings[#Headers], 0) ), ))} -> Fyll i byggnads- och rumstyp ovan | M68: {=IFERROR(_xlfn.IFS(M$19='4. Reduktionsfaktorer, LENI-tal'!$Q$12,INDEX('4. Reduktionsfaktorer, LENI-tal'!$H$13:$O$23,MATCH(M$21,'4. Reduktionsfaktorer, LENI-tal'!$H$13:$H$23,0),3), M$19='4. Reduktionsfaktorer, LENI-tal'!$R$12,INDEX('4. Reduktionsfaktorer, LENI-tal'!$H$24:$O$32,MATCH(M$21,'4. Reduktionsfaktorer, LENI-tal'!$H$24:$H$32,0),3), M$19='4. Reduktionsfaktorer, LENI-tal'!$S$12,INDEX('4. Reduktionsfaktorer, LENI-tal'!$H$33:$O$37,MATCH(M$21,'4. Reduktionsfaktorer, LENI-tal'!$H$33:$H$37,0),3), M$19='4. Reduktionsfaktorer, LENI-tal'!$T$12,INDEX('4. Reduktionsfaktorer, LENI-tal'!$H$38:$O$45,MATCH(M$21,'4. Reduktionsfaktorer, LENI-tal'!$H$38:$H$45,0),3), M$19='4. Reduktionsfaktorer, LENI-tal'!$U$12,INDEX('4. Reduktionsfaktorer, LENI-tal'!$H$46:$O$54,MATCH(M$21,'4. Reduktionsfaktorer, LENI-tal'!$H$46:$H$54,0),3)), IFERROR( INDEX( tblStrings[], MATCH( 1, (tblStrings[[Cell]:[Cell]]=AllStrings!$D$350) * (tblStrings[[Sheet]:[Sheet]]=AllStrings!$C$433), 0 ), MATCH(Språkval, tblStrings[#Headers], 0) ), ))} -> Fyll i byggnads- och rumstyp ovan | N68: {=IFERROR(_xlfn.IFS(N$19='4. Reduktionsfaktorer, LENI-tal'!$Q$12,INDEX('4. Reduktionsfaktorer, LENI-tal'!$H$13:$O$23,MATCH(N$21,'4. Reduktionsfaktorer, LENI-tal'!$H$13:$H$23,0),3), N$19='4. Reduktionsfaktorer, LENI-tal'!$R$12,INDEX('4. Reduktionsfaktorer, LENI-tal'!$H$24:$O$32,MATCH(N$21,'4. Reduktionsfaktorer, LENI-tal'!$H$24:$H$32,0),3), N$19='4. Reduktionsfaktorer, LENI-tal'!$S$12,INDEX('4. Reduktionsfaktorer, LENI-tal'!$H$33:$O$37,MATCH(N$21,'4. Reduktionsfaktorer, LENI-tal'!$H$33:$H$37,0),3), N$19='4. Reduktionsfaktorer, LENI-tal'!$T$12,INDEX('4. Reduktionsfaktorer, LENI-tal'!$H$38:$O$45,MATCH(N$21,'4. Reduktionsfaktorer, LENI-tal'!$H$38:$H$45,0),3), N$19='4. Reduktionsfaktorer, LENI-tal'!$U$12,INDEX('4. Reduktionsfaktorer, LENI-tal'!$H$46:$O$54,MATCH(N$21,'4. Reduktionsfaktorer, LENI-tal'!$H$46:$H$54,0),3)), IFERROR( INDEX( tblStrings[], MATCH( 1, (tblStrings[[Cell]:[Cell]]=AllStrings!$D$350) * (tblStrings[[Sheet]:[Sheet]]=AllStrings!$C$433), 0 ), MATCH(Språkval, tblStrings[#Headers], 0) ), ))} -> Fyll i byggnads- och rumstyp ovan | O68: {=IFERROR(_xlfn.IFS(O$19='4. Reduktionsfaktorer, LENI-tal'!$Q$12,INDEX('4. Reduktionsfaktorer, LENI-tal'!$H$13:$O$23,MATCH(O$21,'4. Reduktionsfaktorer, LENI-tal'!$H$13:$H$23,0),3), O$19='4. Reduktionsfaktorer, LENI-tal'!$R$12,INDEX('4. Reduktionsfaktorer, LENI-tal'!$H$24:$O$32,MATCH(O$21,'4. Reduktionsfaktorer, LENI-tal'!$H$24:$H$32,0),3), O$19='4. Reduktionsfaktorer, LENI-tal'!$S$12,INDEX('4. Reduktionsfaktorer, LENI-tal'!$H$33:$O$37,MATCH(O$21,'4. Reduktionsfaktorer, LENI-tal'!$H$33:$H$37,0),3), O$19='4. Reduktionsfaktorer, LENI-tal'!$T$12,INDEX('4. Reduktionsfaktorer, LENI-tal'!$H$38:$O$45,MATCH(O$21,'4. Reduktionsfaktorer, LENI-tal'!$H$38:$H$45,0),3), O$19='4. Reduktionsfaktorer, LENI-tal'!$U$12,INDEX('4. Reduktionsfaktorer, LENI-tal'!$H$46:$O$54,MATCH(O$21,'4. Reduktionsfaktorer, LENI-tal'!$H$46:$H$54,0),3)), IFERROR( INDEX( tblStrings[], MATCH( 1, (tblStrings[[Cell]:[Cell]]=AllStrings!$D$350) * (tblStrings[[Sheet]:[Sheet]]=AllStrings!$C$433), 0 ), MATCH(Språkval, tblStrings[#Headers], 0) ), ))} -> Fyll i byggnads- och rumstyp ovan | P68: {=IFERROR(_xlfn.IFS(P$19='4. Reduktionsfaktorer, LENI-tal'!$Q$12,INDEX('4. Reduktionsfaktorer, LENI-tal'!$H$13:$O$23,MATCH(P$21,'4. Reduktionsfaktorer, LENI-tal'!$H$13:$H$23,0),3), P$19='4. Reduktionsfaktorer, LENI-tal'!$R$12,INDEX('4. Reduktionsfaktorer, LENI-tal'!$H$24:$O$32,MATCH(P$21,'4. Reduktionsfaktorer, LENI-tal'!$H$24:$H$32,0),3), P$19='4. Reduktionsfaktorer, LENI-tal'!$S$12,INDEX('4. Reduktionsfaktorer, LENI-tal'!$H$33:$O$37,MATCH(P$21,'4. Reduktionsfaktorer, LENI-tal'!$H$33:$H$37,0),3), P$19='4. Reduktionsfaktorer, LENI-tal'!$T$12,INDEX('4. Reduktionsfaktorer, LENI-tal'!$H$38:$O$45,MATCH(P$21,'4. Reduktionsfaktorer, LENI-tal'!$H$38:$H$45,0),3), P$19='4. Reduktionsfaktorer, LENI-tal'!$U$12,INDEX('4. Reduktionsfaktorer, LENI-tal'!$H$46:$O$54,MATCH(P$21,'4. Reduktionsfaktorer, LENI-tal'!$H$46:$H$54,0),3)), IFERROR( INDEX( tblStrings[], MATCH( 1, (tblStrings[[Cell]:[Cell]]=AllStrings!$D$350) * (tblStrings[[Sheet]:[Sheet]]=AllStrings!$C$433), 0 ), MATCH(Språkval, tblStrings[#Headers], 0) ), ))} -> Fyll i byggnads- och rumstyp ovan | ... R68: {=IFERROR(_xlfn.IFS(R$19='4. Reduktionsfaktorer, LENI-tal'!$Q$12,INDEX('4. Reduktionsfaktorer, LENI-tal'!$H$13:$O$23,MATCH(R$21,'4. Reduktionsfaktorer, LENI-tal'!$H$13:$H$23,0),3), R$19='4. Reduktionsfaktorer, LENI-tal'!$R$12,INDEX('4. Reduktionsfaktorer, LENI-tal'!$H$24:$O$32,MATCH(R$21,'4. Reduktionsfaktorer, LENI-tal'!$H$24:$H$32,0),3), R$19='4. Reduktionsfaktorer, LENI-tal'!$S$12,INDEX('4. Reduktionsfaktorer, LENI-tal'!$H$33:$O$37,MATCH(R$21,'4. Reduktionsfaktorer, LENI-tal'!$H$33:$H$37,0),3), R$19='4. Reduktionsfaktorer, LENI-tal'!$T$12,INDEX('4. Reduktionsfaktorer, LENI-tal'!$H$38:$O$45,MATCH(R$21,'4. Reduktionsfaktorer, LENI-tal'!$H$38:$H$45,0),3), R$19='4. Reduktionsfaktorer, LENI-tal'!$U$12,INDEX('4. Reduktionsfaktorer, LENI-tal'!$H$46:$O$54,MATCH(R$21,'4. Reduktionsfaktorer, LENI-tal'!$H$46:$H$54,0),3)), IFERROR( INDEX( tblStrings[], MATCH( 1, (tblStrings[[Cell]:[Cell]]=AllStrings!$D$350) * (tblStrings[[Sheet]:[Sheet]]=AllStrings!$C$433), 0 ), MATCH(Språkval, tblStrings[#Headers], 0) ), ))} -> Fyll i byggnads- och rumstyp ovan
B69: 2.7 | C69: =$C57 -> Reduktionsfaktor närvaro-/frånvarostyrning | I69: {=IFERROR(_xlfn.IFS(I$19='4. Reduktionsfaktorer, LENI-tal'!$Q$12,INDEX('4. Reduktionsfaktorer, LENI-tal'!$H$13:$O$23,MATCH(I$21,'4. Reduktionsfaktorer, LENI-tal'!$H$13:$H$23,0),4), I$19='4. Reduktionsfaktorer, LENI-tal'!$R$12,INDEX('4. Reduktionsfaktorer, LENI-tal'!$H$24:$O$32,MATCH(I$21,'4. Reduktionsfaktorer, LENI-tal'!$H$24:$H$32,0),4), I$19='4. Reduktionsfaktorer, LENI-tal'!$S$12,INDEX('4. Reduktionsfaktorer, LENI-tal'!$H$33:$O$37,MATCH(I$21,'4. Reduktionsfaktorer, LENI-tal'!$H$33:$H$37,0),4), I$19='4. Reduktionsfaktorer, LENI-tal'!$T$12,INDEX('4. Reduktionsfaktorer, LENI-tal'!$H$38:$O$45,MATCH(I$21,'4. Reduktionsfaktorer, LENI-tal'!$H$38:$H$45,0),4), I$19='4. Reduktionsfaktorer, LENI-tal'!$U$12,INDEX('4. Reduktionsfaktorer, LENI-tal'!$H$46:$O$54,MATCH(I$21,'4. Reduktionsfaktorer, LENI-tal'!$H$46:$H$54,0),4)), IFERROR( INDEX( tblStrings[], MATCH( 1, (tblStrings[[Cell]:[Cell]]=AllStrings!$D$350) * (tblStrings[[Sheet]:[Sheet]]=AllStrings!$C$433), 0 ), MATCH(Språkval, tblStrings[#Headers], 0) ), ))} -> Fyll i byggnads- och rumstyp ovan | J69: {=IFERROR(_xlfn.IFS(J$19='4. Reduktionsfaktorer, LENI-tal'!$Q$12,INDEX('4. Reduktionsfaktorer, LENI-tal'!$H$13:$O$23,MATCH(J$21,'4. Reduktionsfaktorer, LENI-tal'!$H$13:$H$23,0),4), J$19='4. Reduktionsfaktorer, LENI-tal'!$R$12,INDEX('4. Reduktionsfaktorer, LENI-tal'!$H$24:$O$32,MATCH(J$21,'4. Reduktionsfaktorer, LENI-tal'!$H$24:$H$32,0),4), J$19='4. Reduktionsfaktorer, LENI-tal'!$S$12,INDEX('4. Reduktionsfaktorer, LENI-tal'!$H$33:$O$37,MATCH(J$21,'4. Reduktionsfaktorer, LENI-tal'!$H$33:$H$37,0),4), J$19='4. Reduktionsfaktorer, LENI-tal'!$T$12,INDEX('4. Reduktionsfaktorer, LENI-tal'!$H$38:$O$45,MATCH(J$21,'4. Reduktionsfaktorer, LENI-tal'!$H$38:$H$45,0),4), J$19='4. Reduktionsfaktorer, LENI-tal'!$U$12,INDEX('4. Reduktionsfaktorer, LENI-tal'!$H$46:$O$54,MATCH(J$21,'4. Reduktionsfaktorer, LENI-tal'!$H$46:$H$54,0),4)), IFERROR( INDEX( tblStrings[], MATCH( 1, (tblStrings[[Cell]:[Cell]]=AllStrings!$D$350) * (tblStrings[[Sheet]:[Sheet]]=AllStrings!$C$433), 0 ), MATCH(Språkval, tblStrings[#Headers], 0) ), ))} -> Fyll i byggnads- och rumstyp ovan | K69: {=IFERROR(_xlfn.IFS(K$19='4. Reduktionsfaktorer, LENI-tal'!$Q$12,INDEX('4. Reduktionsfaktorer, LENI-tal'!$H$13:$O$23,MATCH(K$21,'4. Reduktionsfaktorer, LENI-tal'!$H$13:$H$23,0),4), K$19='4. Reduktionsfaktorer, LENI-tal'!$R$12,INDEX('4. Reduktionsfaktorer, LENI-tal'!$H$24:$O$32,MATCH(K$21,'4. Reduktionsfaktorer, LENI-tal'!$H$24:$H$32,0),4), K$19='4. Reduktionsfaktorer, LENI-tal'!$S$12,INDEX('4. Reduktionsfaktorer, LENI-tal'!$H$33:$O$37,MATCH(K$21,'4. Reduktionsfaktorer, LENI-tal'!$H$33:$H$37,0),4), K$19='4. Reduktionsfaktorer, LENI-tal'!$T$12,INDEX('4. Reduktionsfaktorer, LENI-tal'!$H$38:$O$45,MATCH(K$21,'4. Reduktionsfaktorer, LENI-tal'!$H$38:$H$45,0),4), K$19='4. Reduktionsfaktorer, LENI-tal'!$U$12,INDEX('4. Reduktionsfaktorer, LENI-tal'!$H$46:$O$54,MATCH(K$21,'4. Reduktionsfaktorer, LENI-tal'!$H$46:$H$54,0),4)), IFERROR( INDEX( tblStrings[], MATCH( 1, (tblStrings[[Cell]:[Cell]]=AllStrings!$D$350) * (tblStrings[[Sheet]:[Sheet]]=AllStrings!$C$433), 0 ), MATCH(Språkval, tblStrings[#Headers], 0) ), ))} -> Fyll i byggnads- och rumstyp ovan | L69: {=IFERROR(_xlfn.IFS(L$19='4. Reduktionsfaktorer, LENI-tal'!$Q$12,INDEX('4. Reduktionsfaktorer, LENI-tal'!$H$13:$O$23,MATCH(L$21,'4. Reduktionsfaktorer, LENI-tal'!$H$13:$H$23,0),4), L$19='4. Reduktionsfaktorer, LENI-tal'!$R$12,INDEX('4. Reduktionsfaktorer, LENI-tal'!$H$24:$O$32,MATCH(L$21,'4. Reduktionsfaktorer, LENI-tal'!$H$24:$H$32,0),4), L$19='4. Reduktionsfaktorer, LENI-tal'!$S$12,INDEX('4. Reduktionsfaktorer, LENI-tal'!$H$33:$O$37,MATCH(L$21,'4. Reduktionsfaktorer, LENI-tal'!$H$33:$H$37,0),4), L$19='4. Reduktionsfaktorer, LENI-tal'!$T$12,INDEX('4. Reduktionsfaktorer, LENI-tal'!$H$38:$O$45,MATCH(L$21,'4. Reduktionsfaktorer, LENI-tal'!$H$38:$H$45,0),4), L$19='4. Reduktionsfaktorer, LENI-tal'!$U$12,INDEX('4. Reduktionsfaktorer, LENI-tal'!$H$46:$O$54,MATCH(L$21,'4. Reduktionsfaktorer, LENI-tal'!$H$46:$H$54,0),4)), IFERROR( INDEX( tblStrings[], MATCH( 1, (tblStrings[[Cell]:[Cell]]=AllStrings!$D$350) * (tblStrings[[Sheet]:[Sheet]]=AllStrings!$C$433), 0 ), MATCH(Språkval, tblStrings[#Headers], 0) ), ))} -> Fyll i byggnads- och rumstyp ovan | M69: {=IFERROR(_xlfn.IFS(M$19='4. Reduktionsfaktorer, LENI-tal'!$Q$12,INDEX('4. Reduktionsfaktorer, LENI-tal'!$H$13:$O$23,MATCH(M$21,'4. Reduktionsfaktorer, LENI-tal'!$H$13:$H$23,0),4), M$19='4. Reduktionsfaktorer, LENI-tal'!$R$12,INDEX('4. Reduktionsfaktorer, LENI-tal'!$H$24:$O$32,MATCH(M$21,'4. Reduktionsfaktorer, LENI-tal'!$H$24:$H$32,0),4), M$19='4. Reduktionsfaktorer, LENI-tal'!$S$12,INDEX('4. Reduktionsfaktorer, LENI-tal'!$H$33:$O$37,MATCH(M$21,'4. Reduktionsfaktorer, LENI-tal'!$H$33:$H$37,0),4), M$19='4. Reduktionsfaktorer, LENI-tal'!$T$12,INDEX('4. Reduktionsfaktorer, LENI-tal'!$H$38:$O$45,MATCH(M$21,'4. Reduktionsfaktorer, LENI-tal'!$H$38:$H$45,0),4), M$19='4. Reduktionsfaktorer, LENI-tal'!$U$12,INDEX('4. Reduktionsfaktorer, LENI-tal'!$H$46:$O$54,MATCH(M$21,'4. Reduktionsfaktorer, LENI-tal'!$H$46:$H$54,0),4)), IFERROR( INDEX( tblStrings[], MATCH( 1, (tblStrings[[Cell]:[Cell]]=AllStrings!$D$350) * (tblStrings[[Sheet]:[Sheet]]=AllStrings!$C$433), 0 ), MATCH(Språkval, tblStrings[#Headers], 0) ), ))} -> Fyll i byggnads- och rumstyp ovan | N69: {=IFERROR(_xlfn.IFS(N$19='4. Reduktionsfaktorer, LENI-tal'!$Q$12,INDEX('4. Reduktionsfaktorer, LENI-tal'!$H$13:$O$23,MATCH(N$21,'4. Reduktionsfaktorer, LENI-tal'!$H$13:$H$23,0),4), N$19='4. Reduktionsfaktorer, LENI-tal'!$R$12,INDEX('4. Reduktionsfaktorer, LENI-tal'!$H$24:$O$32,MATCH(N$21,'4. Reduktionsfaktorer, LENI-tal'!$H$24:$H$32,0),4), N$19='4. Reduktionsfaktorer, LENI-tal'!$S$12,INDEX('4. Reduktionsfaktorer, LENI-tal'!$H$33:$O$37,MATCH(N$21,'4. Reduktionsfaktorer, LENI-tal'!$H$33:$H$37,0),4), N$19='4. Reduktionsfaktorer, LENI-tal'!$T$12,INDEX('4. Reduktionsfaktorer, LENI-tal'!$H$38:$O$45,MATCH(N$21,'4. Reduktionsfaktorer, LENI-tal'!$H$38:$H$45,0),4), N$19='4. Reduktionsfaktorer, LENI-tal'!$U$12,INDEX('4. Reduktionsfaktorer, LENI-tal'!$H$46:$O$54,MATCH(N$21,'4. Reduktionsfaktorer, LENI-tal'!$H$46:$H$54,0),4)), IFERROR( INDEX( tblStrings[], MATCH( 1, (tblStrings[[Cell]:[Cell]]=AllStrings!$D$350) * (tblStrings[[Sheet]:[Sheet]]=AllStrings!$C$433), 0 ), MATCH(Språkval, tblStrings[#Headers], 0) ), ))} -> Fyll i byggnads- och rumstyp ovan | O69: {=IFERROR(_xlfn.IFS(O$19='4. Reduktionsfaktorer, LENI-tal'!$Q$12,INDEX('4. Reduktionsfaktorer, LENI-tal'!$H$13:$O$23,MATCH(O$21,'4. Reduktionsfaktorer, LENI-tal'!$H$13:$H$23,0),4), O$19='4. Reduktionsfaktorer, LENI-tal'!$R$12,INDEX('4. Reduktionsfaktorer, LENI-tal'!$H$24:$O$32,MATCH(O$21,'4. Reduktionsfaktorer, LENI-tal'!$H$24:$H$32,0),4), O$19='4. Reduktionsfaktorer, LENI-tal'!$S$12,INDEX('4. Reduktionsfaktorer, LENI-tal'!$H$33:$O$37,MATCH(O$21,'4. Reduktionsfaktorer, LENI-tal'!$H$33:$H$37,0),4), O$19='4. Reduktionsfaktorer, LENI-tal'!$T$12,INDEX('4. Reduktionsfaktorer, LENI-tal'!$H$38:$O$45,MATCH(O$21,'4. Reduktionsfaktorer, LENI-tal'!$H$38:$H$45,0),4), O$19='4. Reduktionsfaktorer, LENI-tal'!$U$12,INDEX('4. Reduktionsfaktorer, LENI-tal'!$H$46:$O$54,MATCH(O$21,'4. Reduktionsfaktorer, LENI-tal'!$H$46:$H$54,0),4)), IFERROR( INDEX( tblStrings[], MATCH( 1, (tblStrings[[Cell]:[Cell]]=AllStrings!$D$350) * (tblStrings[[Sheet]:[Sheet]]=AllStrings!$C$433), 0 ), MATCH(Språkval, tblStrings[#Headers], 0) ), ))} -> Fyll i byggnads- och rumstyp ovan | P69: {=IFERROR(_xlfn.IFS(P$19='4. Reduktionsfaktorer, LENI-tal'!$Q$12,INDEX('4. Reduktionsfaktorer, LENI-tal'!$H$13:$O$23,MATCH(P$21,'4. Reduktionsfaktorer, LENI-tal'!$H$13:$H$23,0),4), P$19='4. Reduktionsfaktorer, LENI-tal'!$R$12,INDEX('4. Reduktionsfaktorer, LENI-tal'!$H$24:$O$32,MATCH(P$21,'4. Reduktionsfaktorer, LENI-tal'!$H$24:$H$32,0),4), P$19='4. Reduktionsfaktorer, LENI-tal'!$S$12,INDEX('4. Reduktionsfaktorer, LENI-tal'!$H$33:$O$37,MATCH(P$21,'4. Reduktionsfaktorer, LENI-tal'!$H$33:$H$37,0),4), P$19='4. Reduktionsfaktorer, LENI-tal'!$T$12,INDEX('4. Reduktionsfaktorer, LENI-tal'!$H$38:$O$45,MATCH(P$21,'4. Reduktionsfaktorer, LENI-tal'!$H$38:$H$45,0),4), P$19='4. Reduktionsfaktorer, LENI-tal'!$U$12,INDEX('4. Reduktionsfaktorer, LENI-tal'!$H$46:$O$54,MATCH(P$21,'4. Reduktionsfaktorer, LENI-tal'!$H$46:$H$54,0),4)), IFERROR( INDEX( tblStrings[], MATCH( 1, (tblStrings[[Cell]:[Cell]]=AllStrings!$D$350) * (tblStrings[[Sheet]:[Sheet]]=AllStrings!$C$433), 0 ), MATCH(Språkval, tblStrings[#Headers], 0) ), ))} -> Fyll i byggnads- och rumstyp ovan | ... R69: {=IFERROR(_xlfn.IFS(R$19='4. Reduktionsfaktorer, LENI-tal'!$Q$12,INDEX('4. Reduktionsfaktorer, LENI-tal'!$H$13:$O$23,MATCH(R$21,'4. Reduktionsfaktorer, LENI-tal'!$H$13:$H$23,0),4), R$19='4. Reduktionsfaktorer, LENI-tal'!$R$12,INDEX('4. Reduktionsfaktorer, LENI-tal'!$H$24:$O$32,MATCH(R$21,'4. Reduktionsfaktorer, LENI-tal'!$H$24:$H$32,0),4), R$19='4. Reduktionsfaktorer, LENI-tal'!$S$12,INDEX('4. Reduktionsfaktorer, LENI-tal'!$H$33:$O$37,MATCH(R$21,'4. Reduktionsfaktorer, LENI-tal'!$H$33:$H$37,0),4), R$19='4. Reduktionsfaktorer, LENI-tal'!$T$12,INDEX('4. Reduktionsfaktorer, LENI-tal'!$H$38:$O$45,MATCH(R$21,'4. Reduktionsfaktorer, LENI-tal'!$H$38:$H$45,0),4), R$19='4. Reduktionsfaktorer, LENI-tal'!$U$12,INDEX('4. Reduktionsfaktorer, LENI-tal'!$H$46:$O$54,MATCH(R$21,'4. Reduktionsfaktorer, LENI-tal'!$H$46:$H$54,0),4)), IFERROR( INDEX( tblStrings[], MATCH( 1, (tblStrings[[Cell]:[Cell]]=AllStrings!$D$350) * (tblStrings[[Sheet]:[Sheet]]=AllStrings!$C$433), 0 ), MATCH(Språkval, tblStrings[#Headers], 0) ), ))} -> Fyll i byggnads- och rumstyp ovan
B70: 2.8 | C70: =$C58 -> Reduktionsfaktor dagsljusstyrning | I70: {=IFERROR(_xlfn.IFS(I$19='4. Reduktionsfaktorer, LENI-tal'!$Q$12,INDEX('4. Reduktionsfaktorer, LENI-tal'!$H$13:$O$23,MATCH(I$21,'4. Reduktionsfaktorer, LENI-tal'!$H$13:$H$23,0),5), I$19='4. Reduktionsfaktorer, LENI-tal'!$R$12,INDEX('4. Reduktionsfaktorer, LENI-tal'!$H$24:$O$32,MATCH(I$21,'4. Reduktionsfaktorer, LENI-tal'!$H$24:$H$32,0),5), I$19='4. Reduktionsfaktorer, LENI-tal'!$S$12,INDEX('4. Reduktionsfaktorer, LENI-tal'!$H$33:$O$37,MATCH(I$21,'4. Reduktionsfaktorer, LENI-tal'!$H$33:$H$37,0),5), I$19='4. Reduktionsfaktorer, LENI-tal'!$T$12,INDEX('4. Reduktionsfaktorer, LENI-tal'!$H$38:$O$45,MATCH(I$21,'4. Reduktionsfaktorer, LENI-tal'!$H$38:$H$45,0),5), I$19='4. Reduktionsfaktorer, LENI-tal'!$U$12,INDEX('4. Reduktionsfaktorer, LENI-tal'!$H$46:$O$54,MATCH(I$21,'4. Reduktionsfaktorer, LENI-tal'!$H$46:$H$54,0),5)), IFERROR( INDEX( tblStrings[], MATCH( 1, (tblStrings[[Cell]:[Cell]]=AllStrings!$D$350) * (tblStrings[[Sheet]:[Sheet]]=AllStrings!$C$433), 0 ), MATCH(Språkval, tblStrings[#Headers], 0) ), ))} -> Fyll i byggnads- och rumstyp ovan | J70: {=IFERROR(_xlfn.IFS(J$19='4. Reduktionsfaktorer, LENI-tal'!$Q$12,INDEX('4. Reduktionsfaktorer, LENI-tal'!$H$13:$O$23,MATCH(J$21,'4. Reduktionsfaktorer, LENI-tal'!$H$13:$H$23,0),5), J$19='4. Reduktionsfaktorer, LENI-tal'!$R$12,INDEX('4. Reduktionsfaktorer, LENI-tal'!$H$24:$O$32,MATCH(J$21,'4. Reduktionsfaktorer, LENI-tal'!$H$24:$H$32,0),5), J$19='4. Reduktionsfaktorer, LENI-tal'!$S$12,INDEX('4. Reduktionsfaktorer, LENI-tal'!$H$33:$O$37,MATCH(J$21,'4. Reduktionsfaktorer, LENI-tal'!$H$33:$H$37,0),5), J$19='4. Reduktionsfaktorer, LENI-tal'!$T$12,INDEX('4. Reduktionsfaktorer, LENI-tal'!$H$38:$O$45,MATCH(J$21,'4. Reduktionsfaktorer, LENI-tal'!$H$38:$H$45,0),5), J$19='4. Reduktionsfaktorer, LENI-tal'!$U$12,INDEX('4. Reduktionsfaktorer, LENI-tal'!$H$46:$O$54,MATCH(J$21,'4. Reduktionsfaktorer, LENI-tal'!$H$46:$H$54,0),5)), IFERROR( INDEX( tblStrings[], MATCH( 1, (tblStrings[[Cell]:[Cell]]=AllStrings!$D$350) * (tblStrings[[Sheet]:[Sheet]]=AllStrings!$C$433), 0 ), MATCH(Språkval, tblStrings[#Headers], 0) ), ))} -> Fyll i byggnads- och rumstyp ovan | K70: {=IFERROR(_xlfn.IFS(K$19='4. Reduktionsfaktorer, LENI-tal'!$Q$12,INDEX('4. Reduktionsfaktorer, LENI-tal'!$H$13:$O$23,MATCH(K$21,'4. Reduktionsfaktorer, LENI-tal'!$H$13:$H$23,0),5), K$19='4. Reduktionsfaktorer, LENI-tal'!$R$12,INDEX('4. Reduktionsfaktorer, LENI-tal'!$H$24:$O$32,MATCH(K$21,'4. Reduktionsfaktorer, LENI-tal'!$H$24:$H$32,0),5), K$19='4. Reduktionsfaktorer, LENI-tal'!$S$12,INDEX('4. Reduktionsfaktorer, LENI-tal'!$H$33:$O$37,MATCH(K$21,'4. Reduktionsfaktorer, LENI-tal'!$H$33:$H$37,0),5), K$19='4. Reduktionsfaktorer, LENI-tal'!$T$12,INDEX('4. Reduktionsfaktorer, LENI-tal'!$H$38:$O$45,MATCH(K$21,'4. Reduktionsfaktorer, LENI-tal'!$H$38:$H$45,0),5), K$19='4. Reduktionsfaktorer, LENI-tal'!$U$12,INDEX('4. Reduktionsfaktorer, LENI-tal'!$H$46:$O$54,MATCH(K$21,'4. Reduktionsfaktorer, LENI-tal'!$H$46:$H$54,0),5)), IFERROR( INDEX( tblStrings[], MATCH( 1, (tblStrings[[Cell]:[Cell]]=AllStrings!$D$350) * (tblStrings[[Sheet]:[Sheet]]=AllStrings!$C$433), 0 ), MATCH(Språkval, tblStrings[#Headers], 0) ), ))} -> Fyll i byggnads- och rumstyp ovan | L70: {=IFERROR(_xlfn.IFS(L$19='4. Reduktionsfaktorer, LENI-tal'!$Q$12,INDEX('4. Reduktionsfaktorer, LENI-tal'!$H$13:$O$23,MATCH(L$21,'4. Reduktionsfaktorer, LENI-tal'!$H$13:$H$23,0),5), L$19='4. Reduktionsfaktorer, LENI-tal'!$R$12,INDEX('4. Reduktionsfaktorer, LENI-tal'!$H$24:$O$32,MATCH(L$21,'4. Reduktionsfaktorer, LENI-tal'!$H$24:$H$32,0),5), L$19='4. Reduktionsfaktorer, LENI-tal'!$S$12,INDEX('4. Reduktionsfaktorer, LENI-tal'!$H$33:$O$37,MATCH(L$21,'4. Reduktionsfaktorer, LENI-tal'!$H$33:$H$37,0),5), L$19='4. Reduktionsfaktorer, LENI-tal'!$T$12,INDEX('4. Reduktionsfaktorer, LENI-tal'!$H$38:$O$45,MATCH(L$21,'4. Reduktionsfaktorer, LENI-tal'!$H$38:$H$45,0),5), L$19='4. Reduktionsfaktorer, LENI-tal'!$U$12,INDEX('4. Reduktionsfaktorer, LENI-tal'!$H$46:$O$54,MATCH(L$21,'4. Reduktionsfaktorer, LENI-tal'!$H$46:$H$54,0),5)), IFERROR( INDEX( tblStrings[], MATCH( 1, (tblStrings[[Cell]:[Cell]]=AllStrings!$D$350) * (tblStrings[[Sheet]:[Sheet]]=AllStrings!$C$433), 0 ), MATCH(Språkval, tblStrings[#Headers], 0) ), ))} -> Fyll i byggnads- och rumstyp ovan | M70: {=IFERROR(_xlfn.IFS(M$19='4. Reduktionsfaktorer, LENI-tal'!$Q$12,INDEX('4. Reduktionsfaktorer, LENI-tal'!$H$13:$O$23,MATCH(M$21,'4. Reduktionsfaktorer, LENI-tal'!$H$13:$H$23,0),5), M$19='4. Reduktionsfaktorer, LENI-tal'!$R$12,INDEX('4. Reduktionsfaktorer, LENI-tal'!$H$24:$O$32,MATCH(M$21,'4. Reduktionsfaktorer, LENI-tal'!$H$24:$H$32,0),5), M$19='4. Reduktionsfaktorer, LENI-tal'!$S$12,INDEX('4. Reduktionsfaktorer, LENI-tal'!$H$33:$O$37,MATCH(M$21,'4. Reduktionsfaktorer, LENI-tal'!$H$33:$H$37,0),5), M$19='4. Reduktionsfaktorer, LENI-tal'!$T$12,INDEX('4. Reduktionsfaktorer, LENI-tal'!$H$38:$O$45,MATCH(M$21,'4. Reduktionsfaktorer, LENI-tal'!$H$38:$H$45,0),5), M$19='4. Reduktionsfaktorer, LENI-tal'!$U$12,INDEX('4. Reduktionsfaktorer, LENI-tal'!$H$46:$O$54,MATCH(M$21,'4. Reduktionsfaktorer, LENI-tal'!$H$46:$H$54,0),5)), IFERROR( INDEX( tblStrings[], MATCH( 1, (tblStrings[[Cell]:[Cell]]=AllStrings!$D$350) * (tblStrings[[Sheet]:[Sheet]]=AllStrings!$C$433), 0 ), MATCH(Språkval, tblStrings[#Headers], 0) ), ))} -> Fyll i byggnads- och rumstyp ovan | N70: {=IFERROR(_xlfn.IFS(N$19='4. Reduktionsfaktorer, LENI-tal'!$Q$12,INDEX('4. Reduktionsfaktorer, LENI-tal'!$H$13:$O$23,MATCH(N$21,'4. Reduktionsfaktorer, LENI-tal'!$H$13:$H$23,0),5), N$19='4. Reduktionsfaktorer, LENI-tal'!$R$12,INDEX('4. Reduktionsfaktorer, LENI-tal'!$H$24:$O$32,MATCH(N$21,'4. Reduktionsfaktorer, LENI-tal'!$H$24:$H$32,0),5), N$19='4. Reduktionsfaktorer, LENI-tal'!$S$12,INDEX('4. Reduktionsfaktorer, LENI-tal'!$H$33:$O$37,MATCH(N$21,'4. Reduktionsfaktorer, LENI-tal'!$H$33:$H$37,0),5), N$19='4. Reduktionsfaktorer, LENI-tal'!$T$12,INDEX('4. Reduktionsfaktorer, LENI-tal'!$H$38:$O$45,MATCH(N$21,'4. Reduktionsfaktorer, LENI-tal'!$H$38:$H$45,0),5), N$19='4. Reduktionsfaktorer, LENI-tal'!$U$12,INDEX('4. Reduktionsfaktorer, LENI-tal'!$H$46:$O$54,MATCH(N$21,'4. Reduktionsfaktorer, LENI-tal'!$H$46:$H$54,0),5)), IFERROR( INDEX( tblStrings[], MATCH( 1, (tblStrings[[Cell]:[Cell]]=AllStrings!$D$350) * (tblStrings[[Sheet]:[Sheet]]=AllStrings!$C$433), 0 ), MATCH(Språkval, tblStrings[#Headers], 0) ), ))} -> Fyll i byggnads- och rumstyp ovan | O70: {=IFERROR(_xlfn.IFS(O$19='4. Reduktionsfaktorer, LENI-tal'!$Q$12,INDEX('4. Reduktionsfaktorer, LENI-tal'!$H$13:$O$23,MATCH(O$21,'4. Reduktionsfaktorer, LENI-tal'!$H$13:$H$23,0),5), O$19='4. Reduktionsfaktorer, LENI-tal'!$R$12,INDEX('4. Reduktionsfaktorer, LENI-tal'!$H$24:$O$32,MATCH(O$21,'4. Reduktionsfaktorer, LENI-tal'!$H$24:$H$32,0),5), O$19='4. Reduktionsfaktorer, LENI-tal'!$S$12,INDEX('4. Reduktionsfaktorer, LENI-tal'!$H$33:$O$37,MATCH(O$21,'4. Reduktionsfaktorer, LENI-tal'!$H$33:$H$37,0),5), O$19='4. Reduktionsfaktorer, LENI-tal'!$T$12,INDEX('4. Reduktionsfaktorer, LENI-tal'!$H$38:$O$45,MATCH(O$21,'4. Reduktionsfaktorer, LENI-tal'!$H$38:$H$45,0),5), O$19='4. Reduktionsfaktorer, LENI-tal'!$U$12,INDEX('4. Reduktionsfaktorer, LENI-tal'!$H$46:$O$54,MATCH(O$21,'4. Reduktionsfaktorer, LENI-tal'!$H$46:$H$54,0),5)), IFERROR( INDEX( tblStrings[], MATCH( 1, (tblStrings[[Cell]:[Cell]]=AllStrings!$D$350) * (tblStrings[[Sheet]:[Sheet]]=AllStrings!$C$433), 0 ), MATCH(Språkval, tblStrings[#Headers], 0) ), ))} -> Fyll i byggnads- och rumstyp ovan | P70: {=IFERROR(_xlfn.IFS(P$19='4. Reduktionsfaktorer, LENI-tal'!$Q$12,INDEX('4. Reduktionsfaktorer, LENI-tal'!$H$13:$O$23,MATCH(P$21,'4. Reduktionsfaktorer, LENI-tal'!$H$13:$H$23,0),5), P$19='4. Reduktionsfaktorer, LENI-tal'!$R$12,INDEX('4. Reduktionsfaktorer, LENI-tal'!$H$24:$O$32,MATCH(P$21,'4. Reduktionsfaktorer, LENI-tal'!$H$24:$H$32,0),5), P$19='4. Reduktionsfaktorer, LENI-tal'!$S$12,INDEX('4. Reduktionsfaktorer, LENI-tal'!$H$33:$O$37,MATCH(P$21,'4. Reduktionsfaktorer, LENI-tal'!$H$33:$H$37,0),5), P$19='4. Reduktionsfaktorer, LENI-tal'!$T$12,INDEX('4. Reduktionsfaktorer, LENI-tal'!$H$38:$O$45,MATCH(P$21,'4. Reduktionsfaktorer, LENI-tal'!$H$38:$H$45,0),5), P$19='4. Reduktionsfaktorer, LENI-tal'!$U$12,INDEX('4. Reduktionsfaktorer, LENI-tal'!$H$46:$O$54,MATCH(P$21,'4. Reduktionsfaktorer, LENI-tal'!$H$46:$H$54,0),5)), IFERROR( INDEX( tblStrings[], MATCH( 1, (tblStrings[[Cell]:[Cell]]=AllStrings!$D$350) * (tblStrings[[Sheet]:[Sheet]]=AllStrings!$C$433), 0 ), MATCH(Språkval, tblStrings[#Headers], 0) ), ))} -> Fyll i byggnads- och rumstyp ovan | ... R70: {=IFERROR(_xlfn.IFS(R$19='4. Reduktionsfaktorer, LENI-tal'!$Q$12,INDEX('4. Reduktionsfaktorer, LENI-tal'!$H$13:$O$23,MATCH(R$21,'4. Reduktionsfaktorer, LENI-tal'!$H$13:$H$23,0),5), R$19='4. Reduktionsfaktorer, LENI-tal'!$R$12,INDEX('4. Reduktionsfaktorer, LENI-tal'!$H$24:$O$32,MATCH(R$21,'4. Reduktionsfaktorer, LENI-tal'!$H$24:$H$32,0),5), R$19='4. Reduktionsfaktorer, LENI-tal'!$S$12,INDEX('4. Reduktionsfaktorer, LENI-tal'!$H$33:$O$37,MATCH(R$21,'4. Reduktionsfaktorer, LENI-tal'!$H$33:$H$37,0),5), R$19='4. Reduktionsfaktorer, LENI-tal'!$T$12,INDEX('4. Reduktionsfaktorer, LENI-tal'!$H$38:$O$45,MATCH(R$21,'4. Reduktionsfaktorer, LENI-tal'!$H$38:$H$45,0),5), R$19='4. Reduktionsfaktorer, LENI-tal'!$U$12,INDEX('4. Reduktionsfaktorer, LENI-tal'!$H$46:$O$54,MATCH(R$21,'4. Reduktionsfaktorer, LENI-tal'!$H$46:$H$54,0),5)), IFERROR( INDEX( tblStrings[], MATCH( 1, (tblStrings[[Cell]:[Cell]]=AllStrings!$D$350) * (tblStrings[[Sheet]:[Sheet]]=AllStrings!$C$433), 0 ), MATCH(Språkval, tblStrings[#Headers], 0) ), ))} -> Fyll i byggnads- och rumstyp ovan
B71: 2.9 | C71: =$C$35 -> Total reduktionsfaktor för styrning | I71: =IF(IF(I67=$I$233,I68,IF(I67=$I$234,I68*I69,IF(I67=$I$235,I68*I69*I70,1)))=0,"Fyll i 2.6-2.8",IF(I67=$I$233,I68,IF(I67=$I$234,I68*I69,IF(I67=$I$235,I68*I69*I70,1)))) -> 1 | J71: =IF(IF(J67=$I$233,J68,IF(J67=$I$234,J68*J69,IF(J67=$I$235,J68*J69*J70,1)))=0,"Fyll i 2.6-2.8",IF(J67=$I$233,J68,IF(J67=$I$234,J68*J69,IF(J67=$I$235,J68*J69*J70,1)))) -> 1 | K71: =IF(IF(K67=$I$233,K68,IF(K67=$I$234,K68*K69,IF(K67=$I$235,K68*K69*K70,1)))=0,"Fyll i 2.6-2.8",IF(K67=$I$233,K68,IF(K67=$I$234,K68*K69,IF(K67=$I$235,K68*K69*K70,1)))) -> 1 | L71: =IF(IF(L67=$I$233,L68,IF(L67=$I$234,L68*L69,IF(L67=$I$235,L68*L69*L70,1)))=0,"Fyll i 2.6-2.8",IF(L67=$I$233,L68,IF(L67=$I$234,L68*L69,IF(L67=$I$235,L68*L69*L70,1)))) -> 1 | M71: =IF(IF(M67=$I$233,M68,IF(M67=$I$234,M68*M69,IF(M67=$I$235,M68*M69*M70,1)))=0,"Fyll i 2.6-2.8",IF(M67=$I$233,M68,IF(M67=$I$234,M68*M69,IF(M67=$I$235,M68*M69*M70,1)))) -> 1 | N71: =IF(IF(N67=$I$233,N68,IF(N67=$I$234,N68*N69,IF(N67=$I$235,N68*N69*N70,1)))=0,"Fyll i 2.6-2.8",IF(N67=$I$233,N68,IF(N67=$I$234,N68*N69,IF(N67=$I$235,N68*N69*N70,1)))) -> 1 | O71: =IF(IF(O67=$I$233,O68,IF(O67=$I$234,O68*O69,IF(O67=$I$235,O68*O69*O70,1)))=0,"Fyll i 2.6-2.8",IF(O67=$I$233,O68,IF(O67=$I$234,O68*O69,IF(O67=$I$235,O68*O69*O70,1)))) -> 1 | P71: =IF(IF(P67=$I$233,P68,IF(P67=$I$234,P68*P69,IF(P67=$I$235,P68*P69*P70,1)))=0,"Fyll i 2.6-2.8",IF(P67=$I$233,P68,IF(P67=$I$234,P68*P69,IF(P67=$I$235,P68*P69*P70,1)))) -> 1 | ... R71: =IF(IF(R67=$I$233,R68,IF(R67=$I$234,R68*R69,IF(R67=$I$235,R68*R69*R70,1)))=0,"Fyll i 2.6-2.8",IF(R67=$I$233,R68,IF(R67=$I$234,R68*R69,IF(R67=$I$235,R68*R69*R70,1)))) -> 1
B72: 2.10 | C72: =$C$36 -> Underhållskostnader | H72: =$H$36 -> kr/år
C74: =$C$26 -> Armaturbeteckning
B75: 2.1 | C75: =$C$27 -> Antal armaturer | H75: =$H$27 -> stk
B76: 2.2 | C76: =$C$28 -> Armaturpris | H76: =$H$28 -> kr/stk
B77: 2.3 | C77: =$C$29 -> Material- och arbetskostnader armatur | H77: =$H$29 -> kr
B78: 2.4 | C78: =$C$30 -> Effekt per armatur, inkl. driftsförluster | H78: =$H$30 -> W/stk
B79: 2.5 | C79: =$C$31 -> Typ av styrning
B80: 2.6 | C80: =$C68 -> Reduktionsfaktor manuell styrning | I80: {=IFERROR(_xlfn.IFS(I$19='4. Reduktionsfaktorer, LENI-tal'!$Q$12,INDEX('4. Reduktionsfaktorer, LENI-tal'!$H$13:$O$23,MATCH(I$21,'4. Reduktionsfaktorer, LENI-tal'!$H$13:$H$23,0),3), I$19='4. Reduktionsfaktorer, LENI-tal'!$R$12,INDEX('4. Reduktionsfaktorer, LENI-tal'!$H$24:$O$32,MATCH(I$21,'4. Reduktionsfaktorer, LENI-tal'!$H$24:$H$32,0),3), I$19='4. Reduktionsfaktorer, LENI-tal'!$S$12,INDEX('4. Reduktionsfaktorer, LENI-tal'!$H$33:$O$37,MATCH(I$21,'4. Reduktionsfaktorer, LENI-tal'!$H$33:$H$37,0),3), I$19='4. Reduktionsfaktorer, LENI-tal'!$T$12,INDEX('4. Reduktionsfaktorer, LENI-tal'!$H$38:$O$45,MATCH(I$21,'4. Reduktionsfaktorer, LENI-tal'!$H$38:$H$45,0),3), I$19='4. Reduktionsfaktorer, LENI-tal'!$U$12,INDEX('4. Reduktionsfaktorer, LENI-tal'!$H$46:$O$54,MATCH(I$21,'4. Reduktionsfaktorer, LENI-tal'!$H$46:$H$54,0),3)), IFERROR( INDEX( tblStrings[], MATCH( 1, (tblStrings[[Cell]:[Cell]]=AllStrings!$D$350) * (tblStrings[[Sheet]:[Sheet]]=AllStrings!$C$433), 0 ), MATCH(Språkval, tblStrings[#Headers], 0) ), ))} -> Fyll i byggnads- och rumstyp ovan | J80: {=IFERROR(_xlfn.IFS(J$19='4. Reduktionsfaktorer, LENI-tal'!$Q$12,INDEX('4. Reduktionsfaktorer, LENI-tal'!$H$13:$O$23,MATCH(J$21,'4. Reduktionsfaktorer, LENI-tal'!$H$13:$H$23,0),3), J$19='4. Reduktionsfaktorer, LENI-tal'!$R$12,INDEX('4. Reduktionsfaktorer, LENI-tal'!$H$24:$O$32,MATCH(J$21,'4. Reduktionsfaktorer, LENI-tal'!$H$24:$H$32,0),3), J$19='4. Reduktionsfaktorer, LENI-tal'!$S$12,INDEX('4. Reduktionsfaktorer, LENI-tal'!$H$33:$O$37,MATCH(J$21,'4. Reduktionsfaktorer, LENI-tal'!$H$33:$H$37,0),3), J$19='4. Reduktionsfaktorer, LENI-tal'!$T$12,INDEX('4. Reduktionsfaktorer, LENI-tal'!$H$38:$O$45,MATCH(J$21,'4. Reduktionsfaktorer, LENI-tal'!$H$38:$H$45,0),3), J$19='4. Reduktionsfaktorer, LENI-tal'!$U$12,INDEX('4. Reduktionsfaktorer, LENI-tal'!$H$46:$O$54,MATCH(J$21,'4. Reduktionsfaktorer, LENI-tal'!$H$46:$H$54,0),3)), IFERROR( INDEX( tblStrings[], MATCH( 1, (tblStrings[[Cell]:[Cell]]=AllStrings!$D$350) * (tblStrings[[Sheet]:[Sheet]]=AllStrings!$C$433), 0 ), MATCH(Språkval, tblStrings[#Headers], 0) ), ))} -> Fyll i byggnads- och rumstyp ovan | K80: {=IFERROR(_xlfn.IFS(K$19='4. Reduktionsfaktorer, LENI-tal'!$Q$12,INDEX('4. Reduktionsfaktorer, LENI-tal'!$H$13:$O$23,MATCH(K$21,'4. Reduktionsfaktorer, LENI-tal'!$H$13:$H$23,0),3), K$19='4. Reduktionsfaktorer, LENI-tal'!$R$12,INDEX('4. Reduktionsfaktorer, LENI-tal'!$H$24:$O$32,MATCH(K$21,'4. Reduktionsfaktorer, LENI-tal'!$H$24:$H$32,0),3), K$19='4. Reduktionsfaktorer, LENI-tal'!$S$12,INDEX('4. Reduktionsfaktorer, LENI-tal'!$H$33:$O$37,MATCH(K$21,'4. Reduktionsfaktorer, LENI-tal'!$H$33:$H$37,0),3), K$19='4. Reduktionsfaktorer, LENI-tal'!$T$12,INDEX('4. Reduktionsfaktorer, LENI-tal'!$H$38:$O$45,MATCH(K$21,'4. Reduktionsfaktorer, LENI-tal'!$H$38:$H$45,0),3), K$19='4. Reduktionsfaktorer, LENI-tal'!$U$12,INDEX('4. Reduktionsfaktorer, LENI-tal'!$H$46:$O$54,MATCH(K$21,'4. Reduktionsfaktorer, LENI-tal'!$H$46:$H$54,0),3)), IFERROR( INDEX( tblStrings[], MATCH( 1, (tblStrings[[Cell]:[Cell]]=AllStrings!$D$350) * (tblStrings[[Sheet]:[Sheet]]=AllStrings!$C$433), 0 ), MATCH(Språkval, tblStrings[#Headers], 0) ), ))} -> Fyll i byggnads- och rumstyp ovan | L80: {=IFERROR(_xlfn.IFS(L$19='4. Reduktionsfaktorer, LENI-tal'!$Q$12,INDEX('4. Reduktionsfaktorer, LENI-tal'!$H$13:$O$23,MATCH(L$21,'4. Reduktionsfaktorer, LENI-tal'!$H$13:$H$23,0),3), L$19='4. Reduktionsfaktorer, LENI-tal'!$R$12,INDEX('4. Reduktionsfaktorer, LENI-tal'!$H$24:$O$32,MATCH(L$21,'4. Reduktionsfaktorer, LENI-tal'!$H$24:$H$32,0),3), L$19='4. Reduktionsfaktorer, LENI-tal'!$S$12,INDEX('4. Reduktionsfaktorer, LENI-tal'!$H$33:$O$37,MATCH(L$21,'4. Reduktionsfaktorer, LENI-tal'!$H$33:$H$37,0),3), L$19='4. Reduktionsfaktorer, LENI-tal'!$T$12,INDEX('4. Reduktionsfaktorer, LENI-tal'!$H$38:$O$45,MATCH(L$21,'4. Reduktionsfaktorer, LENI-tal'!$H$38:$H$45,0),3), L$19='4. Reduktionsfaktorer, LENI-tal'!$U$12,INDEX('4. Reduktionsfaktorer, LENI-tal'!$H$46:$O$54,MATCH(L$21,'4. Reduktionsfaktorer, LENI-tal'!$H$46:$H$54,0),3)), IFERROR( INDEX( tblStrings[], MATCH( 1, (tblStrings[[Cell]:[Cell]]=AllStrings!$D$350) * (tblStrings[[Sheet]:[Sheet]]=AllStrings!$C$433), 0 ), MATCH(Språkval, tblStrings[#Headers], 0) ), ))} -> Fyll i byggnads- och rumstyp ovan | M80: {=IFERROR(_xlfn.IFS(M$19='4. Reduktionsfaktorer, LENI-tal'!$Q$12,INDEX('4. Reduktionsfaktorer, LENI-tal'!$H$13:$O$23,MATCH(M$21,'4. Reduktionsfaktorer, LENI-tal'!$H$13:$H$23,0),3), M$19='4. Reduktionsfaktorer, LENI-tal'!$R$12,INDEX('4. Reduktionsfaktorer, LENI-tal'!$H$24:$O$32,MATCH(M$21,'4. Reduktionsfaktorer, LENI-tal'!$H$24:$H$32,0),3), M$19='4. Reduktionsfaktorer, LENI-tal'!$S$12,INDEX('4. Reduktionsfaktorer, LENI-tal'!$H$33:$O$37,MATCH(M$21,'4. Reduktionsfaktorer, LENI-tal'!$H$33:$H$37,0),3), M$19='4. Reduktionsfaktorer, LENI-tal'!$T$12,INDEX('4. Reduktionsfaktorer, LENI-tal'!$H$38:$O$45,MATCH(M$21,'4. Reduktionsfaktorer, LENI-tal'!$H$38:$H$45,0),3), M$19='4. Reduktionsfaktorer, LENI-tal'!$U$12,INDEX('4. Reduktionsfaktorer, LENI-tal'!$H$46:$O$54,MATCH(M$21,'4. Reduktionsfaktorer, LENI-tal'!$H$46:$H$54,0),3)), IFERROR( INDEX( tblStrings[], MATCH( 1, (tblStrings[[Cell]:[Cell]]=AllStrings!$D$350) * (tblStrings[[Sheet]:[Sheet]]=AllStrings!$C$433), 0 ), MATCH(Språkval, tblStrings[#Headers], 0) ), ))} -> Fyll i byggnads- och rumstyp ovan | N80: {=IFERROR(_xlfn.IFS(N$19='4. Reduktionsfaktorer, LENI-tal'!$Q$12,INDEX('4. Reduktionsfaktorer, LENI-tal'!$H$13:$O$23,MATCH(N$21,'4. Reduktionsfaktorer, LENI-tal'!$H$13:$H$23,0),3), N$19='4. Reduktionsfaktorer, LENI-tal'!$R$12,INDEX('4. Reduktionsfaktorer, LENI-tal'!$H$24:$O$32,MATCH(N$21,'4. Reduktionsfaktorer, LENI-tal'!$H$24:$H$32,0),3), N$19='4. Reduktionsfaktorer, LENI-tal'!$S$12,INDEX('4. Reduktionsfaktorer, LENI-tal'!$H$33:$O$37,MATCH(N$21,'4. Reduktionsfaktorer, LENI-tal'!$H$33:$H$37,0),3), N$19='4. Reduktionsfaktorer, LENI-tal'!$T$12,INDEX('4. Reduktionsfaktorer, LENI-tal'!$H$38:$O$45,MATCH(N$21,'4. Reduktionsfaktorer, LENI-tal'!$H$38:$H$45,0),3), N$19='4. Reduktionsfaktorer, LENI-tal'!$U$12,INDEX('4. Reduktionsfaktorer, LENI-tal'!$H$46:$O$54,MATCH(N$21,'4. Reduktionsfaktorer, LENI-tal'!$H$46:$H$54,0),3)), IFERROR( INDEX( tblStrings[], MATCH( 1, (tblStrings[[Cell]:[Cell]]=AllStrings!$D$350) * (tblStrings[[Sheet]:[Sheet]]=AllStrings!$C$433), 0 ), MATCH(Språkval, tblStrings[#Headers], 0) ), ))} -> Fyll i byggnads- och rumstyp ovan | O80: {=IFERROR(_xlfn.IFS(O$19='4. Reduktionsfaktorer, LENI-tal'!$Q$12,INDEX('4. Reduktionsfaktorer, LENI-tal'!$H$13:$O$23,MATCH(O$21,'4. Reduktionsfaktorer, LENI-tal'!$H$13:$H$23,0),3), O$19='4. Reduktionsfaktorer, LENI-tal'!$R$12,INDEX('4. Reduktionsfaktorer, LENI-tal'!$H$24:$O$32,MATCH(O$21,'4. Reduktionsfaktorer, LENI-tal'!$H$24:$H$32,0),3), O$19='4. Reduktionsfaktorer, LENI-tal'!$S$12,INDEX('4. Reduktionsfaktorer, LENI-tal'!$H$33:$O$37,MATCH(O$21,'4. Reduktionsfaktorer, LENI-tal'!$H$33:$H$37,0),3), O$19='4. Reduktionsfaktorer, LENI-tal'!$T$12,INDEX('4. Reduktionsfaktorer, LENI-tal'!$H$38:$O$45,MATCH(O$21,'4. Reduktionsfaktorer, LENI-tal'!$H$38:$H$45,0),3), O$19='4. Reduktionsfaktorer, LENI-tal'!$U$12,INDEX('4. Reduktionsfaktorer, LENI-tal'!$H$46:$O$54,MATCH(O$21,'4. Reduktionsfaktorer, LENI-tal'!$H$46:$H$54,0),3)), IFERROR( INDEX( tblStrings[], MATCH( 1, (tblStrings[[Cell]:[Cell]]=AllStrings!$D$350) * (tblStrings[[Sheet]:[Sheet]]=AllStrings!$C$433), 0 ), MATCH(Språkval, tblStrings[#Headers], 0) ), ))} -> Fyll i byggnads- och rumstyp ovan | P80: {=IFERROR(_xlfn.IFS(P$19='4. Reduktionsfaktorer, LENI-tal'!$Q$12,INDEX('4. Reduktionsfaktorer, LENI-tal'!$H$13:$O$23,MATCH(P$21,'4. Reduktionsfaktorer, LENI-tal'!$H$13:$H$23,0),3), P$19='4. Reduktionsfaktorer, LENI-tal'!$R$12,INDEX('4. Reduktionsfaktorer, LENI-tal'!$H$24:$O$32,MATCH(P$21,'4. Reduktionsfaktorer, LENI-tal'!$H$24:$H$32,0),3), P$19='4. Reduktionsfaktorer, LENI-tal'!$S$12,INDEX('4. Reduktionsfaktorer, LENI-tal'!$H$33:$O$37,MATCH(P$21,'4. Reduktionsfaktorer, LENI-tal'!$H$33:$H$37,0),3), P$19='4. Reduktionsfaktorer, LENI-tal'!$T$12,INDEX('4. Reduktionsfaktorer, LENI-tal'!$H$38:$O$45,MATCH(P$21,'4. Reduktionsfaktorer, LENI-tal'!$H$38:$H$45,0),3), P$19='4. Reduktionsfaktorer, LENI-tal'!$U$12,INDEX('4. Reduktionsfaktorer, LENI-tal'!$H$46:$O$54,MATCH(P$21,'4. Reduktionsfaktorer, LENI-tal'!$H$46:$H$54,0),3)), IFERROR( INDEX( tblStrings[], MATCH( 1, (tblStrings[[Cell]:[Cell]]=AllStrings!$D$350) * (tblStrings[[Sheet]:[Sheet]]=AllStrings!$C$433), 0 ), MATCH(Språkval, tblStrings[#Headers], 0) ), ))} -> Fyll i byggnads- och rumstyp ovan | ... R80: {=IFERROR(_xlfn.IFS(R$19='4. Reduktionsfaktorer, LENI-tal'!$Q$12,INDEX('4. Reduktionsfaktorer, LENI-tal'!$H$13:$O$23,MATCH(R$21,'4. Reduktionsfaktorer, LENI-tal'!$H$13:$H$23,0),3), R$19='4. Reduktionsfaktorer, LENI-tal'!$R$12,INDEX('4. Reduktionsfaktorer, LENI-tal'!$H$24:$O$32,MATCH(R$21,'4. Reduktionsfaktorer, LENI-tal'!$H$24:$H$32,0),3), R$19='4. Reduktionsfaktorer, LENI-tal'!$S$12,INDEX('4. Reduktionsfaktorer, LENI-tal'!$H$33:$O$37,MATCH(R$21,'4. Reduktionsfaktorer, LENI-tal'!$H$33:$H$37,0),3), R$19='4. Reduktionsfaktorer, LENI-tal'!$T$12,INDEX('4. Reduktionsfaktorer, LENI-tal'!$H$38:$O$45,MATCH(R$21,'4. Reduktionsfaktorer, LENI-tal'!$H$38:$H$45,0),3), R$19='4. Reduktionsfaktorer, LENI-tal'!$U$12,INDEX('4. Reduktionsfaktorer, LENI-tal'!$H$46:$O$54,MATCH(R$21,'4. Reduktionsfaktorer, LENI-tal'!$H$46:$H$54,0),3)), IFERROR( INDEX( tblStrings[], MATCH( 1, (tblStrings[[Cell]:[Cell]]=AllStrings!$D$350) * (tblStrings[[Sheet]:[Sheet]]=AllStrings!$C$433), 0 ), MATCH(Språkval, tblStrings[#Headers], 0) ), ))} -> Fyll i byggnads- och rumstyp ovan
B81: 2.7 | C81: =$C69 -> Reduktionsfaktor närvaro-/frånvarostyrning | I81: {=IFERROR(_xlfn.IFS(I$19='4. Reduktionsfaktorer, LENI-tal'!$Q$12,INDEX('4. Reduktionsfaktorer, LENI-tal'!$H$13:$O$23,MATCH(I$21,'4. Reduktionsfaktorer, LENI-tal'!$H$13:$H$23,0),4), I$19='4. Reduktionsfaktorer, LENI-tal'!$R$12,INDEX('4. Reduktionsfaktorer, LENI-tal'!$H$24:$O$32,MATCH(I$21,'4. Reduktionsfaktorer, LENI-tal'!$H$24:$H$32,0),4), I$19='4. Reduktionsfaktorer, LENI-tal'!$S$12,INDEX('4. Reduktionsfaktorer, LENI-tal'!$H$33:$O$37,MATCH(I$21,'4. Reduktionsfaktorer, LENI-tal'!$H$33:$H$37,0),4), I$19='4. Reduktionsfaktorer, LENI-tal'!$T$12,INDEX('4. Reduktionsfaktorer, LENI-tal'!$H$38:$O$45,MATCH(I$21,'4. Reduktionsfaktorer, LENI-tal'!$H$38:$H$45,0),4), I$19='4. Reduktionsfaktorer, LENI-tal'!$U$12,INDEX('4. Reduktionsfaktorer, LENI-tal'!$H$46:$O$54,MATCH(I$21,'4. Reduktionsfaktorer, LENI-tal'!$H$46:$H$54,0),4)), IFERROR( INDEX( tblStrings[], MATCH( 1, (tblStrings[[Cell]:[Cell]]=AllStrings!$D$350) * (tblStrings[[Sheet]:[Sheet]]=AllStrings!$C$433), 0 ), MATCH(Språkval, tblStrings[#Headers], 0) ), ))} -> Fyll i byggnads- och rumstyp ovan | J81: {=IFERROR(_xlfn.IFS(J$19='4. Reduktionsfaktorer, LENI-tal'!$Q$12,INDEX('4. Reduktionsfaktorer, LENI-tal'!$H$13:$O$23,MATCH(J$21,'4. Reduktionsfaktorer, LENI-tal'!$H$13:$H$23,0),4), J$19='4. Reduktionsfaktorer, LENI-tal'!$R$12,INDEX('4. Reduktionsfaktorer, LENI-tal'!$H$24:$O$32,MATCH(J$21,'4. Reduktionsfaktorer, LENI-tal'!$H$24:$H$32,0),4), J$19='4. Reduktionsfaktorer, LENI-tal'!$S$12,INDEX('4. Reduktionsfaktorer, LENI-tal'!$H$33:$O$37,MATCH(J$21,'4. Reduktionsfaktorer, LENI-tal'!$H$33:$H$37,0),4), J$19='4. Reduktionsfaktorer, LENI-tal'!$T$12,INDEX('4. Reduktionsfaktorer, LENI-tal'!$H$38:$O$45,MATCH(J$21,'4. Reduktionsfaktorer, LENI-tal'!$H$38:$H$45,0),4), J$19='4. Reduktionsfaktorer, LENI-tal'!$U$12,INDEX('4. Reduktionsfaktorer, LENI-tal'!$H$46:$O$54,MATCH(J$21,'4. Reduktionsfaktorer, LENI-tal'!$H$46:$H$54,0),4)), IFERROR( INDEX( tblStrings[], MATCH( 1, (tblStrings[[Cell]:[Cell]]=AllStrings!$D$350) * (tblStrings[[Sheet]:[Sheet]]=AllStrings!$C$433), 0 ), MATCH(Språkval, tblStrings[#Headers], 0) ), ))} -> Fyll i byggnads- och rumstyp ovan | K81: {=IFERROR(_xlfn.IFS(K$19='4. Reduktionsfaktorer, LENI-tal'!$Q$12,INDEX('4. Reduktionsfaktorer, LENI-tal'!$H$13:$O$23,MATCH(K$21,'4. Reduktionsfaktorer, LENI-tal'!$H$13:$H$23,0),4), K$19='4. Reduktionsfaktorer, LENI-tal'!$R$12,INDEX('4. Reduktionsfaktorer, LENI-tal'!$H$24:$O$32,MATCH(K$21,'4. Reduktionsfaktorer, LENI-tal'!$H$24:$H$32,0),4), K$19='4. Reduktionsfaktorer, LENI-tal'!$S$12,INDEX('4. Reduktionsfaktorer, LENI-tal'!$H$33:$O$37,MATCH(K$21,'4. Reduktionsfaktorer, LENI-tal'!$H$33:$H$37,0),4), K$19='4. Reduktionsfaktorer, LENI-tal'!$T$12,INDEX('4. Reduktionsfaktorer, LENI-tal'!$H$38:$O$45,MATCH(K$21,'4. Reduktionsfaktorer, LENI-tal'!$H$38:$H$45,0),4), K$19='4. Reduktionsfaktorer, LENI-tal'!$U$12,INDEX('4. Reduktionsfaktorer, LENI-tal'!$H$46:$O$54,MATCH(K$21,'4. Reduktionsfaktorer, LENI-tal'!$H$46:$H$54,0),4)), IFERROR( INDEX( tblStrings[], MATCH( 1, (tblStrings[[Cell]:[Cell]]=AllStrings!$D$350) * (tblStrings[[Sheet]:[Sheet]]=AllStrings!$C$433), 0 ), MATCH(Språkval, tblStrings[#Headers], 0) ), ))} -> Fyll i byggnads- och rumstyp ovan | L81: {=IFERROR(_xlfn.IFS(L$19='4. Reduktionsfaktorer, LENI-tal'!$Q$12,INDEX('4. Reduktionsfaktorer, LENI-tal'!$H$13:$O$23,MATCH(L$21,'4. Reduktionsfaktorer, LENI-tal'!$H$13:$H$23,0),4), L$19='4. Reduktionsfaktorer, LENI-tal'!$R$12,INDEX('4. Reduktionsfaktorer, LENI-tal'!$H$24:$O$32,MATCH(L$21,'4. Reduktionsfaktorer, LENI-tal'!$H$24:$H$32,0),4), L$19='4. Reduktionsfaktorer, LENI-tal'!$S$12,INDEX('4. Reduktionsfaktorer, LENI-tal'!$H$33:$O$37,MATCH(L$21,'4. Reduktionsfaktorer, LENI-tal'!$H$33:$H$37,0),4), L$19='4. Reduktionsfaktorer, LENI-tal'!$T$12,INDEX('4. Reduktionsfaktorer, LENI-tal'!$H$38:$O$45,MATCH(L$21,'4. Reduktionsfaktorer, LENI-tal'!$H$38:$H$45,0),4), L$19='4. Reduktionsfaktorer, LENI-tal'!$U$12,INDEX('4. Reduktionsfaktorer, LENI-tal'!$H$46:$O$54,MATCH(L$21,'4. Reduktionsfaktorer, LENI-tal'!$H$46:$H$54,0),4)), IFERROR( INDEX( tblStrings[], MATCH( 1, (tblStrings[[Cell]:[Cell]]=AllStrings!$D$350) * (tblStrings[[Sheet]:[Sheet]]=AllStrings!$C$433), 0 ), MATCH(Språkval, tblStrings[#Headers], 0) ), ))} -> Fyll i byggnads- och rumstyp ovan | M81: {=IFERROR(_xlfn.IFS(M$19='4. Reduktionsfaktorer, LENI-tal'!$Q$12,INDEX('4. Reduktionsfaktorer, LENI-tal'!$H$13:$O$23,MATCH(M$21,'4. Reduktionsfaktorer, LENI-tal'!$H$13:$H$23,0),4), M$19='4. Reduktionsfaktorer, LENI-tal'!$R$12,INDEX('4. Reduktionsfaktorer, LENI-tal'!$H$24:$O$32,MATCH(M$21,'4. Reduktionsfaktorer, LENI-tal'!$H$24:$H$32,0),4), M$19='4. Reduktionsfaktorer, LENI-tal'!$S$12,INDEX('4. Reduktionsfaktorer, LENI-tal'!$H$33:$O$37,MATCH(M$21,'4. Reduktionsfaktorer, LENI-tal'!$H$33:$H$37,0),4), M$19='4. Reduktionsfaktorer, LENI-tal'!$T$12,INDEX('4. Reduktionsfaktorer, LENI-tal'!$H$38:$O$45,MATCH(M$21,'4. Reduktionsfaktorer, LENI-tal'!$H$38:$H$45,0),4), M$19='4. Reduktionsfaktorer, LENI-tal'!$U$12,INDEX('4. Reduktionsfaktorer, LENI-tal'!$H$46:$O$54,MATCH(M$21,'4. Reduktionsfaktorer, LENI-tal'!$H$46:$H$54,0),4)), IFERROR( INDEX( tblStrings[], MATCH( 1, (tblStrings[[Cell]:[Cell]]=AllStrings!$D$350) * (tblStrings[[Sheet]:[Sheet]]=AllStrings!$C$433), 0 ), MATCH(Språkval, tblStrings[#Headers], 0) ), ))} -> Fyll i byggnads- och rumstyp ovan | N81: {=IFERROR(_xlfn.IFS(N$19='4. Reduktionsfaktorer, LENI-tal'!$Q$12,INDEX('4. Reduktionsfaktorer, LENI-tal'!$H$13:$O$23,MATCH(N$21,'4. Reduktionsfaktorer, LENI-tal'!$H$13:$H$23,0),4), N$19='4. Reduktionsfaktorer, LENI-tal'!$R$12,INDEX('4. Reduktionsfaktorer, LENI-tal'!$H$24:$O$32,MATCH(N$21,'4. Reduktionsfaktorer, LENI-tal'!$H$24:$H$32,0),4), N$19='4. Reduktionsfaktorer, LENI-tal'!$S$12,INDEX('4. Reduktionsfaktorer, LENI-tal'!$H$33:$O$37,MATCH(N$21,'4. Reduktionsfaktorer, LENI-tal'!$H$33:$H$37,0),4), N$19='4. Reduktionsfaktorer, LENI-tal'!$T$12,INDEX('4. Reduktionsfaktorer, LENI-tal'!$H$38:$O$45,MATCH(N$21,'4. Reduktionsfaktorer, LENI-tal'!$H$38:$H$45,0),4), N$19='4. Reduktionsfaktorer, LENI-tal'!$U$12,INDEX('4. Reduktionsfaktorer, LENI-tal'!$H$46:$O$54,MATCH(N$21,'4. Reduktionsfaktorer, LENI-tal'!$H$46:$H$54,0),4)), IFERROR( INDEX( tblStrings[], MATCH( 1, (tblStrings[[Cell]:[Cell]]=AllStrings!$D$350) * (tblStrings[[Sheet]:[Sheet]]=AllStrings!$C$433), 0 ), MATCH(Språkval, tblStrings[#Headers], 0) ), ))} -> Fyll i byggnads- och rumstyp ovan | O81: {=IFERROR(_xlfn.IFS(O$19='4. Reduktionsfaktorer, LENI-tal'!$Q$12,INDEX('4. Reduktionsfaktorer, LENI-tal'!$H$13:$O$23,MATCH(O$21,'4. Reduktionsfaktorer, LENI-tal'!$H$13:$H$23,0),4), O$19='4. Reduktionsfaktorer, LENI-tal'!$R$12,INDEX('4. Reduktionsfaktorer, LENI-tal'!$H$24:$O$32,MATCH(O$21,'4. Reduktionsfaktorer, LENI-tal'!$H$24:$H$32,0),4), O$19='4. Reduktionsfaktorer, LENI-tal'!$S$12,INDEX('4. Reduktionsfaktorer, LENI-tal'!$H$33:$O$37,MATCH(O$21,'4. Reduktionsfaktorer, LENI-tal'!$H$33:$H$37,0),4), O$19='4. Reduktionsfaktorer, LENI-tal'!$T$12,INDEX('4. Reduktionsfaktorer, LENI-tal'!$H$38:$O$45,MATCH(O$21,'4. Reduktionsfaktorer, LENI-tal'!$H$38:$H$45,0),4), O$19='4. Reduktionsfaktorer, LENI-tal'!$U$12,INDEX('4. Reduktionsfaktorer, LENI-tal'!$H$46:$O$54,MATCH(O$21,'4. Reduktionsfaktorer, LENI-tal'!$H$46:$H$54,0),4)), IFERROR( INDEX( tblStrings[], MATCH( 1, (tblStrings[[Cell]:[Cell]]=AllStrings!$D$350) * (tblStrings[[Sheet]:[Sheet]]=AllStrings!$C$433), 0 ), MATCH(Språkval, tblStrings[#Headers], 0) ), ))} -> Fyll i byggnads- och rumstyp ovan | P81: {=IFERROR(_xlfn.IFS(P$19='4. Reduktionsfaktorer, LENI-tal'!$Q$12,INDEX('4. Reduktionsfaktorer, LENI-tal'!$H$13:$O$23,MATCH(P$21,'4. Reduktionsfaktorer, LENI-tal'!$H$13:$H$23,0),4), P$19='4. Reduktionsfaktorer, LENI-tal'!$R$12,INDEX('4. Reduktionsfaktorer, LENI-tal'!$H$24:$O$32,MATCH(P$21,'4. Reduktionsfaktorer, LENI-tal'!$H$24:$H$32,0),4), P$19='4. Reduktionsfaktorer, LENI-tal'!$S$12,INDEX('4. Reduktionsfaktorer, LENI-tal'!$H$33:$O$37,MATCH(P$21,'4. Reduktionsfaktorer, LENI-tal'!$H$33:$H$37,0),4), P$19='4. Reduktionsfaktorer, LENI-tal'!$T$12,INDEX('4. Reduktionsfaktorer, LENI-tal'!$H$38:$O$45,MATCH(P$21,'4. Reduktionsfaktorer, LENI-tal'!$H$38:$H$45,0),4), P$19='4. Reduktionsfaktorer, LENI-tal'!$U$12,INDEX('4. Reduktionsfaktorer, LENI-tal'!$H$46:$O$54,MATCH(P$21,'4. Reduktionsfaktorer, LENI-tal'!$H$46:$H$54,0),4)), IFERROR( INDEX( tblStrings[], MATCH( 1, (tblStrings[[Cell]:[Cell]]=AllStrings!$D$350) * (tblStrings[[Sheet]:[Sheet]]=AllStrings!$C$433), 0 ), MATCH(Språkval, tblStrings[#Headers], 0) ), ))} -> Fyll i byggnads- och rumstyp ovan | ... R81: {=IFERROR(_xlfn.IFS(R$19='4. Reduktionsfaktorer, LENI-tal'!$Q$12,INDEX('4. Reduktionsfaktorer, LENI-tal'!$H$13:$O$23,MATCH(R$21,'4. Reduktionsfaktorer, LENI-tal'!$H$13:$H$23,0),4), R$19='4. Reduktionsfaktorer, LENI-tal'!$R$12,INDEX('4. Reduktionsfaktorer, LENI-tal'!$H$24:$O$32,MATCH(R$21,'4. Reduktionsfaktorer, LENI-tal'!$H$24:$H$32,0),4), R$19='4. Reduktionsfaktorer, LENI-tal'!$S$12,INDEX('4. Reduktionsfaktorer, LENI-tal'!$H$33:$O$37,MATCH(R$21,'4. Reduktionsfaktorer, LENI-tal'!$H$33:$H$37,0),4), R$19='4. Reduktionsfaktorer, LENI-tal'!$T$12,INDEX('4. Reduktionsfaktorer, LENI-tal'!$H$38:$O$45,MATCH(R$21,'4. Reduktionsfaktorer, LENI-tal'!$H$38:$H$45,0),4), R$19='4. Reduktionsfaktorer, LENI-tal'!$U$12,INDEX('4. Reduktionsfaktorer, LENI-tal'!$H$46:$O$54,MATCH(R$21,'4. Reduktionsfaktorer, LENI-tal'!$H$46:$H$54,0),4)), IFERROR( INDEX( tblStrings[], MATCH( 1, (tblStrings[[Cell]:[Cell]]=AllStrings!$D$350) * (tblStrings[[Sheet]:[Sheet]]=AllStrings!$C$433), 0 ), MATCH(Språkval, tblStrings[#Headers], 0) ), ))} -> Fyll i byggnads- och rumstyp ovan
B82: 2.8 | C82: =$C70 -> Reduktionsfaktor dagsljusstyrning | I82: {=IFERROR(_xlfn.IFS(I$19='4. Reduktionsfaktorer, LENI-tal'!$Q$12,INDEX('4. Reduktionsfaktorer, LENI-tal'!$H$13:$O$23,MATCH(I$21,'4. Reduktionsfaktorer, LENI-tal'!$H$13:$H$23,0),5), I$19='4. Reduktionsfaktorer, LENI-tal'!$R$12,INDEX('4. Reduktionsfaktorer, LENI-tal'!$H$24:$O$32,MATCH(I$21,'4. Reduktionsfaktorer, LENI-tal'!$H$24:$H$32,0),5), I$19='4. Reduktionsfaktorer, LENI-tal'!$S$12,INDEX('4. Reduktionsfaktorer, LENI-tal'!$H$33:$O$37,MATCH(I$21,'4. Reduktionsfaktorer, LENI-tal'!$H$33:$H$37,0),5), I$19='4. Reduktionsfaktorer, LENI-tal'!$T$12,INDEX('4. Reduktionsfaktorer, LENI-tal'!$H$38:$O$45,MATCH(I$21,'4. Reduktionsfaktorer, LENI-tal'!$H$38:$H$45,0),5), I$19='4. Reduktionsfaktorer, LENI-tal'!$U$12,INDEX('4. Reduktionsfaktorer, LENI-tal'!$H$46:$O$54,MATCH(I$21,'4. Reduktionsfaktorer, LENI-tal'!$H$46:$H$54,0),5)), IFERROR( INDEX( tblStrings[], MATCH( 1, (tblStrings[[Cell]:[Cell]]=AllStrings!$D$350) * (tblStrings[[Sheet]:[Sheet]]=AllStrings!$C$433), 0 ), MATCH(Språkval, tblStrings[#Headers], 0) ), ))} -> Fyll i byggnads- och rumstyp ovan | J82: {=IFERROR(_xlfn.IFS(J$19='4. Reduktionsfaktorer, LENI-tal'!$Q$12,INDEX('4. Reduktionsfaktorer, LENI-tal'!$H$13:$O$23,MATCH(J$21,'4. Reduktionsfaktorer, LENI-tal'!$H$13:$H$23,0),5), J$19='4. Reduktionsfaktorer, LENI-tal'!$R$12,INDEX('4. Reduktionsfaktorer, LENI-tal'!$H$24:$O$32,MATCH(J$21,'4. Reduktionsfaktorer, LENI-tal'!$H$24:$H$32,0),5), J$19='4. Reduktionsfaktorer, LENI-tal'!$S$12,INDEX('4. Reduktionsfaktorer, LENI-tal'!$H$33:$O$37,MATCH(J$21,'4. Reduktionsfaktorer, LENI-tal'!$H$33:$H$37,0),5), J$19='4. Reduktionsfaktorer, LENI-tal'!$T$12,INDEX('4. Reduktionsfaktorer, LENI-tal'!$H$38:$O$45,MATCH(J$21,'4. Reduktionsfaktorer, LENI-tal'!$H$38:$H$45,0),5), J$19='4. Reduktionsfaktorer, LENI-tal'!$U$12,INDEX('4. Reduktionsfaktorer, LENI-tal'!$H$46:$O$54,MATCH(J$21,'4. Reduktionsfaktorer, LENI-tal'!$H$46:$H$54,0),5)), IFERROR( INDEX( tblStrings[], MATCH( 1, (tblStrings[[Cell]:[Cell]]=AllStrings!$D$350) * (tblStrings[[Sheet]:[Sheet]]=AllStrings!$C$433), 0 ), MATCH(Språkval, tblStrings[#Headers], 0) ), ))} -> Fyll i byggnads- och rumstyp ovan | K82: {=IFERROR(_xlfn.IFS(K$19='4. Reduktionsfaktorer, LENI-tal'!$Q$12,INDEX('4. Reduktionsfaktorer, LENI-tal'!$H$13:$O$23,MATCH(K$21,'4. Reduktionsfaktorer, LENI-tal'!$H$13:$H$23,0),5), K$19='4. Reduktionsfaktorer, LENI-tal'!$R$12,INDEX('4. Reduktionsfaktorer, LENI-tal'!$H$24:$O$32,MATCH(K$21,'4. Reduktionsfaktorer, LENI-tal'!$H$24:$H$32,0),5), K$19='4. Reduktionsfaktorer, LENI-tal'!$S$12,INDEX('4. Reduktionsfaktorer, LENI-tal'!$H$33:$O$37,MATCH(K$21,'4. Reduktionsfaktorer, LENI-tal'!$H$33:$H$37,0),5), K$19='4. Reduktionsfaktorer, LENI-tal'!$T$12,INDEX('4. Reduktionsfaktorer, LENI-tal'!$H$38:$O$45,MATCH(K$21,'4. Reduktionsfaktorer, LENI-tal'!$H$38:$H$45,0),5), K$19='4. Reduktionsfaktorer, LENI-tal'!$U$12,INDEX('4. Reduktionsfaktorer, LENI-tal'!$H$46:$O$54,MATCH(K$21,'4. Reduktionsfaktorer, LENI-tal'!$H$46:$H$54,0),5)), IFERROR( INDEX( tblStrings[], MATCH( 1, (tblStrings[[Cell]:[Cell]]=AllStrings!$D$350) * (tblStrings[[Sheet]:[Sheet]]=AllStrings!$C$433), 0 ), MATCH(Språkval, tblStrings[#Headers], 0) ), ))} -> Fyll i byggnads- och rumstyp ovan | L82: {=IFERROR(_xlfn.IFS(L$19='4. Reduktionsfaktorer, LENI-tal'!$Q$12,INDEX('4. Reduktionsfaktorer, LENI-tal'!$H$13:$O$23,MATCH(L$21,'4. Reduktionsfaktorer, LENI-tal'!$H$13:$H$23,0),5), L$19='4. Reduktionsfaktorer, LENI-tal'!$R$12,INDEX('4. Reduktionsfaktorer, LENI-tal'!$H$24:$O$32,MATCH(L$21,'4. Reduktionsfaktorer, LENI-tal'!$H$24:$H$32,0),5), L$19='4. Reduktionsfaktorer, LENI-tal'!$S$12,INDEX('4. Reduktionsfaktorer, LENI-tal'!$H$33:$O$37,MATCH(L$21,'4. Reduktionsfaktorer, LENI-tal'!$H$33:$H$37,0),5), L$19='4. Reduktionsfaktorer, LENI-tal'!$T$12,INDEX('4. Reduktionsfaktorer, LENI-tal'!$H$38:$O$45,MATCH(L$21,'4. Reduktionsfaktorer, LENI-tal'!$H$38:$H$45,0),5), L$19='4. Reduktionsfaktorer, LENI-tal'!$U$12,INDEX('4. Reduktionsfaktorer, LENI-tal'!$H$46:$O$54,MATCH(L$21,'4. Reduktionsfaktorer, LENI-tal'!$H$46:$H$54,0),5)), IFERROR( INDEX( tblStrings[], MATCH( 1, (tblStrings[[Cell]:[Cell]]=AllStrings!$D$350) * (tblStrings[[Sheet]:[Sheet]]=AllStrings!$C$433), 0 ), MATCH(Språkval, tblStrings[#Headers], 0) ), ))} -> Fyll i byggnads- och rumstyp ovan | M82: {=IFERROR(_xlfn.IFS(M$19='4. Reduktionsfaktorer, LENI-tal'!$Q$12,INDEX('4. Reduktionsfaktorer, LENI-tal'!$H$13:$O$23,MATCH(M$21,'4. Reduktionsfaktorer, LENI-tal'!$H$13:$H$23,0),5), M$19='4. Reduktionsfaktorer, LENI-tal'!$R$12,INDEX('4. Reduktionsfaktorer, LENI-tal'!$H$24:$O$32,MATCH(M$21,'4. Reduktionsfaktorer, LENI-tal'!$H$24:$H$32,0),5), M$19='4. Reduktionsfaktorer, LENI-tal'!$S$12,INDEX('4. Reduktionsfaktorer, LENI-tal'!$H$33:$O$37,MATCH(M$21,'4. Reduktionsfaktorer, LENI-tal'!$H$33:$H$37,0),5), M$19='4. Reduktionsfaktorer, LENI-tal'!$T$12,INDEX('4. Reduktionsfaktorer, LENI-tal'!$H$38:$O$45,MATCH(M$21,'4. Reduktionsfaktorer, LENI-tal'!$H$38:$H$45,0),5), M$19='4. Reduktionsfaktorer, LENI-tal'!$U$12,INDEX('4. Reduktionsfaktorer, LENI-tal'!$H$46:$O$54,MATCH(M$21,'4. Reduktionsfaktorer, LENI-tal'!$H$46:$H$54,0),5)), IFERROR( INDEX( tblStrings[], MATCH( 1, (tblStrings[[Cell]:[Cell]]=AllStrings!$D$350) * (tblStrings[[Sheet]:[Sheet]]=AllStrings!$C$433), 0 ), MATCH(Språkval, tblStrings[#Headers], 0) ), ))} -> Fyll i byggnads- och rumstyp ovan | N82: {=IFERROR(_xlfn.IFS(N$19='4. Reduktionsfaktorer, LENI-tal'!$Q$12,INDEX('4. Reduktionsfaktorer, LENI-tal'!$H$13:$O$23,MATCH(N$21,'4. Reduktionsfaktorer, LENI-tal'!$H$13:$H$23,0),5), N$19='4. Reduktionsfaktorer, LENI-tal'!$R$12,INDEX('4. Reduktionsfaktorer, LENI-tal'!$H$24:$O$32,MATCH(N$21,'4. Reduktionsfaktorer, LENI-tal'!$H$24:$H$32,0),5), N$19='4. Reduktionsfaktorer, LENI-tal'!$S$12,INDEX('4. Reduktionsfaktorer, LENI-tal'!$H$33:$O$37,MATCH(N$21,'4. Reduktionsfaktorer, LENI-tal'!$H$33:$H$37,0),5), N$19='4. Reduktionsfaktorer, LENI-tal'!$T$12,INDEX('4. Reduktionsfaktorer, LENI-tal'!$H$38:$O$45,MATCH(N$21,'4. Reduktionsfaktorer, LENI-tal'!$H$38:$H$45,0),5), N$19='4. Reduktionsfaktorer, LENI-tal'!$U$12,INDEX('4. Reduktionsfaktorer, LENI-tal'!$H$46:$O$54,MATCH(N$21,'4. Reduktionsfaktorer, LENI-tal'!$H$46:$H$54,0),5)), IFERROR( INDEX( tblStrings[], MATCH( 1, (tblStrings[[Cell]:[Cell]]=AllStrings!$D$350) * (tblStrings[[Sheet]:[Sheet]]=AllStrings!$C$433), 0 ), MATCH(Språkval, tblStrings[#Headers], 0) ), ))} -> Fyll i byggnads- och rumstyp ovan | O82: {=IFERROR(_xlfn.IFS(O$19='4. Reduktionsfaktorer, LENI-tal'!$Q$12,INDEX('4. Reduktionsfaktorer, LENI-tal'!$H$13:$O$23,MATCH(O$21,'4. Reduktionsfaktorer, LENI-tal'!$H$13:$H$23,0),5), O$19='4. Reduktionsfaktorer, LENI-tal'!$R$12,INDEX('4. Reduktionsfaktorer, LENI-tal'!$H$24:$O$32,MATCH(O$21,'4. Reduktionsfaktorer, LENI-tal'!$H$24:$H$32,0),5), O$19='4. Reduktionsfaktorer, LENI-tal'!$S$12,INDEX('4. Reduktionsfaktorer, LENI-tal'!$H$33:$O$37,MATCH(O$21,'4. Reduktionsfaktorer, LENI-tal'!$H$33:$H$37,0),5), O$19='4. Reduktionsfaktorer, LENI-tal'!$T$12,INDEX('4. Reduktionsfaktorer, LENI-tal'!$H$38:$O$45,MATCH(O$21,'4. Reduktionsfaktorer, LENI-tal'!$H$38:$H$45,0),5), O$19='4. Reduktionsfaktorer, LENI-tal'!$U$12,INDEX('4. Reduktionsfaktorer, LENI-tal'!$H$46:$O$54,MATCH(O$21,'4. Reduktionsfaktorer, LENI-tal'!$H$46:$H$54,0),5)), IFERROR( INDEX( tblStrings[], MATCH( 1, (tblStrings[[Cell]:[Cell]]=AllStrings!$D$350) * (tblStrings[[Sheet]:[Sheet]]=AllStrings!$C$433), 0 ), MATCH(Språkval, tblStrings[#Headers], 0) ), ))} -> Fyll i byggnads- och rumstyp ovan | P82: {=IFERROR(_xlfn.IFS(P$19='4. Reduktionsfaktorer, LENI-tal'!$Q$12,INDEX('4. Reduktionsfaktorer, LENI-tal'!$H$13:$O$23,MATCH(P$21,'4. Reduktionsfaktorer, LENI-tal'!$H$13:$H$23,0),5), P$19='4. Reduktionsfaktorer, LENI-tal'!$R$12,INDEX('4. Reduktionsfaktorer, LENI-tal'!$H$24:$O$32,MATCH(P$21,'4. Reduktionsfaktorer, LENI-tal'!$H$24:$H$32,0),5), P$19='4. Reduktionsfaktorer, LENI-tal'!$S$12,INDEX('4. Reduktionsfaktorer, LENI-tal'!$H$33:$O$37,MATCH(P$21,'4. Reduktionsfaktorer, LENI-tal'!$H$33:$H$37,0),5), P$19='4. Reduktionsfaktorer, LENI-tal'!$T$12,INDEX('4. Reduktionsfaktorer, LENI-tal'!$H$38:$O$45,MATCH(P$21,'4. Reduktionsfaktorer, LENI-tal'!$H$38:$H$45,0),5), P$19='4. Reduktionsfaktorer, LENI-tal'!$U$12,INDEX('4. Reduktionsfaktorer, LENI-tal'!$H$46:$O$54,MATCH(P$21,'4. Reduktionsfaktorer, LENI-tal'!$H$46:$H$54,0),5)), IFERROR( INDEX( tblStrings[], MATCH( 1, (tblStrings[[Cell]:[Cell]]=AllStrings!$D$350) * (tblStrings[[Sheet]:[Sheet]]=AllStrings!$C$433), 0 ), MATCH(Språkval, tblStrings[#Headers], 0) ), ))} -> Fyll i byggnads- och rumstyp ovan | ... R82: {=IFERROR(_xlfn.IFS(R$19='4. Reduktionsfaktorer, LENI-tal'!$Q$12,INDEX('4. Reduktionsfaktorer, LENI-tal'!$H$13:$O$23,MATCH(R$21,'4. Reduktionsfaktorer, LENI-tal'!$H$13:$H$23,0),5), R$19='4. Reduktionsfaktorer, LENI-tal'!$R$12,INDEX('4. Reduktionsfaktorer, LENI-tal'!$H$24:$O$32,MATCH(R$21,'4. Reduktionsfaktorer, LENI-tal'!$H$24:$H$32,0),5), R$19='4. Reduktionsfaktorer, LENI-tal'!$S$12,INDEX('4. Reduktionsfaktorer, LENI-tal'!$H$33:$O$37,MATCH(R$21,'4. Reduktionsfaktorer, LENI-tal'!$H$33:$H$37,0),5), R$19='4. Reduktionsfaktorer, LENI-tal'!$T$12,INDEX('4. Reduktionsfaktorer, LENI-tal'!$H$38:$O$45,MATCH(R$21,'4. Reduktionsfaktorer, LENI-tal'!$H$38:$H$45,0),5), R$19='4. Reduktionsfaktorer, LENI-tal'!$U$12,INDEX('4. Reduktionsfaktorer, LENI-tal'!$H$46:$O$54,MATCH(R$21,'4. Reduktionsfaktorer, LENI-tal'!$H$46:$H$54,0),5)), IFERROR( INDEX( tblStrings[], MATCH( 1, (tblStrings[[Cell]:[Cell]]=AllStrings!$D$350) * (tblStrings[[Sheet]:[Sheet]]=AllStrings!$C$433), 0 ), MATCH(Språkval, tblStrings[#Headers], 0) ), ))} -> Fyll i byggnads- och rumstyp ovan
B83: 2.9 | C83: =$C$35 -> Total reduktionsfaktor för styrning | I83: =IF(IF(I79=$I$233,I80,IF(I79=$I$234,I80*I81,IF(I79=$I$235,I80*I81*I82,1)))=0,"Fyll i 2.6-2.8",IF(I79=$I$233,I80,IF(I79=$I$234,I80*I81,IF(I79=$I$235,I80*I81*I82,1)))) -> 1 | J83: =IF(IF(J79=$I$233,J80,IF(J79=$I$234,J80*J81,IF(J79=$I$235,J80*J81*J82,1)))=0,"Fyll i 2.6-2.8",IF(J79=$I$233,J80,IF(J79=$I$234,J80*J81,IF(J79=$I$235,J80*J81*J82,1)))) -> 1 | K83: =IF(IF(K79=$I$233,K80,IF(K79=$I$234,K80*K81,IF(K79=$I$235,K80*K81*K82,1)))=0,"Fyll i 2.6-2.8",IF(K79=$I$233,K80,IF(K79=$I$234,K80*K81,IF(K79=$I$235,K80*K81*K82,1)))) -> 1 | L83: =IF(IF(L79=$I$233,L80,IF(L79=$I$234,L80*L81,IF(L79=$I$235,L80*L81*L82,1)))=0,"Fyll i 2.6-2.8",IF(L79=$I$233,L80,IF(L79=$I$234,L80*L81,IF(L79=$I$235,L80*L81*L82,1)))) -> 1 | M83: =IF(IF(M79=$I$233,M80,IF(M79=$I$234,M80*M81,IF(M79=$I$235,M80*M81*M82,1)))=0,"Fyll i 2.6-2.8",IF(M79=$I$233,M80,IF(M79=$I$234,M80*M81,IF(M79=$I$235,M80*M81*M82,1)))) -> 1 | N83: =IF(IF(N79=$I$233,N80,IF(N79=$I$234,N80*N81,IF(N79=$I$235,N80*N81*N82,1)))=0,"Fyll i 2.6-2.8",IF(N79=$I$233,N80,IF(N79=$I$234,N80*N81,IF(N79=$I$235,N80*N81*N82,1)))) -> 1 | O83: =IF(IF(O79=$I$233,O80,IF(O79=$I$234,O80*O81,IF(O79=$I$235,O80*O81*O82,1)))=0,"Fyll i 2.6-2.8",IF(O79=$I$233,O80,IF(O79=$I$234,O80*O81,IF(O79=$I$235,O80*O81*O82,1)))) -> 1 | P83: =IF(IF(P79=$I$233,P80,IF(P79=$I$234,P80*P81,IF(P79=$I$235,P80*P81*P82,1)))=0,"Fyll i 2.6-2.8",IF(P79=$I$233,P80,IF(P79=$I$234,P80*P81,IF(P79=$I$235,P80*P81*P82,1)))) -> 1 | ... R83: =IF(IF(R79=$I$233,R80,IF(R79=$I$234,R80*R81,IF(R79=$I$235,R80*R81*R82,1)))=0,"Fyll i 2.6-2.8",IF(R79=$I$233,R80,IF(R79=$I$234,R80*R81,IF(R79=$I$235,R80*R81*R82,1)))) -> 1
B84: 2.10 | C84: =$C$36 -> Underhållskostnader | H84: =$H$36 -> kr/år
C86: =$C$26 -> Armaturbeteckning
B87: 2.1 | C87: =$C$27 -> Antal armaturer | H87: =$H$27 -> stk
B88: 2.2 | C88: =$C$28 -> Armaturpris | H88: =$H$28 -> kr/stk
B89: 2.3 | C89: =$C$29 -> Material- och arbetskostnader armatur | H89: =$H$29 -> kr
B90: 2.4 | C90: =$C$30 -> Effekt per armatur, inkl. driftsförluster | H90: =$H$30 -> W/stk
B91: 2.5 | C91: =$C$31 -> Typ av styrning
B92: 2.6 | C92: =$C80 -> Reduktionsfaktor manuell styrning | I92: {=IFERROR(_xlfn.IFS(I$19='4. Reduktionsfaktorer, LENI-tal'!$Q$12,INDEX('4. Reduktionsfaktorer, LENI-tal'!$H$13:$O$23,MATCH(I$21,'4. Reduktionsfaktorer, LENI-tal'!$H$13:$H$23,0),3), I$19='4. Reduktionsfaktorer, LENI-tal'!$R$12,INDEX('4. Reduktionsfaktorer, LENI-tal'!$H$24:$O$32,MATCH(I$21,'4. Reduktionsfaktorer, LENI-tal'!$H$24:$H$32,0),3), I$19='4. Reduktionsfaktorer, LENI-tal'!$S$12,INDEX('4. Reduktionsfaktorer, LENI-tal'!$H$33:$O$37,MATCH(I$21,'4. Reduktionsfaktorer, LENI-tal'!$H$33:$H$37,0),3), I$19='4. Reduktionsfaktorer, LENI-tal'!$T$12,INDEX('4. Reduktionsfaktorer, LENI-tal'!$H$38:$O$45,MATCH(I$21,'4. Reduktionsfaktorer, LENI-tal'!$H$38:$H$45,0),3), I$19='4. Reduktionsfaktorer, LENI-tal'!$U$12,INDEX('4. Reduktionsfaktorer, LENI-tal'!$H$46:$O$54,MATCH(I$21,'4. Reduktionsfaktorer, LENI-tal'!$H$46:$H$54,0),3)), IFERROR( INDEX( tblStrings[], MATCH( 1, (tblStrings[[Cell]:[Cell]]=AllStrings!$D$350) * (tblStrings[[Sheet]:[Sheet]]=AllStrings!$C$433), 0 ), MATCH(Språkval, tblStrings[#Headers], 0) ), ))} -> Fyll i byggnads- och rumstyp ovan | J92: {=IFERROR(_xlfn.IFS(J$19='4. Reduktionsfaktorer, LENI-tal'!$Q$12,INDEX('4. Reduktionsfaktorer, LENI-tal'!$H$13:$O$23,MATCH(J$21,'4. Reduktionsfaktorer, LENI-tal'!$H$13:$H$23,0),3), J$19='4. Reduktionsfaktorer, LENI-tal'!$R$12,INDEX('4. Reduktionsfaktorer, LENI-tal'!$H$24:$O$32,MATCH(J$21,'4. Reduktionsfaktorer, LENI-tal'!$H$24:$H$32,0),3), J$19='4. Reduktionsfaktorer, LENI-tal'!$S$12,INDEX('4. Reduktionsfaktorer, LENI-tal'!$H$33:$O$37,MATCH(J$21,'4. Reduktionsfaktorer, LENI-tal'!$H$33:$H$37,0),3), J$19='4. Reduktionsfaktorer, LENI-tal'!$T$12,INDEX('4. Reduktionsfaktorer, LENI-tal'!$H$38:$O$45,MATCH(J$21,'4. Reduktionsfaktorer, LENI-tal'!$H$38:$H$45,0),3), J$19='4. Reduktionsfaktorer, LENI-tal'!$U$12,INDEX('4. Reduktionsfaktorer, LENI-tal'!$H$46:$O$54,MATCH(J$21,'4. Reduktionsfaktorer, LENI-tal'!$H$46:$H$54,0),3)), IFERROR( INDEX( tblStrings[], MATCH( 1, (tblStrings[[Cell]:[Cell]]=AllStrings!$D$350) * (tblStrings[[Sheet]:[Sheet]]=AllStrings!$C$433), 0 ), MATCH(Språkval, tblStrings[#Headers], 0) ), ))} -> Fyll i byggnads- och rumstyp ovan | K92: {=IFERROR(_xlfn.IFS(K$19='4. Reduktionsfaktorer, LENI-tal'!$Q$12,INDEX('4. Reduktionsfaktorer, LENI-tal'!$H$13:$O$23,MATCH(K$21,'4. Reduktionsfaktorer, LENI-tal'!$H$13:$H$23,0),3), K$19='4. Reduktionsfaktorer, LENI-tal'!$R$12,INDEX('4. Reduktionsfaktorer, LENI-tal'!$H$24:$O$32,MATCH(K$21,'4. Reduktionsfaktorer, LENI-tal'!$H$24:$H$32,0),3), K$19='4. Reduktionsfaktorer, LENI-tal'!$S$12,INDEX('4. Reduktionsfaktorer, LENI-tal'!$H$33:$O$37,MATCH(K$21,'4. Reduktionsfaktorer, LENI-tal'!$H$33:$H$37,0),3), K$19='4. Reduktionsfaktorer, LENI-tal'!$T$12,INDEX('4. Reduktionsfaktorer, LENI-tal'!$H$38:$O$45,MATCH(K$21,'4. Reduktionsfaktorer, LENI-tal'!$H$38:$H$45,0),3), K$19='4. Reduktionsfaktorer, LENI-tal'!$U$12,INDEX('4. Reduktionsfaktorer, LENI-tal'!$H$46:$O$54,MATCH(K$21,'4. Reduktionsfaktorer, LENI-tal'!$H$46:$H$54,0),3)), IFERROR( INDEX( tblStrings[], MATCH( 1, (tblStrings[[Cell]:[Cell]]=AllStrings!$D$350) * (tblStrings[[Sheet]:[Sheet]]=AllStrings!$C$433), 0 ), MATCH(Språkval, tblStrings[#Headers], 0) ), ))} -> Fyll i byggnads- och rumstyp ovan | L92: {=IFERROR(_xlfn.IFS(L$19='4. Reduktionsfaktorer, LENI-tal'!$Q$12,INDEX('4. Reduktionsfaktorer, LENI-tal'!$H$13:$O$23,MATCH(L$21,'4. Reduktionsfaktorer, LENI-tal'!$H$13:$H$23,0),3), L$19='4. Reduktionsfaktorer, LENI-tal'!$R$12,INDEX('4. Reduktionsfaktorer, LENI-tal'!$H$24:$O$32,MATCH(L$21,'4. Reduktionsfaktorer, LENI-tal'!$H$24:$H$32,0),3), L$19='4. Reduktionsfaktorer, LENI-tal'!$S$12,INDEX('4. Reduktionsfaktorer, LENI-tal'!$H$33:$O$37,MATCH(L$21,'4. Reduktionsfaktorer, LENI-tal'!$H$33:$H$37,0),3), L$19='4. Reduktionsfaktorer, LENI-tal'!$T$12,INDEX('4. Reduktionsfaktorer, LENI-tal'!$H$38:$O$45,MATCH(L$21,'4. Reduktionsfaktorer, LENI-tal'!$H$38:$H$45,0),3), L$19='4. Reduktionsfaktorer, LENI-tal'!$U$12,INDEX('4. Reduktionsfaktorer, LENI-tal'!$H$46:$O$54,MATCH(L$21,'4. Reduktionsfaktorer, LENI-tal'!$H$46:$H$54,0),3)), IFERROR( INDEX( tblStrings[], MATCH( 1, (tblStrings[[Cell]:[Cell]]=AllStrings!$D$350) * (tblStrings[[Sheet]:[Sheet]]=AllStrings!$C$433), 0 ), MATCH(Språkval, tblStrings[#Headers], 0) ), ))} -> Fyll i byggnads- och rumstyp ovan | M92: {=IFERROR(_xlfn.IFS(M$19='4. Reduktionsfaktorer, LENI-tal'!$Q$12,INDEX('4. Reduktionsfaktorer, LENI-tal'!$H$13:$O$23,MATCH(M$21,'4. Reduktionsfaktorer, LENI-tal'!$H$13:$H$23,0),3), M$19='4. Reduktionsfaktorer, LENI-tal'!$R$12,INDEX('4. Reduktionsfaktorer, LENI-tal'!$H$24:$O$32,MATCH(M$21,'4. Reduktionsfaktorer, LENI-tal'!$H$24:$H$32,0),3), M$19='4. Reduktionsfaktorer, LENI-tal'!$S$12,INDEX('4. Reduktionsfaktorer, LENI-tal'!$H$33:$O$37,MATCH(M$21,'4. Reduktionsfaktorer, LENI-tal'!$H$33:$H$37,0),3), M$19='4. Reduktionsfaktorer, LENI-tal'!$T$12,INDEX('4. Reduktionsfaktorer, LENI-tal'!$H$38:$O$45,MATCH(M$21,'4. Reduktionsfaktorer, LENI-tal'!$H$38:$H$45,0),3), M$19='4. Reduktionsfaktorer, LENI-tal'!$U$12,INDEX('4. Reduktionsfaktorer, LENI-tal'!$H$46:$O$54,MATCH(M$21,'4. Reduktionsfaktorer, LENI-tal'!$H$46:$H$54,0),3)), IFERROR( INDEX( tblStrings[], MATCH( 1, (tblStrings[[Cell]:[Cell]]=AllStrings!$D$350) * (tblStrings[[Sheet]:[Sheet]]=AllStrings!$C$433), 0 ), MATCH(Språkval, tblStrings[#Headers], 0) ), ))} -> Fyll i byggnads- och rumstyp ovan | N92: {=IFERROR(_xlfn.IFS(N$19='4. Reduktionsfaktorer, LENI-tal'!$Q$12,INDEX('4. Reduktionsfaktorer, LENI-tal'!$H$13:$O$23,MATCH(N$21,'4. Reduktionsfaktorer, LENI-tal'!$H$13:$H$23,0),3), N$19='4. Reduktionsfaktorer, LENI-tal'!$R$12,INDEX('4. Reduktionsfaktorer, LENI-tal'!$H$24:$O$32,MATCH(N$21,'4. Reduktionsfaktorer, LENI-tal'!$H$24:$H$32,0),3), N$19='4. Reduktionsfaktorer, LENI-tal'!$S$12,INDEX('4. Reduktionsfaktorer, LENI-tal'!$H$33:$O$37,MATCH(N$21,'4. Reduktionsfaktorer, LENI-tal'!$H$33:$H$37,0),3), N$19='4. Reduktionsfaktorer, LENI-tal'!$T$12,INDEX('4. Reduktionsfaktorer, LENI-tal'!$H$38:$O$45,MATCH(N$21,'4. Reduktionsfaktorer, LENI-tal'!$H$38:$H$45,0),3), N$19='4. Reduktionsfaktorer, LENI-tal'!$U$12,INDEX('4. Reduktionsfaktorer, LENI-tal'!$H$46:$O$54,MATCH(N$21,'4. Reduktionsfaktorer, LENI-tal'!$H$46:$H$54,0),3)), IFERROR( INDEX( tblStrings[], MATCH( 1, (tblStrings[[Cell]:[Cell]]=AllStrings!$D$350) * (tblStrings[[Sheet]:[Sheet]]=AllStrings!$C$433), 0 ), MATCH(Språkval, tblStrings[#Headers], 0) ), ))} -> Fyll i byggnads- och rumstyp ovan | O92: {=IFERROR(_xlfn.IFS(O$19='4. Reduktionsfaktorer, LENI-tal'!$Q$12,INDEX('4. Reduktionsfaktorer, LENI-tal'!$H$13:$O$23,MATCH(O$21,'4. Reduktionsfaktorer, LENI-tal'!$H$13:$H$23,0),3), O$19='4. Reduktionsfaktorer, LENI-tal'!$R$12,INDEX('4. Reduktionsfaktorer, LENI-tal'!$H$24:$O$32,MATCH(O$21,'4. Reduktionsfaktorer, LENI-tal'!$H$24:$H$32,0),3), O$19='4. Reduktionsfaktorer, LENI-tal'!$S$12,INDEX('4. Reduktionsfaktorer, LENI-tal'!$H$33:$O$37,MATCH(O$21,'4. Reduktionsfaktorer, LENI-tal'!$H$33:$H$37,0),3), O$19='4. Reduktionsfaktorer, LENI-tal'!$T$12,INDEX('4. Reduktionsfaktorer, LENI-tal'!$H$38:$O$45,MATCH(O$21,'4. Reduktionsfaktorer, LENI-tal'!$H$38:$H$45,0),3), O$19='4. Reduktionsfaktorer, LENI-tal'!$U$12,INDEX('4. Reduktionsfaktorer, LENI-tal'!$H$46:$O$54,MATCH(O$21,'4. Reduktionsfaktorer, LENI-tal'!$H$46:$H$54,0),3)), IFERROR( INDEX( tblStrings[], MATCH( 1, (tblStrings[[Cell]:[Cell]]=AllStrings!$D$350) * (tblStrings[[Sheet]:[Sheet]]=AllStrings!$C$433), 0 ), MATCH(Språkval, tblStrings[#Headers], 0) ), ))} -> Fyll i byggnads- och rumstyp ovan | P92: {=IFERROR(_xlfn.IFS(P$19='4. Reduktionsfaktorer, LENI-tal'!$Q$12,INDEX('4. Reduktionsfaktorer, LENI-tal'!$H$13:$O$23,MATCH(P$21,'4. Reduktionsfaktorer, LENI-tal'!$H$13:$H$23,0),3), P$19='4. Reduktionsfaktorer, LENI-tal'!$R$12,INDEX('4. Reduktionsfaktorer, LENI-tal'!$H$24:$O$32,MATCH(P$21,'4. Reduktionsfaktorer, LENI-tal'!$H$24:$H$32,0),3), P$19='4. Reduktionsfaktorer, LENI-tal'!$S$12,INDEX('4. Reduktionsfaktorer, LENI-tal'!$H$33:$O$37,MATCH(P$21,'4. Reduktionsfaktorer, LENI-tal'!$H$33:$H$37,0),3), P$19='4. Reduktionsfaktorer, LENI-tal'!$T$12,INDEX('4. Reduktionsfaktorer, LENI-tal'!$H$38:$O$45,MATCH(P$21,'4. Reduktionsfaktorer, LENI-tal'!$H$38:$H$45,0),3), P$19='4. Reduktionsfaktorer, LENI-tal'!$U$12,INDEX('4. Reduktionsfaktorer, LENI-tal'!$H$46:$O$54,MATCH(P$21,'4. Reduktionsfaktorer, LENI-tal'!$H$46:$H$54,0),3)), IFERROR( INDEX( tblStrings[], MATCH( 1, (tblStrings[[Cell]:[Cell]]=AllStrings!$D$350) * (tblStrings[[Sheet]:[Sheet]]=AllStrings!$C$433), 0 ), MATCH(Språkval, tblStrings[#Headers], 0) ), ))} -> Fyll i byggnads- och rumstyp ovan | ... R92: {=IFERROR(_xlfn.IFS(R$19='4. Reduktionsfaktorer, LENI-tal'!$Q$12,INDEX('4. Reduktionsfaktorer, LENI-tal'!$H$13:$O$23,MATCH(R$21,'4. Reduktionsfaktorer, LENI-tal'!$H$13:$H$23,0),3), R$19='4. Reduktionsfaktorer, LENI-tal'!$R$12,INDEX('4. Reduktionsfaktorer, LENI-tal'!$H$24:$O$32,MATCH(R$21,'4. Reduktionsfaktorer, LENI-tal'!$H$24:$H$32,0),3), R$19='4. Reduktionsfaktorer, LENI-tal'!$S$12,INDEX('4. Reduktionsfaktorer, LENI-tal'!$H$33:$O$37,MATCH(R$21,'4. Reduktionsfaktorer, LENI-tal'!$H$33:$H$37,0),3), R$19='4. Reduktionsfaktorer, LENI-tal'!$T$12,INDEX('4. Reduktionsfaktorer, LENI-tal'!$H$38:$O$45,MATCH(R$21,'4. Reduktionsfaktorer, LENI-tal'!$H$38:$H$45,0),3), R$19='4. Reduktionsfaktorer, LENI-tal'!$U$12,INDEX('4. Reduktionsfaktorer, LENI-tal'!$H$46:$O$54,MATCH(R$21,'4. Reduktionsfaktorer, LENI-tal'!$H$46:$H$54,0),3)), IFERROR( INDEX( tblStrings[], MATCH( 1, (tblStrings[[Cell]:[Cell]]=AllStrings!$D$350) * (tblStrings[[Sheet]:[Sheet]]=AllStrings!$C$433), 0 ), MATCH(Språkval, tblStrings[#Headers], 0) ), ))} -> Fyll i byggnads- och rumstyp ovan
B93: 2.7 | C93: =$C81 -> Reduktionsfaktor närvaro-/frånvarostyrning | I93: {=IFERROR(_xlfn.IFS(I$19='4. Reduktionsfaktorer, LENI-tal'!$Q$12,INDEX('4. Reduktionsfaktorer, LENI-tal'!$H$13:$O$23,MATCH(I$21,'4. Reduktionsfaktorer, LENI-tal'!$H$13:$H$23,0),4), I$19='4. Reduktionsfaktorer, LENI-tal'!$R$12,INDEX('4. Reduktionsfaktorer, LENI-tal'!$H$24:$O$32,MATCH(I$21,'4. Reduktionsfaktorer, LENI-tal'!$H$24:$H$32,0),4), I$19='4. Reduktionsfaktorer, LENI-tal'!$S$12,INDEX('4. Reduktionsfaktorer, LENI-tal'!$H$33:$O$37,MATCH(I$21,'4. Reduktionsfaktorer, LENI-tal'!$H$33:$H$37,0),4), I$19='4. Reduktionsfaktorer, LENI-tal'!$T$12,INDEX('4. Reduktionsfaktorer, LENI-tal'!$H$38:$O$45,MATCH(I$21,'4. Reduktionsfaktorer, LENI-tal'!$H$38:$H$45,0),4), I$19='4. Reduktionsfaktorer, LENI-tal'!$U$12,INDEX('4. Reduktionsfaktorer, LENI-tal'!$H$46:$O$54,MATCH(I$21,'4. Reduktionsfaktorer, LENI-tal'!$H$46:$H$54,0),4)), IFERROR( INDEX( tblStrings[], MATCH( 1, (tblStrings[[Cell]:[Cell]]=AllStrings!$D$350) * (tblStrings[[Sheet]:[Sheet]]=AllStrings!$C$433), 0 ), MATCH(Språkval, tblStrings[#Headers], 0) ), ))} -> Fyll i byggnads- och rumstyp ovan | J93: {=IFERROR(_xlfn.IFS(J$19='4. Reduktionsfaktorer, LENI-tal'!$Q$12,INDEX('4. Reduktionsfaktorer, LENI-tal'!$H$13:$O$23,MATCH(J$21,'4. Reduktionsfaktorer, LENI-tal'!$H$13:$H$23,0),4), J$19='4. Reduktionsfaktorer, LENI-tal'!$R$12,INDEX('4. Reduktionsfaktorer, LENI-tal'!$H$24:$O$32,MATCH(J$21,'4. Reduktionsfaktorer, LENI-tal'!$H$24:$H$32,0),4), J$19='4. Reduktionsfaktorer, LENI-tal'!$S$12,INDEX('4. Reduktionsfaktorer, LENI-tal'!$H$33:$O$37,MATCH(J$21,'4. Reduktionsfaktorer, LENI-tal'!$H$33:$H$37,0),4), J$19='4. Reduktionsfaktorer, LENI-tal'!$T$12,INDEX('4. Reduktionsfaktorer, LENI-tal'!$H$38:$O$45,MATCH(J$21,'4. Reduktionsfaktorer, LENI-tal'!$H$38:$H$45,0),4), J$19='4. Reduktionsfaktorer, LENI-tal'!$U$12,INDEX('4. Reduktionsfaktorer, LENI-tal'!$H$46:$O$54,MATCH(J$21,'4. Reduktionsfaktorer, LENI-tal'!$H$46:$H$54,0),4)), IFERROR( INDEX( tblStrings[], MATCH( 1, (tblStrings[[Cell]:[Cell]]=AllStrings!$D$350) * (tblStrings[[Sheet]:[Sheet]]=AllStrings!$C$433), 0 ), MATCH(Språkval, tblStrings[#Headers], 0) ), ))} -> Fyll i byggnads- och rumstyp ovan | K93: {=IFERROR(_xlfn.IFS(K$19='4. Reduktionsfaktorer, LENI-tal'!$Q$12,INDEX('4. Reduktionsfaktorer, LENI-tal'!$H$13:$O$23,MATCH(K$21,'4. Reduktionsfaktorer, LENI-tal'!$H$13:$H$23,0),4), K$19='4. Reduktionsfaktorer, LENI-tal'!$R$12,INDEX('4. Reduktionsfaktorer, LENI-tal'!$H$24:$O$32,MATCH(K$21,'4. Reduktionsfaktorer, LENI-tal'!$H$24:$H$32,0),4), K$19='4. Reduktionsfaktorer, LENI-tal'!$S$12,INDEX('4. Reduktionsfaktorer, LENI-tal'!$H$33:$O$37,MATCH(K$21,'4. Reduktionsfaktorer, LENI-tal'!$H$33:$H$37,0),4), K$19='4. Reduktionsfaktorer, LENI-tal'!$T$12,INDEX('4. Reduktionsfaktorer, LENI-tal'!$H$38:$O$45,MATCH(K$21,'4. Reduktionsfaktorer, LENI-tal'!$H$38:$H$45,0),4), K$19='4. Reduktionsfaktorer, LENI-tal'!$U$12,INDEX('4. Reduktionsfaktorer, LENI-tal'!$H$46:$O$54,MATCH(K$21,'4. Reduktionsfaktorer, LENI-tal'!$H$46:$H$54,0),4)), IFERROR( INDEX( tblStrings[], MATCH( 1, (tblStrings[[Cell]:[Cell]]=AllStrings!$D$350) * (tblStrings[[Sheet]:[Sheet]]=AllStrings!$C$433), 0 ), MATCH(Språkval, tblStrings[#Headers], 0) ), ))} -> Fyll i byggnads- och rumstyp ovan | L93: {=IFERROR(_xlfn.IFS(L$19='4. Reduktionsfaktorer, LENI-tal'!$Q$12,INDEX('4. Reduktionsfaktorer, LENI-tal'!$H$13:$O$23,MATCH(L$21,'4. Reduktionsfaktorer, LENI-tal'!$H$13:$H$23,0),4), L$19='4. Reduktionsfaktorer, LENI-tal'!$R$12,INDEX('4. Reduktionsfaktorer, LENI-tal'!$H$24:$O$32,MATCH(L$21,'4. Reduktionsfaktorer, LENI-tal'!$H$24:$H$32,0),4), L$19='4. Reduktionsfaktorer, LENI-tal'!$S$12,INDEX('4. Reduktionsfaktorer, LENI-tal'!$H$33:$O$37,MATCH(L$21,'4. Reduktionsfaktorer, LENI-tal'!$H$33:$H$37,0),4), L$19='4. Reduktionsfaktorer, LENI-tal'!$T$12,INDEX('4. Reduktionsfaktorer, LENI-tal'!$H$38:$O$45,MATCH(L$21,'4. Reduktionsfaktorer, LENI-tal'!$H$38:$H$45,0),4), L$19='4. Reduktionsfaktorer, LENI-tal'!$U$12,INDEX('4. Reduktionsfaktorer, LENI-tal'!$H$46:$O$54,MATCH(L$21,'4. Reduktionsfaktorer, LENI-tal'!$H$46:$H$54,0),4)), IFERROR( INDEX( tblStrings[], MATCH( 1, (tblStrings[[Cell]:[Cell]]=AllStrings!$D$350) * (tblStrings[[Sheet]:[Sheet]]=AllStrings!$C$433), 0 ), MATCH(Språkval, tblStrings[#Headers], 0) ), ))} -> Fyll i byggnads- och rumstyp ovan | M93: {=IFERROR(_xlfn.IFS(M$19='4. Reduktionsfaktorer, LENI-tal'!$Q$12,INDEX('4. Reduktionsfaktorer, LENI-tal'!$H$13:$O$23,MATCH(M$21,'4. Reduktionsfaktorer, LENI-tal'!$H$13:$H$23,0),4), M$19='4. Reduktionsfaktorer, LENI-tal'!$R$12,INDEX('4. Reduktionsfaktorer, LENI-tal'!$H$24:$O$32,MATCH(M$21,'4. Reduktionsfaktorer, LENI-tal'!$H$24:$H$32,0),4), M$19='4. Reduktionsfaktorer, LENI-tal'!$S$12,INDEX('4. Reduktionsfaktorer, LENI-tal'!$H$33:$O$37,MATCH(M$21,'4. Reduktionsfaktorer, LENI-tal'!$H$33:$H$37,0),4), M$19='4. Reduktionsfaktorer, LENI-tal'!$T$12,INDEX('4. Reduktionsfaktorer, LENI-tal'!$H$38:$O$45,MATCH(M$21,'4. Reduktionsfaktorer, LENI-tal'!$H$38:$H$45,0),4), M$19='4. Reduktionsfaktorer, LENI-tal'!$U$12,INDEX('4. Reduktionsfaktorer, LENI-tal'!$H$46:$O$54,MATCH(M$21,'4. Reduktionsfaktorer, LENI-tal'!$H$46:$H$54,0),4)), IFERROR( INDEX( tblStrings[], MATCH( 1, (tblStrings[[Cell]:[Cell]]=AllStrings!$D$350) * (tblStrings[[Sheet]:[Sheet]]=AllStrings!$C$433), 0 ), MATCH(Språkval, tblStrings[#Headers], 0) ), ))} -> Fyll i byggnads- och rumstyp ovan | N93: {=IFERROR(_xlfn.IFS(N$19='4. Reduktionsfaktorer, LENI-tal'!$Q$12,INDEX('4. Reduktionsfaktorer, LENI-tal'!$H$13:$O$23,MATCH(N$21,'4. Reduktionsfaktorer, LENI-tal'!$H$13:$H$23,0),4), N$19='4. Reduktionsfaktorer, LENI-tal'!$R$12,INDEX('4. Reduktionsfaktorer, LENI-tal'!$H$24:$O$32,MATCH(N$21,'4. Reduktionsfaktorer, LENI-tal'!$H$24:$H$32,0),4), N$19='4. Reduktionsfaktorer, LENI-tal'!$S$12,INDEX('4. Reduktionsfaktorer, LENI-tal'!$H$33:$O$37,MATCH(N$21,'4. Reduktionsfaktorer, LENI-tal'!$H$33:$H$37,0),4), N$19='4. Reduktionsfaktorer, LENI-tal'!$T$12,INDEX('4. Reduktionsfaktorer, LENI-tal'!$H$38:$O$45,MATCH(N$21,'4. Reduktionsfaktorer, LENI-tal'!$H$38:$H$45,0),4), N$19='4. Reduktionsfaktorer, LENI-tal'!$U$12,INDEX('4. Reduktionsfaktorer, LENI-tal'!$H$46:$O$54,MATCH(N$21,'4. Reduktionsfaktorer, LENI-tal'!$H$46:$H$54,0),4)), IFERROR( INDEX( tblStrings[], MATCH( 1, (tblStrings[[Cell]:[Cell]]=AllStrings!$D$350) * (tblStrings[[Sheet]:[Sheet]]=AllStrings!$C$433), 0 ), MATCH(Språkval, tblStrings[#Headers], 0) ), ))} -> Fyll i byggnads- och rumstyp ovan | O93: {=IFERROR(_xlfn.IFS(O$19='4. Reduktionsfaktorer, LENI-tal'!$Q$12,INDEX('4. Reduktionsfaktorer, LENI-tal'!$H$13:$O$23,MATCH(O$21,'4. Reduktionsfaktorer, LENI-tal'!$H$13:$H$23,0),4), O$19='4. Reduktionsfaktorer, LENI-tal'!$R$12,INDEX('4. Reduktionsfaktorer, LENI-tal'!$H$24:$O$32,MATCH(O$21,'4. Reduktionsfaktorer, LENI-tal'!$H$24:$H$32,0),4), O$19='4. Reduktionsfaktorer, LENI-tal'!$S$12,INDEX('4. Reduktionsfaktorer, LENI-tal'!$H$33:$O$37,MATCH(O$21,'4. Reduktionsfaktorer, LENI-tal'!$H$33:$H$37,0),4), O$19='4. Reduktionsfaktorer, LENI-tal'!$T$12,INDEX('4. Reduktionsfaktorer, LENI-tal'!$H$38:$O$45,MATCH(O$21,'4. Reduktionsfaktorer, LENI-tal'!$H$38:$H$45,0),4), O$19='4. Reduktionsfaktorer, LENI-tal'!$U$12,INDEX('4. Reduktionsfaktorer, LENI-tal'!$H$46:$O$54,MATCH(O$21,'4. Reduktionsfaktorer, LENI-tal'!$H$46:$H$54,0),4)), IFERROR( INDEX( tblStrings[], MATCH( 1, (tblStrings[[Cell]:[Cell]]=AllStrings!$D$350) * (tblStrings[[Sheet]:[Sheet]]=AllStrings!$C$433), 0 ), MATCH(Språkval, tblStrings[#Headers], 0) ), ))} -> Fyll i byggnads- och rumstyp ovan | P93: {=IFERROR(_xlfn.IFS(P$19='4. Reduktionsfaktorer, LENI-tal'!$Q$12,INDEX('4. Reduktionsfaktorer, LENI-tal'!$H$13:$O$23,MATCH(P$21,'4. Reduktionsfaktorer, LENI-tal'!$H$13:$H$23,0),4), P$19='4. Reduktionsfaktorer, LENI-tal'!$R$12,INDEX('4. Reduktionsfaktorer, LENI-tal'!$H$24:$O$32,MATCH(P$21,'4. Reduktionsfaktorer, LENI-tal'!$H$24:$H$32,0),4), P$19='4. Reduktionsfaktorer, LENI-tal'!$S$12,INDEX('4. Reduktionsfaktorer, LENI-tal'!$H$33:$O$37,MATCH(P$21,'4. Reduktionsfaktorer, LENI-tal'!$H$33:$H$37,0),4), P$19='4. Reduktionsfaktorer, LENI-tal'!$T$12,INDEX('4. Reduktionsfaktorer, LENI-tal'!$H$38:$O$45,MATCH(P$21,'4. Reduktionsfaktorer, LENI-tal'!$H$38:$H$45,0),4), P$19='4. Reduktionsfaktorer, LENI-tal'!$U$12,INDEX('4. Reduktionsfaktorer, LENI-tal'!$H$46:$O$54,MATCH(P$21,'4. Reduktionsfaktorer, LENI-tal'!$H$46:$H$54,0),4)), IFERROR( INDEX( tblStrings[], MATCH( 1, (tblStrings[[Cell]:[Cell]]=AllStrings!$D$350) * (tblStrings[[Sheet]:[Sheet]]=AllStrings!$C$433), 0 ), MATCH(Språkval, tblStrings[#Headers], 0) ), ))} -> Fyll i byggnads- och rumstyp ovan | ... R93: {=IFERROR(_xlfn.IFS(R$19='4. Reduktionsfaktorer, LENI-tal'!$Q$12,INDEX('4. Reduktionsfaktorer, LENI-tal'!$H$13:$O$23,MATCH(R$21,'4. Reduktionsfaktorer, LENI-tal'!$H$13:$H$23,0),4), R$19='4. Reduktionsfaktorer, LENI-tal'!$R$12,INDEX('4. Reduktionsfaktorer, LENI-tal'!$H$24:$O$32,MATCH(R$21,'4. Reduktionsfaktorer, LENI-tal'!$H$24:$H$32,0),4), R$19='4. Reduktionsfaktorer, LENI-tal'!$S$12,INDEX('4. Reduktionsfaktorer, LENI-tal'!$H$33:$O$37,MATCH(R$21,'4. Reduktionsfaktorer, LENI-tal'!$H$33:$H$37,0),4), R$19='4. Reduktionsfaktorer, LENI-tal'!$T$12,INDEX('4. Reduktionsfaktorer, LENI-tal'!$H$38:$O$45,MATCH(R$21,'4. Reduktionsfaktorer, LENI-tal'!$H$38:$H$45,0),4), R$19='4. Reduktionsfaktorer, LENI-tal'!$U$12,INDEX('4. Reduktionsfaktorer, LENI-tal'!$H$46:$O$54,MATCH(R$21,'4. Reduktionsfaktorer, LENI-tal'!$H$46:$H$54,0),4)), IFERROR( INDEX( tblStrings[], MATCH( 1, (tblStrings[[Cell]:[Cell]]=AllStrings!$D$350) * (tblStrings[[Sheet]:[Sheet]]=AllStrings!$C$433), 0 ), MATCH(Språkval, tblStrings[#Headers], 0) ), ))} -> Fyll i byggnads- och rumstyp ovan
